Workbook

Sheet 参数
A1: 参数（可改）
A2: 美元兑人民币汇率 (USD→CNY) | B2: 6.683751 | C2: ← 主表「汇率」列全部引用此格
A3: 更新日期/来源时间 | B3: Tue, 27 Oct 2026 00:02:31 +0000
A4: 数据来源 | B4: https://open.er-api.com/v6/latest/USD
A5: 说明 | B5: 每日运行「更新汇率.py」自动刷新；也可手动改 B2。
A7: 汇率请运行 更新汇率.py，或手动改 B2（勿用 WEBSERVICE）
A9: 固定费率默认
A10: 佣金率 | B10: 0.15 | C10: 主表 I–L 已按此写入，可按行单独改
A11: 退款率 | B11: 0.07
A12: 广告率 | B12: 0.15
A13: 提现费率 | B13: 0.01
A15: 地毯采购单价(RMB/㎡) | B15: 19 | C15: 主表 U 列已固定为19；改这里后请同步改主表U列，或改主表U为 =参数!$B$15
A16: 目标利润率(利润售价) | B16: 0.3 | C16: 利润售价按此利润率反推（含退税口径）
A17: 保本口径 | B17: 利润(售价+退税-总成本)≥0，售价ROUNDUP到分
A18: 必填项 | B18: 尺寸(C) + 起运地(BE) + FBA仓(BF)；渠道(BH)可空=自动最低价；竞品售价不用填
A19: 费用口径 | B19: 全部按「一件」：头程=单箱运费÷装数；FBA按单件净重；采购按单件面积×19
A20: 装数来源 | B20: 箱规「装箱数（件）」
A21: FBA规则 | B21: 美站2025非旺季家居口径，详见「FBA规则」表；可改该表费率参数
A22: 预计发货/出库日期 | B22: 46322 | C22: ← 改这个日期，FBA自动切换旺季/非旺季费率
A23: 当前季节 | B23: =IF(B22="","",IF(OR(AND(MONTH(B22)=10,DAY(B22)>=15),MONTH(B22)=11,MONTH(B22)=12,AND(MONTH(B22)=1,DAY(B22)<=14)),"旺季","非旺季")) | C23: 旺季：每年10/15–次年1/14（美站FBA假日旺季）
A24: 旺季开始(月-日) | B24: 10-15
A25: 旺季结束(月-日) | B25: 01-14
A26: 说明 | B26: 费用按「货件离开运营中心」日期计；填预计出库日即可估算

Sheet FBA规则
A1: Amazon美国站 FBA 配送费规则（非服装鞋靴·按发货日判旺季/非旺季）
A2: 主表发货日期在「参数!B22」。旺季=每年10/15–1/14。计费重→尺寸段→按季节查费率。
A4: 换算与计费重
A5: cm→inch | B5: 2.54
A6: kg→lb | B6: 2.2046226
A7: 抛重除数(inch³/lb) | B7: 139
A8: 计费重 | B8: MAX(实重lb, 抛重lb)；小标准件费用只用实重
A9: 围长相关 | B9: 长+围长 = 最长边 + 2×(中边+短边)
A11: 尺寸分段判定（同时满足才落入该段；从上到下先匹配小标准→大标准→大件→超大）
A12: 分段 | B12: 计费重上限(lb) | C12: 最长边(in) | D12: 中边(in) | E12: 最短边(in) | F12: 长+围长(in) | G12: 说明
A13: 小标准 Small Standard | B13: 1 | C13: 15 | D13: 12 | E13: 0.75 | G13: ≤16oz；费用按实重oz
A14: 大标准 Large Standard | B14: 20 | C14: 18 | D14: 14 | E14: 8 | G14: 最常见；计费重=max(实重,抛重)
A15: 大件 Large Bulky | B15: 50 | C15: 59 | D15: 33 | E15: 33 | F15: 130 | G15: 超标准尺寸但仍在大件限内
A16: 超大XL 0-50lb | B16: 50 | G16: 超出大件任一边/围长/或计费重逻辑
A17: 超大XL 50-70lb | B17: 70 | G17: 计费重>50且≤70
A18: 超大XL 70-150lb | B18: 150 | G18: 计费重>70且≤150
A19: 超大XL 150lb+ | G19: 计费重>150
A22: 配送费（USD/件，非旺季）
A23: 分段 | B23: 计费重条件 | C23: 费用公式 | D23: 备注
A24: 小标准 | B24: ≤16 oz 分档 | C24: 见右侧小标准表 / 或简化≈3.06~3.65 | D24: 地毯一般不会落入
A25: 大标准 | B25: ≤3 lb 分档；>3 lb | C25: ≤3lb查表；>3lb：6.92+0.08×每4oz(向上) | D25: 家居常见
A26: 大件 Large Bulky | B26: 任意 | C26: 9.61+0.38×(计费重lb-1)（按lb向上取整间隔） | D26: 超尺寸常用
A27: 超大 0-50 | B27: ≤50 | C27: 26.33+0.38×(计费重-1)
A28: 超大 50-70 | B28: 50+~70 | C28: 40.12+0.75×(计费重-51)
A29: 超大 70-150 | B29: 70+~150 | C29: 54.81+0.75×(计费重-71)
A30: 超大 150+ | B30: >150 | C30: 194.95+0.19×(计费重-151)
A33: 大标准费用档（计费重lb上限 → 非旺季 / 旺季）
A34: 上限lb | B34: 非旺季USD | C34: 旺季USD
A35: 0.25 | B35: 3.68 | C35: 3.92
A36: 0.5 | B36: 3.9 | C36: 4.16
A37: 0.75 | B37: 4.15 | C37: 4.43
A38: 1 | B38: 4.55 | C38: 4.84
A39: 1.25 | B39: 4.99 | C39: 5.29
A40: 1.5 | B40: 5.37 | C40: 5.68
A41: 1.75 | B41: 5.52 | C41: 5.84
A42: 2 | B42: 5.77 | C42: 6.1
A43: 2.25 | B43: 5.87 | C43: 6.24
A44: 2.5 | B44: 6.05 | C44: 6.44
A45: 2.75 | B45: 6.21 | C45: 6.61
A46: 3 | B46: 6.62 | C46: 7.03
A47: 大标准>3lb | B47: 6.92 | C47: 7.46 | D47: 0.08 | E47: B非旺季基数 / C旺季基数 / D每4oz
A49: 大件/超大参数（B非旺季基数 C旺季基数 D每lb增量）
A50: 大件 Large Bulky | B50: 9.61 | C50: 10.65 | D50: 0.38
A51: 超大0-50lb | B51: 26.33 | C51: 29.06 | D51: 0.38
A52: 超大50-70lb | B52: 40.12 | C52: 42.93 | D52: 0.75 | E52: 超出起始lb | F52: 51
A53: 超大70-150lb | B53: 54.81 | C53: 59.23 | D53: 0.75 | F53: 71
A54: 超大150lb+ | B54: 194.95 | C54: 203.46 | D54: 0.19 | F54: 151
A56: 小标准费用档（实重oz上限 → 非旺季 / 旺季）
A57: 上限oz | B57: 非旺季 | C57: 旺季
A58: 2 | B58: 3.06 | C58: 3.25
A59: 4 | B59: 3.15 | C59: 3.34
A60: 6 | B60: 3.24 | C60: 3.44
A61: 8 | B61: 3.33 | C61: 3.53
A62: 10 | B62: 3.43 | C62: 3.64
A63: 12 | B63: 3.53 | C63: 3.74
A64: 14 | B64: 3.6 | C64: 3.82
A65: 16 | B65: 3.65 | C65: 3.87
A68: 绿列=非旺季(约1/15–10/14)；橙列=旺季(10/15–1/14)。主表按「参数!B22」发货日自动选用。服装鞋靴另表，本表作家居/地毯估算。
A70: 当前参数季节(联动) | B70: =参数!B23

Sheet 采购成本对比
B1: ①产品信息（箱规带出·装数用于把整箱费用摊到一件） | F1: 不用填 | G1: ②自动售价（按「一件」核算） | I1: ③固定费率/汇率 | N1: ④单件尺寸/计费重/季节FBA（箱规尺寸→计费重→分段；费用随参数!发货日旺季切换） | U1: ⑤采购（一件·平米×19） | Y1: ⑥保本明细（一件·对应保本售价） | AN1: ⑦利润明细（一件·对应利润售价） | BE1: ⑧头程物流（先算整箱运费，再÷装数摊到一件） | BM1: 说明 | CF1: FBA季节 | CG1: 发货日
B2: 款式 | C2: 尺寸 | D2: 装数(件/箱) | E2: 图片 | F2: 竞品售价 | G2: 保本售价 | H2: 利润售价 | I2: 佣金率 | J2: 退款率 | K2: 广告率 | L2: 提现费率 | M2: 汇率 | N2: 单件净重(kg) | O2: 单件长(cm) | P2: 单件宽(cm) | Q2: 单件高(cm) | R2: FBA计费重(lb) | S2: FBA尺寸分段 | T2: 长+围长(in) | U2: 单价(RMB/㎡) | V2: 采购(RMB) | W2: 重量(计价备用) | X2: 采购价(USD) | Y2: 采购/售价比值(保本) | Z2: 中转调拨费 | AA2: 头程运费(RMB/件) | AB2: FBA配送费(USD/件) | AC2: 佣金(USD) | AD2: 退款(USD) | AE2: 广告(USD) | AF2: 提现(USD) | AG2: 仓储费率 | AH2: 仓储费(USD) | AI2: 优惠券(USD) | AJ2: 总成本(保本) | AK2: 退税 | AL2: 单品利润(保本) | AM2: 利润率(保本) | AN2: 采购/售价比值(销售) | AO2: 中转调拨费 | AP2: 头程运费(RMB/件) | AQ2: FBA配送费(USD/件) | AR2: 佣金(USD) | AS2: 退款(USD) | AT2: 广告(USD) | AU2: 提现(USD) | AV2: 仓储费率 | AW2: 仓储费(USD) | AX2: 优惠券(USD) | AY2: 总成本(销售) | AZ2: 退税 | BA2: 利润(销售-退税) | BB2: 利润率(销售-退税) | BC2: 利润(销售) | BD2: 利润率(销售) | BE2: 起运地 | BF2: FBA仓 | BG2: 运输方式 | BH2: 海运渠道(可选) | BI2: 海运单价(RMB/KG) | BJ2: 单箱计费重(kg) | BK2: 单箱海运费(RMB) | BL2: 陆运运费(RMB/箱) | BM2: 计价说明 | BO2: 可选渠道1 | BP2: 可选渠道2 | BQ2: 可选渠道3 | BR2: 可选渠道4 | BS2: 可选渠道5 | BT2: 可选渠道6 | BU2: 可选渠道7 | BV2: 可选渠道8 | BW2: 可选渠道9 | BX2: 可选渠道10 | BY2: 可选渠道11 | BZ2: 可选渠道12 | CA2: 可选渠道13 | CB2: 可选渠道14 | CC2: 可选渠道15 | CD2: 固定成本USD(内部) | CE2: 变动费率合计(内部) | CF2: =参数!B23 | CG2: =参数!B22
A3: 已列出箱规全部可算尺寸共22行（起运义乌/仓ABE8/渠道最低价；发货2026-10-27=旺季）。详见工作表「全尺寸利润」汇总。改仓或发货日后主表公式会变，汇总表需重算。
A4: 数据行 | C4: 2'3' | D4: =IF(C4="","",VLOOKUP($C4,箱规!$A$2:$S$23,9,FALSE)) | G4: =IF(OR(CD4="",CE4="",CE4>=1,X4=""),"",ROUNDUP((CD4-0.13*X4/1.13)/(1-CE4),2)) | H4: =IF(OR(CD4="",CE4="",X4=""),"",IF((1-CE4-参数!$B$16)<=0,"费率过高",ROUND((CD4-0.13*X4/1.13)/(1-CE4-参数!$B$16),2))) | I4: 0.15 | J4: 0.07 | K4: 0.15 | L4: 0.01 | M4: =参数!$B$2 | N4: =IF(C4="","",VLOOKUP($C4,箱规!$A$2:$S$23,14,FALSE)) | O4: =IF(C4="","",VLOOKUP($C4,箱规!$A$2:$S$23,5,FALSE)) | P4: =IF(C4="","",VLOOKUP($C4,箱规!$A$2:$S$23,6,FALSE)) | Q4: =IF(C4="","",VLOOKUP($C4,箱规!$A$2:$S$23,7,FALSE)) | R4: =IF(OR(N4="",O4="",P4="",Q4=""),"",MAX(N4*FBA规则!$B$6,(O4/FBA规则!$B$5)*(P4/FBA规则!$B$5)*(Q4/FBA规则!$B$5)/FBA规则!$B$7)) | S4: =IF(R4="","",IF(AND(N4*FBA规则!$B$6<=1,MAX(O4,P4,Q4)/FBA规则!$B$5<=15,MEDIAN(O4,P4,Q4)/FBA规则!$B$5<=12,MIN(O4,P4,Q4)/FBA规则!$B$5<=0.75),"小标准",IF(AND(R4<=20,MAX(O4,P4,Q4)/FBA规则!$B$5<=18,MEDIAN(O4,P4,Q4)/FBA规则!$B$5<=14,MIN(O4,P4,Q4)/FBA规则!$B$5<=8),"大标准",IF(AND(R4<=50,MAX(O4,P4,Q4)/FBA规则!$B$5<=59,MEDIAN(O4,P4,Q4)/FBA规则!$B$5<=33,MIN(O4,P4,Q4)/FBA规则!$B$5<=33,T4<=130),"大件",IF(R4<=50,"超大0-50lb",IF(R4<=70,"超大50-70lb",IF(R4<=150,"超大70-150lb","超大150lb+"))))))) | T4: =IF(OR(O4="",P4="",Q4=""),"",MAX(O4,P4,Q4)/FBA规则!$B$5+2*((MEDIAN(O4,P4,Q4)+MIN(O4,P4,Q4))/FBA规则!$B$5)) | U4: =参数!$B$15 | V4: =IF(OR(C4="",U4=""),"",(IF(OR(VLOOKUP($C4,箱规!$A$2:$S$23,4,FALSE)="",VLOOKUP($C4,箱规!$A$2:$S$23,4,FALSE)=0),VLOOKUP($C4,箱规!$A$2:$S$23,2,FALSE)*VLOOKUP($C4,箱规!$A$2:$S$23,3,FALSE)/10000,VLOOKUP($C4,箱规!$A$2:$S$23,4,FALSE)))*U4) | X4: =IF(AND(V4<>"",M4<>""),V4/M4,IF(AND(W4<>"",M4<>""),W4*1.13/M4,"")) | Y4: =IF(OR(X4="",G4=""),"",X4/G4) | AA4: =IF(OR(D4="",D4=0),"",IF(BG4="陆运",IF(BL4="",0,BL4)/D4,IF(BG4="海运",IF(BK4="",0,BK4)/D4,IF(BG4="海运+陆运",(IF(BK4="",0,BK4)+IF(BL4="",0,BL4))/D4,IF(BK4="",0,BK4)/D4)))) | AB4: =IF(OR(S4="",R4="",参数!$B$23=""),"",IF(S4="小标准",IFERROR(INDEX(FBA规则!$B$58:$C$65,MATCH(N4*FBA规则!$B$6*16,FBA规则!$A$58:$A$65,1),IF(参数!$B$23="旺季",2,1)),INDEX(FBA规则!$B$65:$C$65,1,IF(参数!$B$23="旺季",2,1))),IF(S4="大标准",IF(R4<=3,IFERROR(INDEX(FBA规则!$B$35:$C$46,MATCH(R4,FBA规则!$A$35:$A$46,1),IF(参数!$B$23="旺季",2,1)),INDEX(FBA规则!$B$46:$C$46,1,IF(参数!$B$23="旺季",2,1))),INDEX(FBA规则!$B$47:$C$47,1,IF(参数!$B$23="旺季",2,1))+FBA规则!$D$47*CEILING((R4-3)*4,1)),IF(S4="大件",INDEX(FBA规则!$B$50:$C$50,1,IF(参数!$B$23="旺季",2,1))+FBA规则!$D$50*MAX(0,CEILING(R4,1)-1),IF(S4="超大0-50lb",INDEX(FBA规则!$B$51:$C$51,1,IF(参数!$B$23="旺季",2,1))+FBA规则!$D$51*MAX(0,CEILING(R4,1)-1),IF(S4="超大50-70lb",INDEX(FBA规则!$B$52:$C$52,1,IF(参数!$B$23="旺季",2,1))+FBA规则!$D$52*MAX(0,R4-FBA规则!$F$52),IF(S4="超大70-150lb",INDEX(FBA规则!$B$53:$C$53,1,IF(参数!$B$23="旺季",2,1))+FBA规则!$D$53*MAX(0,R4-FBA规则!$F$53),INDEX(FBA规则!$B$54:$C$54,1,IF(参数!$B$23="旺季",2,1))+FBA规则!$D$54*MAX(0,R4-FBA规则!$F$54)))))))) | AC4: =IF(OR(G4="",I4=""),"",G4*I4) | AD4: =IF(OR(G4="",J4=""),"",G4*J4) | AE4: =IF(OR(G4="",K4=""),"",G4*K4) | AF4: =IF(OR(G4="",L4=""),"",G4*L4) | AG4: 0.02 | AH4: =IF(OR(G4="",AG4=""),"",G4*AG4) | AJ4: =IF(X4="","",X4+IF(OR(AA4="",M4=""),0,AA4/M4)+SUM(AB4:AF4)+IF(AH4="",0,AH4)+IF(AI4="",0,AI4)) | AK4: =IF(X4="","",0.13*X4/1.13) | AL4: =IF(OR(G4="",AJ4=""),"",G4+AK4-AJ4) | AM4: =IF(OR(AL4="",G4=""),"",AL4/G4) | AN4: =IF(OR(X4="",H4=""),"",X4/H4) | AP4: =AA4 | AQ4: =IF(OR(S4="",R4="",参数!$B$23=""),"",IF(S4="小标准",IFERROR(INDEX(FBA规则!$B$58:$C$65,MATCH(N4*FBA规则!$B$6*16,FBA规则!$A$58:$A$65,1),IF(参数!$B$23="旺季",2,1)),INDEX(FBA规则!$B$65:$C$65,1,IF(参数!$B$23="旺季",2,1))),IF(S4="大标准",IF(R4<=3,IFERROR(INDEX(FBA规则!$B$35:$C$46,MATCH(R4,FBA规则!$A$35:$A$46,1),IF(参数!$B$23="旺季",2,1)),INDEX(FBA规则!$B$46:$C$46,1,IF(参数!$B$23="旺季",2,1))),INDEX(FBA规则!$B$47:$C$47,1,IF(参数!$B$23="旺季",2,1))+FBA规则!$D$47*CEILING((R4-3)*4,1)),IF(S4="大件",INDEX(FBA规则!$B$50:$C$50,1,IF(参数!$B$23="旺季",2,1))+FBA规则!$D$50*MAX(0,CEILING(R4,1)-1),IF(S4="超大0-50lb",INDEX(FBA规则!$B$51:$C$51,1,IF(参数!$B$23="旺季",2,1))+FBA规则!$D$51*MAX(0,CEILING(R4,1)-1),IF(S4="超大50-70lb",INDEX(FBA规则!$B$52:$C$52,1,IF(参数!$B$23="旺季",2,1))+FBA规则!$D$52*MAX(0,R4-FBA规则!$F$52),IF(S4="超大70-150lb",INDEX(FBA规则!$B$53:$C$53,1,IF(参数!$B$23="旺季",2,1))+FBA规则!$D$53*MAX(0,R4-FBA规则!$F$53),INDEX(FBA规则!$B$54:$C$54,1,IF(参数!$B$23="旺季",2,1))+FBA规则!$D$54*MAX(0,R4-FBA规则!$F$54)))))))) | AR4: =IF(OR(H4="",I4=""),"",H4*I4) | AS4: =IF(OR(H4="",J4=""),"",H4*J4) | AT4: =IF(OR(H4="",K4=""),"",H4*K4) | AU4: =IF(OR(H4="",L4=""),"",H4*L4) | AV4: 0.02 | AW4: =IF(OR(H4="",AV4=""),"",H4*AV4) | AY4: =IF(X4="","",X4+IF(OR(AP4="",M4=""),0,AP4/M4)+SUM(AQ4:AU4)+IF(AW4="",0,AW4)+IF(AX4="",0,AX4)) | AZ4: =IF(X4="","",0.13*X4/1.13) | BA4: =IF(OR(H4="",AY4=""),"",H4+AZ4-AY4) | BB4: =IF(OR(BA4="",H4=""),"",BA4/H4) | BC4: =IF(OR(H4="",AY4=""),"",H4-AY4) | BD4: =IF(OR(BC4="",H4=""),"",BC4/H4) | BE4: 义乌 | BF4: ABE8 | BG4: 海运 | BH4: （最低价） | BI4: =IF(OR(BE4="",BF4=""),"",IF(AND(BH4<>"",BH4<>"（最低价）"),IFERROR(IF(SUMIFS(海运报价!$F$2:$F$2000,海运报价!$C$2:$C$2000,BH4,海运报价!$D$2:$D$2000,BE4,海运报价!$E$2:$E$2000,BF4)=0,"",SUMIFS(海运报价!$F$2:$F$2000,海运报价!$C$2:$C$2000,BH4,海运报价!$D$2:$D$2000,BE4,海运报价!$E$2:$E$2000,BF4)),""),IFERROR(IF(SUMIFS(海运下拉!$H$2:$H$311,海运下拉!$F$2:$F$311,BE4,海运下拉!$G$2:$G$311,BF4)=0,"",SUMIFS(海运下拉!$H$2:$H$311,海运下拉!$F$2:$F$311,BE4,海运下拉!$G$2:$G$311,BF4)),""))) | BJ4: =IF(C4="","",VLOOKUP($C4,箱规!$A$2:$S$23,18,FALSE)) | BK4: =IF(OR(BI4="",BJ4=""),"",BJ4*(BI4+IF(AND(BH4<>"",BH4<>"（最低价）"),IFERROR(AVERAGEIFS(海运报价!$H$2:$H$2000,海运报价!$C$2:$C$2000,BH4,海运报价!$D$2:$D$2000,BE4,海运报价!$E$2:$E$2000,BF4),0),IFERROR(SUMIFS(海运下拉!$J$2:$J$311,海运下拉!$F$2:$F$311,BE4,海运下拉!$G$2:$G$311,BF4),0)))) | BM4: =IF(OR(BE4="",BF4=""),"请选起运地+FBA仓",IF(AND(AND(BH4<>"",BH4<>"（最低价）"),BI4=""),"⚠该渠道不服务此仓：请重选渠道，或选「（最低价）」",IF(BI4="","无报价：请换起运地/仓库",IF(AND(BH4<>"",BH4<>"（最低价）"),"按你选的渠道「"&BH4&"」计价","按最低价「"&IFERROR(SUMIFS(海运下拉!$I$2:$I$311,海运下拉!$F$2:$F$311,BE4,海运下拉!$G$2:$G$311,BF4),"")&"」（渠道默认最低价）")))) | BO4: =IF(OR($BE4="",$BF4=""),"",IFERROR(INDEX(海运报价!$C$2:$C$2000,AGGREGATE(15,6,(ROW(海运报价!$C$2:$C$2000)-ROW(海运报价!$C$2)+1)/((海运报价!$D$2:$D$2000=$BE4)*(海运报价!$E$2:$E$2000=$BF4)),1)),"")) | BP4: =IF(OR($BE4="",$BF4=""),"",IFERROR(INDEX(海运报价!$C$2:$C$2000,AGGREGATE(15,6,(ROW(海运报价!$C$2:$C$2000)-ROW(海运报价!$C$2)+1)/((海运报价!$D$2:$D$2000=$BE4)*(海运报价!$E$2:$E$2000=$BF4)),2)),"")) | BQ4: =IF(OR($BE4="",$BF4=""),"",IFERROR(INDEX(海运报价!$C$2:$C$2000,AGGREGATE(15,6,(ROW(海运报价!$C$2:$C$2000)-ROW(海运报价!$C$2)+1)/((海运报价!$D$2:$D$2000=$BE4)*(海运报价!$E$2:$E$2000=$BF4)),3)),"")) | BR4: =IF(OR($BE4="",$BF4=""),"",IFERROR(INDEX(海运报价!$C$2:$C$2000,AGGREGATE(15,6,(ROW(海运报价!$C$2:$C$2000)-ROW(海运报价!$C$2)+1)/((海运报价!$D$2:$D$2000=$BE4)*(海运报价!$E$2:$E$2000=$BF4)),4)),"")) | BS4: =IF(OR($BE4="",$BF4=""),"",IFERROR(INDEX(海运报价!$C$2:$C$2000,AGGREGATE(15,6,(ROW(海运报价!$C$2:$C$2000)-ROW(海运报价!$C$2)+1)/((海运报价!$D$2:$D$2000=$BE4)*(海运报价!$E$2:$E$2000=$BF4)),5)),"")) | BT4: =IF(OR($BE4="",$BF4=""),"",IFERROR(INDEX(海运报价!$C$2:$C$2000,AGGREGATE(15,6,(ROW(海运报价!$C$2:$C$2000)-ROW(海运报价!$C$2)+1)/((海运报价!$D$2:$D$2000=$BE4)*(海运报价!$E$2:$E$2000=$BF4)),6)),"")) | BU4: =IF(OR($BE4="",$BF4=""),"",IFERROR(INDEX(海运报价!$C$2:$C$2000,AGGREGATE(15,6,(ROW(海运报价!$C$2:$C$2000)-ROW(海运报价!$C$2)+1)/((海运报价!$D$2:$D$2000=$BE4)*(海运报价!$E$2:$E$2000=$BF4)),7)),"")) | BV4: =IF(OR($BE4="",$BF4=""),"",IFERROR(INDEX(海运报价!$C$2:$C$2000,AGGREGATE(15,6,(ROW(海运报价!$C$2:$C$2000)-ROW(海运报价!$C$2)+1)/((海运报价!$D$2:$D$2000=$BE4)*(海运报价!$E$2:$E$2000=$BF4)),8)),"")) | BW4: =IF(OR($BE4="",$BF4=""),"",IFERROR(INDEX(海运报价!$C$2:$C$2000,AGGREGATE(15,6,(ROW(海运报价!$C$2:$C$2000)-ROW(海运报价!$C$2)+1)/((海运报价!$D$2:$D$2000=$BE4)*(海运报价!$E$2:$E$2000=$BF4)),9)),"")) | BX4: =IF(OR($BE4="",$BF4=""),"",IFERROR(INDEX(海运报价!$C$2:$C$2000,AGGREGATE(15,6,(ROW(海运报价!$C$2:$C$2000)-ROW(海运报价!$C$2)+1)/((海运报价!$D$2:$D$2000=$BE4)*(海运报价!$E$2:$E$2000=$BF4)),10)),"")) | BY4: =IF(OR($BE4="",$BF4=""),"",IFERROR(INDEX(海运报价!$C$2:$C$2000,AGGREGATE(15,6,(ROW(海运报价!$C$2:$C$2000)-ROW(海运报价!$C$2)+1)/((海运报价!$D$2:$D$2000=$BE4)*(海运报价!$E$2:$E$2000=$BF4)),11)),"")) | BZ4: =IF(OR($BE4="",$BF4=""),"",IFERROR(INDEX(海运报价!$C$2:$C$2000,AGGREGATE(15,6,(ROW(海运报价!$C$2:$C$2000)-ROW(海运报价!$C$2)+1)/((海运报价!$D$2:$D$2000=$BE4)*(海运报价!$E$2:$E$2000=$BF4)),12)),"")) | CA4: =IF(OR($BE4="",$BF4=""),"",IFERROR(INDEX(海运报价!$C$2:$C$2000,AGGREGATE(15,6,(ROW(海运报价!$C$2:$C$2000)-ROW(海运报价!$C$2)+1)/((海运报价!$D$2:$D$2000=$BE4)*(海运报价!$E$2:$E$2000=$BF4)),13)),"")) | CB4: =IF(OR($BE4="",$BF4=""),"",IFERROR(INDEX(海运报价!$C$2:$C$2000,AGGREGATE(15,6,(ROW(海运报价!$C$2:$C$2000)-ROW(海运报价!$C$2)+1)/((海运报价!$D$2:$D$2000=$BE4)*(海运报价!$E$2:$E$2000=$BF4)),14)),"")) | CC4: =IF(OR($BE4="",$BF4=""),"",IFERROR(INDEX(海运报价!$C$2:$C$2000,AGGREGATE(15,6,(ROW(海运报价!$C$2:$C$2000)-ROW(海运报价!$C$2)+1)/((海运报价!$D$2:$D$2000=$BE4)*(海运报价!$E$2:$E$2000=$BF4)),15)),"")) | CD4: =IF(OR(X4="",M4=""),"",X4+IF(OR(AA4="",M4=""),0,AA4/M4)+IF(AB4="",0,AB4)+IF(AI4="",0,AI4)+IF(Z4="",0,Z4)) | CE4: =I4+J4+K4+L4+AG4
C5: 2'5' | D5: =IF(C5="","",VLOOKUP($C5,箱规!$A$2:$S$23,9,FALSE)) | G5: =IF(OR(CD5="",CE5="",CE5>=1,X5=""),"",ROUNDUP((CD5-0.13*X5/1.13)/(1-CE5),2)) | H5: =IF(OR(CD5="",CE5="",X5=""),"",IF((1-CE5-参数!$B$16)<=0,"费率过高",ROUND((CD5-0.13*X5/1.13)/(1-CE5-参数!$B$16),2))) | I5: 0.15 | J5: 0.07 | K5: 0.15 | L5: 0.01 | M5: =参数!$B$2 | N5: =IF(C5="","",VLOOKUP($C5,箱规!$A$2:$S$23,14,FALSE)) | O5: =IF(C5="","",VLOOKUP($C5,箱规!$A$2:$S$23,5,FALSE)) | P5: =IF(C5="","",VLOOKUP($C5,箱规!$A$2:$S$23,6,FALSE)) | Q5: =IF(C5="","",VLOOKUP($C5,箱规!$A$2:$S$23,7,FALSE)) | R5: =IF(OR(N5="",O5="",P5="",Q5=""),"",MAX(N5*FBA规则!$B$6,(O5/FBA规则!$B$5)*(P5/FBA规则!$B$5)*(Q5/FBA规则!$B$5)/FBA规则!$B$7)) | S5: =IF(R5="","",IF(AND(N5*FBA规则!$B$6<=1,MAX(O5,P5,Q5)/FBA规则!$B$5<=15,MEDIAN(O5,P5,Q5)/FBA规则!$B$5<=12,MIN(O5,P5,Q5)/FBA规则!$B$5<=0.75),"小标准",IF(AND(R5<=20,MAX(O5,P5,Q5)/FBA规则!$B$5<=18,MEDIAN(O5,P5,Q5)/FBA规则!$B$5<=14,MIN(O5,P5,Q5)/FBA规则!$B$5<=8),"大标准",IF(AND(R5<=50,MAX(O5,P5,Q5)/FBA规则!$B$5<=59,MEDIAN(O5,P5,Q5)/FBA规则!$B$5<=33,MIN(O5,P5,Q5)/FBA规则!$B$5<=33,T5<=130),"大件",IF(R5<=50,"超大0-50lb",IF(R5<=70,"超大50-70lb",IF(R5<=150,"超大70-150lb","超大150lb+"))))))) | T5: =IF(OR(O5="",P5="",Q5=""),"",MAX(O5,P5,Q5)/FBA规则!$B$5+2*((MEDIAN(O5,P5,Q5)+MIN(O5,P5,Q5))/FBA规则!$B$5)) | U5: =参数!$B$15 | V5: =IF(OR(C5="",U5=""),"",(IF(OR(VLOOKUP($C5,箱规!$A$2:$S$23,4,FALSE)="",VLOOKUP($C5,箱规!$A$2:$S$23,4,FALSE)=0),VLOOKUP($C5,箱规!$A$2:$S$23,2,FALSE)*VLOOKUP($C5,箱规!$A$2:$S$23,3,FALSE)/10000,VLOOKUP($C5,箱规!$A$2:$S$23,4,FALSE)))*U5) | X5: =IF(AND(V5<>"",M5<>""),V5/M5,IF(AND(W5<>"",M5<>""),W5*1.13/M5,"")) | Y5: =IF(OR(X5="",G5=""),"",X5/G5) | AA5: =IF(OR(D5="",D5=0),"",IF(BG5="陆运",IF(BL5="",0,BL5)/D5,IF(BG5="海运",IF(BK5="",0,BK5)/D5,IF(BG5="海运+陆运",(IF(BK5="",0,BK5)+IF(BL5="",0,BL5))/D5,IF(BK5="",0,BK5)/D5)))) | AB5: =IF(OR(S5="",R5="",参数!$B$23=""),"",IF(S5="小标准",IFERROR(INDEX(FBA规则!$B$58:$C$65,MATCH(N5*FBA规则!$B$6*16,FBA规则!$A$58:$A$65,1),IF(参数!$B$23="旺季",2,1)),INDEX(FBA规则!$B$65:$C$65,1,IF(参数!$B$23="旺季",2,1))),IF(S5="大标准",IF(R5<=3,IFERROR(INDEX(FBA规则!$B$35:$C$46,MATCH(R5,FBA规则!$A$35:$A$46,1),IF(参数!$B$23="旺季",2,1)),INDEX(FBA规则!$B$46:$C$46,1,IF(参数!$B$23="旺季",2,1))),INDEX(FBA规则!$B$47:$C$47,1,IF(参数!$B$23="旺季",2,1))+FBA规则!$D$47*CEILING((R5-3)*4,1)),IF(S5="大件",INDEX(FBA规则!$B$50:$C$50,1,IF(参数!$B$23="旺季",2,1))+FBA规则!$D$50*MAX(0,CEILING(R5,1)-1),IF(S5="超大0-50lb",INDEX(FBA规则!$B$51:$C$51,1,IF(参数!$B$23="旺季",2,1))+FBA规则!$D$51*MAX(0,CEILING(R5,1)-1),IF(S5="超大50-70lb",INDEX(FBA规则!$B$52:$C$52,1,IF(参数!$B$23="旺季",2,1))+FBA规则!$D$52*MAX(0,R5-FBA规则!$F$52),IF(S5="超大70-150lb",INDEX(FBA规则!$B$53:$C$53,1,IF(参数!$B$23="旺季",2,1))+FBA规则!$D$53*MAX(0,R5-FBA规则!$F$53),INDEX(FBA规则!$B$54:$C$54,1,IF(参数!$B$23="旺季",2,1))+FBA规则!$D$54*MAX(0,R5-FBA规则!$F$54)))))))) | AC5: =IF(OR(G5="",I5=""),"",G5*I5) | AD5: =IF(OR(G5="",J5=""),"",G5*J5) | AE5: =IF(OR(G5="",K5=""),"",G5*K5) | AF5: =IF(OR(G5="",L5=""),"",G5*L5) | AG5: 0.02 | AH5: =IF(OR(G5="",AG5=""),"",G5*AG5) | AJ5: =IF(X5="","",X5+IF(OR(AA5="",M5=""),0,AA5/M5)+SUM(AB5:AF5)+IF(AH5="",0,AH5)+IF(AI5="",0,AI5)) | AK5: =IF(X5="","",0.13*X5/1.13) | AL5: =IF(OR(G5="",AJ5=""),"",G5+AK5-AJ5) | AM5: =IF(OR(AL5="",G5=""),"",AL5/G5) | AN5: =IF(OR(X5="",H5=""),"",X5/H5) | AP5: =AA5 | AQ5: =IF(OR(S5="",R5="",参数!$B$23=""),"",IF(S5="小标准",IFERROR(INDEX(FBA规则!$B$58:$C$65,MATCH(N5*FBA规则!$B$6*16,FBA规则!$A$58:$A$65,1),IF(参数!$B$23="旺季",2,1)),INDEX(FBA规则!$B$65:$C$65,1,IF(参数!$B$23="旺季",2,1))),IF(S5="大标准",IF(R5<=3,IFERROR(INDEX(FBA规则!$B$35:$C$46,MATCH(R5,FBA规则!$A$35:$A$46,1),IF(参数!$B$23="旺季",2,1)),INDEX(FBA规则!$B$46:$C$46,1,IF(参数!$B$23="旺季",2,1))),INDEX(FBA规则!$B$47:$C$47,1,IF(参数!$B$23="旺季",2,1))+FBA规则!$D$47*CEILING((R5-3)*4,1)),IF(S5="大件",INDEX(FBA规则!$B$50:$C$50,1,IF(参数!$B$23="旺季",2,1))+FBA规则!$D$50*MAX(0,CEILING(R5,1)-1),IF(S5="超大0-50lb",INDEX(FBA规则!$B$51:$C$51,1,IF(参数!$B$23="旺季",2,1))+FBA规则!$D$51*MAX(0,CEILING(R5,1)-1),IF(S5="超大50-70lb",INDEX(FBA规则!$B$52:$C$52,1,IF(参数!$B$23="旺季",2,1))+FBA规则!$D$52*MAX(0,R5-FBA规则!$F$52),IF(S5="超大70-150lb",INDEX(FBA规则!$B$53:$C$53,1,IF(参数!$B$23="旺季",2,1))+FBA规则!$D$53*MAX(0,R5-FBA规则!$F$53),INDEX(FBA规则!$B$54:$C$54,1,IF(参数!$B$23="旺季",2,1))+FBA规则!$D$54*MAX(0,R5-FBA规则!$F$54)))))))) | AR5: =IF(OR(H5="",I5=""),"",H5*I5) | AS5: =IF(OR(H5="",J5=""),"",H5*J5) | AT5: =IF(OR(H5="",K5=""),"",H5*K5) | AU5: =IF(OR(H5="",L5=""),"",H5*L5) | AV5: 0.02 | AW5: =IF(OR(H5="",AV5=""),"",H5*AV5) | AY5: =IF(X5="","",X5+IF(OR(AP5="",M5=""),0,AP5/M5)+SUM(AQ5:AU5)+IF(AW5="",0,AW5)+IF(AX5="",0,AX5)) | AZ5: =IF(X5="","",0.13*X5/1.13) | BA5: =IF(OR(H5="",AY5=""),"",H5+AZ5-AY5) | BB5: =IF(OR(BA5="",H5=""),"",BA5/H5) | BC5: =IF(OR(H5="",AY5=""),"",H5-AY5) | BD5: =IF(OR(BC5="",H5=""),"",BC5/H5) | BE5: 义乌 | BF5: ABE8 | BG5: 海运 | BH5: （最低价） | BI5: =IF(OR(BE5="",BF5=""),"",IF(AND(BH5<>"",BH5<>"（最低价）"),IFERROR(IF(SUMIFS(海运报价!$F$2:$F$2000,海运报价!$C$2:$C$2000,BH5,海运报价!$D$2:$D$2000,BE5,海运报价!$E$2:$E$2000,BF5)=0,"",SUMIFS(海运报价!$F$2:$F$2000,海运报价!$C$2:$C$2000,BH5,海运报价!$D$2:$D$2000,BE5,海运报价!$E$2:$E$2000,BF5)),""),IFERROR(IF(SUMIFS(海运下拉!$H$2:$H$311,海运下拉!$F$2:$F$311,BE5,海运下拉!$G$2:$G$311,BF5)=0,"",SUMIFS(海运下拉!$H$2:$H$311,海运下拉!$F$2:$F$311,BE5,海运下拉!$G$2:$G$311,BF5)),""))) | BJ5: =IF(C5="","",VLOOKUP($C5,箱规!$A$2:$S$23,18,FALSE)) | BK5: =IF(OR(BI5="",BJ5=""),"",BJ5*(BI5+IF(AND(BH5<>"",BH5<>"（最低价）"),IFERROR(AVERAGEIFS(海运报价!$H$2:$H$2000,海运报价!$C$2:$C$2000,BH5,海运报价!$D$2:$D$2000,BE5,海运报价!$E$2:$E$2000,BF5),0),IFERROR(SUMIFS(海运下拉!$J$2:$J$311,海运下拉!$F$2:$F$311,BE5,海运下拉!$G$2:$G$311,BF5),0)))) | BM5: =IF(OR(BE5="",BF5=""),"请选起运地+FBA仓",IF(AND(AND(BH5<>"",BH5<>"（最低价）"),BI5=""),"⚠该渠道不服务此仓：请重选渠道，或选「（最低价）」",IF(BI5="","无报价：请换起运地/仓库",IF(AND(BH5<>"",BH5<>"（最低价）"),"按你选的渠道「"&BH5&"」计价","按最低价「"&IFERROR(SUMIFS(海运下拉!$I$2:$I$311,海运下拉!$F$2:$F$311,BE5,海运下拉!$G$2:$G$311,BF5),"")&"」（渠道默认最低价）")))) | BO5: =IF(OR($BE5="",$BF5=""),"",IFERROR(INDEX(海运报价!$C$2:$C$2000,AGGREGATE(15,6,(ROW(海运报价!$C$2:$C$2000)-ROW(海运报价!$C$2)+1)/((海运报价!$D$2:$D$2000=$BE5)*(海运报价!$E$2:$E$2000=$BF5)),1)),"")) | BP5: =IF(OR($BE5="",$BF5=""),"",IFERROR(INDEX(海运报价!$C$2:$C$2000,AGGREGATE(15,6,(ROW(海运报价!$C$2:$C$2000)-ROW(海运报价!$C$2)+1)/((海运报价!$D$2:$D$2000=$BE5)*(海运报价!$E$2:$E$2000=$BF5)),2)),"")) | BQ5: =IF(OR($BE5="",$BF5=""),"",IFERROR(INDEX(海运报价!$C$2:$C$2000,AGGREGATE(15,6,(ROW(海运报价!$C$2:$C$2000)-ROW(海运报价!$C$2)+1)/((海运报价!$D$2:$D$2000=$BE5)*(海运报价!$E$2:$E$2000=$BF5)),3)),"")) | BR5: =IF(OR($BE5="",$BF5=""),"",IFERROR(INDEX(海运报价!$C$2:$C$2000,AGGREGATE(15,6,(ROW(海运报价!$C$2:$C$2000)-ROW(海运报价!$C$2)+1)/((海运报价!$D$2:$D$2000=$BE5)*(海运报价!$E$2:$E$2000=$BF5)),4)),"")) | BS5: =IF(OR($BE5="",$BF5=""),"",IFERROR(INDEX(海运报价!$C$2:$C$2000,AGGREGATE(15,6,(ROW(海运报价!$C$2:$C$2000)-ROW(海运报价!$C$2)+1)/((海运报价!$D$2:$D$2000=$BE5)*(海运报价!$E$2:$E$2000=$BF5)),5)),"")) | BT5: =IF(OR($BE5="",$BF5=""),"",IFERROR(INDEX(海运报价!$C$2:$C$2000,AGGREGATE(15,6,(ROW(海运报价!$C$2:$C$2000)-ROW(海运报价!$C$2)+1)/((海运报价!$D$2:$D$2000=$BE5)*(海运报价!$E$2:$E$2000=$BF5)),6)),"")) | BU5: =IF(OR($BE5="",$BF5=""),"",IFERROR(INDEX(海运报价!$C$2:$C$2000,AGGREGATE(15,6,(ROW(海运报价!$C$2:$C$2000)-ROW(海运报价!$C$2)+1)/((海运报价!$D$2:$D$2000=$BE5)*(海运报价!$E$2:$E$2000=$BF5)),7)),"")) | BV5: =IF(OR($BE5="",$BF5=""),"",IFERROR(INDEX(海运报价!$C$2:$C$2000,AGGREGATE(15,6,(ROW(海运报价!$C$2:$C$2000)-ROW(海运报价!$C$2)+1)/((海运报价!$D$2:$D$2000=$BE5)*(海运报价!$E$2:$E$2000=$BF5)),8)),"")) | BW5: =IF(OR($BE5="",$BF5=""),"",IFERROR(INDEX(海运报价!$C$2:$C$2000,AGGREGATE(15,6,(ROW(海运报价!$C$2:$C$2000)-ROW(海运报价!$C$2)+1)/((海运报价!$D$2:$D$2000=$BE5)*(海运报价!$E$2:$E$2000=$BF5)),9)),"")) | BX5: =IF(OR($BE5="",$BF5=""),"",IFERROR(INDEX(海运报价!$C$2:$C$2000,AGGREGATE(15,6,(ROW(海运报价!$C$2:$C$2000)-ROW(海运报价!$C$2)+1)/((海运报价!$D$2:$D$2000=$BE5)*(海运报价!$E$2:$E$2000=$BF5)),10)),"")) | BY5: =IF(OR($BE5="",$BF5=""),"",IFERROR(INDEX(海运报价!$C$2:$C$2000,AGGREGATE(15,6,(ROW(海运报价!$C$2:$C$2000)-ROW(海运报价!$C$2)+1)/((海运报价!$D$2:$D$2000=$BE5)*(海运报价!$E$2:$E$2000=$BF5)),11)),"")) | BZ5: =IF(OR($BE5="",$BF5=""),"",IFERROR(INDEX(海运报价!$C$2:$C$2000,AGGREGATE(15,6,(ROW(海运报价!$C$2:$C$2000)-ROW(海运报价!$C$2)+1)/((海运报价!$D$2:$D$2000=$BE5)*(海运报价!$E$2:$E$2000=$BF5)),12)),"")) | CA5: =IF(OR($BE5="",$BF5=""),"",IFERROR(INDEX(海运报价!$C$2:$C$2000,AGGREGATE(15,6,(ROW(海运报价!$C$2:$C$2000)-ROW(海运报价!$C$2)+1)/((海运报价!$D$2:$D$2000=$BE5)*(海运报价!$E$2:$E$2000=$BF5)),13)),"")) | CB5: =IF(OR($BE5="",$BF5=""),"",IFERROR(INDEX(海运报价!$C$2:$C$2000,AGGREGATE(15,6,(ROW(海运报价!$C$2:$C$2000)-ROW(海运报价!$C$2)+1)/((海运报价!$D$2:$D$2000=$BE5)*(海运报价!$E$2:$E$2000=$BF5)),14)),"")) | CC5: =IF(OR($BE5="",$BF5=""),"",IFERROR(INDEX(海运报价!$C$2:$C$2000,AGGREGATE(15,6,(ROW(海运报价!$C$2:$C$2000)-ROW(海运报价!$C$2)+1)/((海运报价!$D$2:$D$2000=$BE5)*(海运报价!$E$2:$E$2000=$BF5)),15)),"")) | CD5: =IF(OR(X5="",M5=""),"",X5+IF(OR(AA5="",M5=""),0,AA5/M5)+IF(AB5="",0,AB5)+IF(AI5="",0,AI5)+IF(Z5="",0,Z5)) | CE5: =I5+J5+K5+L5+AG5
C6: 2'6' | D6: =IF(C6="","",VLOOKUP($C6,箱规!$A$2:$S$23,9,FALSE)) | G6: =IF(OR(CD6="",CE6="",CE6>=1,X6=""),"",ROUNDUP((CD6-0.13*X6/1.13)/(1-CE6),2)) | H6: =IF(OR(CD6="",CE6="",X6=""),"",IF((1-CE6-参数!$B$16)<=0,"费率过高",ROUND((CD6-0.13*X6/1.13)/(1-CE6-参数!$B$16),2))) | I6: 0.15 | J6: 0.07 | K6: 0.15 | L6: 0.01 | M6: =参数!$B$2 | N6: =IF(C6="","",VLOOKUP($C6,箱规!$A$2:$S$23,14,FALSE)) | O6: =IF(C6="","",VLOOKUP($C6,箱规!$A$2:$S$23,5,FALSE)) | P6: =IF(C6="","",VLOOKUP($C6,箱规!$A$2:$S$23,6,FALSE)) | Q6: =IF(C6="","",VLOOKUP($C6,箱规!$A$2:$S$23,7,FALSE)) | R6: =IF(OR(N6="",O6="",P6="",Q6=""),"",MAX(N6*FBA规则!$B$6,(O6/FBA规则!$B$5)*(P6/FBA规则!$B$5)*(Q6/FBA规则!$B$5)/FBA规则!$B$7)) | S6: =IF(R6="","",IF(AND(N6*FBA规则!$B$6<=1,MAX(O6,P6,Q6)/FBA规则!$B$5<=15,MEDIAN(O6,P6,Q6)/FBA规则!$B$5<=12,MIN(O6,P6,Q6)/FBA规则!$B$5<=0.75),"小标准",IF(AND(R6<=20,MAX(O6,P6,Q6)/FBA规则!$B$5<=18,MEDIAN(O6,P6,Q6)/FBA规则!$B$5<=14,MIN(O6,P6,Q6)/FBA规则!$B$5<=8),"大标准",IF(AND(R6<=50,MAX(O6,P6,Q6)/FBA规则!$B$5<=59,MEDIAN(O6,P6,Q6)/FBA规则!$B$5<=33,MIN(O6,P6,Q6)/FBA规则!$B$5<=33,T6<=130),"大件",IF(R6<=50,"超大0-50lb",IF(R6<=70,"超大50-70lb",IF(R6<=150,"超大70-150lb","超大150lb+"))))))) | T6: =IF(OR(O6="",P6="",Q6=""),"",MAX(O6,P6,Q6)/FBA规则!$B$5+2*((MEDIAN(O6,P6,Q6)+MIN(O6,P6,Q6))/FBA规则!$B$5)) | U6: =参数!$B$15 | V6: =IF(OR(C6="",U6=""),"",(IF(OR(VLOOKUP($C6,箱规!$A$2:$S$23,4,FALSE)="",VLOOKUP($C6,箱规!$A$2:$S$23,4,FALSE)=0),VLOOKUP($C6,箱规!$A$2:$S$23,2,FALSE)*VLOOKUP($C6,箱规!$A$2:$S$23,3,FALSE)/10000,VLOOKUP($C6,箱规!$A$2:$S$23,4,FALSE)))*U6) | X6: =IF(AND(V6<>"",M6<>""),V6/M6,IF(AND(W6<>"",M6<>""),W6*1.13/M6,"")) | Y6: =IF(OR(X6="",G6=""),"",X6/G6) | AA6: =IF(OR(D6="",D6=0),"",IF(BG6="陆运",IF(BL6="",0,BL6)/D6,IF(BG6="海运",IF(BK6="",0,BK6)/D6,IF(BG6="海运+陆运",(IF(BK6="",0,BK6)+IF(BL6="",0,BL6))/D6,IF(BK6="",0,BK6)/D6)))) | AB6: =IF(OR(S6="",R6="",参数!$B$23=""),"",IF(S6="小标准",IFERROR(INDEX(FBA规则!$B$58:$C$65,MATCH(N6*FBA规则!$B$6*16,FBA规则!$A$58:$A$65,1),IF(参数!$B$23="旺季",2,1)),INDEX(FBA规则!$B$65:$C$65,1,IF(参数!$B$23="旺季",2,1))),IF(S6="大标准",IF(R6<=3,IFERROR(INDEX(FBA规则!$B$35:$C$46,MATCH(R6,FBA规则!$A$35:$A$46,1),IF(参数!$B$23="旺季",2,1)),INDEX(FBA规则!$B$46:$C$46,1,IF(参数!$B$23="旺季",2,1))),INDEX(FBA规则!$B$47:$C$47,1,IF(参数!$B$23="旺季",2,1))+FBA规则!$D$47*CEILING((R6-3)*4,1)),IF(S6="大件",INDEX(FBA规则!$B$50:$C$50,1,IF(参数!$B$23="旺季",2,1))+FBA规则!$D$50*MAX(0,CEILING(R6,1)-1),IF(S6="超大0-50lb",INDEX(FBA规则!$B$51:$C$51,1,IF(参数!$B$23="旺季",2,1))+FBA规则!$D$51*MAX(0,CEILING(R6,1)-1),IF(S6="超大50-70lb",INDEX(FBA规则!$B$52:$C$52,1,IF(参数!$B$23="旺季",2,1))+FBA规则!$D$52*MAX(0,R6-FBA规则!$F$52),IF(S6="超大70-150lb",INDEX(FBA规则!$B$53:$C$53,1,IF(参数!$B$23="旺季",2,1))+FBA规则!$D$53*MAX(0,R6-FBA规则!$F$53),INDEX(FBA规则!$B$54:$C$54,1,IF(参数!$B$23="旺季",2,1))+FBA规则!$D$54*MAX(0,R6-FBA规则!$F$54)))))))) | AC6: =IF(OR(G6="",I6=""),"",G6*I6) | AD6: =IF(OR(G6="",J6=""),"",G6*J6) | AE6: =IF(OR(G6="",K6=""),"",G6*K6) | AF6: =IF(OR(G6="",L6=""),"",G6*L6) | AG6: 0.02 | AH6: =IF(OR(G6="",AG6=""),"",G6*AG6) | AJ6: =IF(X6="","",X6+IF(OR(AA6="",M6=""),0,AA6/M6)+SUM(AB6:AF6)+IF(AH6="",0,AH6)+IF(AI6="",0,AI6)) | AK6: =IF(X6="","",0.13*X6/1.13) | AL6: =IF(OR(G6="",AJ6=""),"",G6+AK6-AJ6) | AM6: =IF(OR(AL6="",G6=""),"",AL6/G6) | AN6: =IF(OR(X6="",H6=""),"",X6/H6) | AP6: =AA6 | AQ6: =IF(OR(S6="",R6="",参数!$B$23=""),"",IF(S6="小标准",IFERROR(INDEX(FBA规则!$B$58:$C$65,MATCH(N6*FBA规则!$B$6*16,FBA规则!$A$58:$A$65,1),IF(参数!$B$23="旺季",2,1)),INDEX(FBA规则!$B$65:$C$65,1,IF(参数!$B$23="旺季",2,1))),IF(S6="大标准",IF(R6<=3,IFERROR(INDEX(FBA规则!$B$35:$C$46,MATCH(R6,FBA规则!$A$35:$A$46,1),IF(参数!$B$23="旺季",2,1)),INDEX(FBA规则!$B$46:$C$46,1,IF(参数!$B$23="旺季",2,1))),INDEX(FBA规则!$B$47:$C$47,1,IF(参数!$B$23="旺季",2,1))+FBA规则!$D$47*CEILING((R6-3)*4,1)),IF(S6="大件",INDEX(FBA规则!$B$50:$C$50,1,IF(参数!$B$23="旺季",2,1))+FBA规则!$D$50*MAX(0,CEILING(R6,1)-1),IF(S6="超大0-50lb",INDEX(FBA规则!$B$51:$C$51,1,IF(参数!$B$23="旺季",2,1))+FBA规则!$D$51*MAX(0,CEILING(R6,1)-1),IF(S6="超大50-70lb",INDEX(FBA规则!$B$52:$C$52,1,IF(参数!$B$23="旺季",2,1))+FBA规则!$D$52*MAX(0,R6-FBA规则!$F$52),IF(S6="超大70-150lb",INDEX(FBA规则!$B$53:$C$53,1,IF(参数!$B$23="旺季",2,1))+FBA规则!$D$53*MAX(0,R6-FBA规则!$F$53),INDEX(FBA规则!$B$54:$C$54,1,IF(参数!$B$23="旺季",2,1))+FBA规则!$D$54*MAX(0,R6-FBA规则!$F$54)))))))) | AR6: =IF(OR(H6="",I6=""),"",H6*I6) | AS6: =IF(OR(H6="",J6=""),"",H6*J6) | AT6: =IF(OR(H6="",K6=""),"",H6*K6) | AU6: =IF(OR(H6="",L6=""),"",H6*L6) | AV6: 0.02 | AW6: =IF(OR(H6="",AV6=""),"",H6*AV6) | AY6: =IF(X6="","",X6+IF(OR(AP6="",M6=""),0,AP6/M6)+SUM(AQ6:AU6)+IF(AW6="",0,AW6)+IF(AX6="",0,AX6)) | AZ6: =IF(X6="","",0.13*X6/1.13) | BA6: =IF(OR(H6="",AY6=""),"",H6+AZ6-AY6) | BB6: =IF(OR(BA6="",H6=""),"",BA6/H6) | BC6: =IF(OR(H6="",AY6=""),"",H6-AY6) | BD6: =IF(OR(BC6="",H6=""),"",BC6/H6) | BE6: 义乌 | BF6: ABE8 | BG6: 海运 | BH6: （最低价） | BI6: =IF(OR(BE6="",BF6=""),"",IF(AND(BH6<>"",BH6<>"（最低价）"),IFERROR(IF(SUMIFS(海运报价!$F$2:$F$2000,海运报价!$C$2:$C$2000,BH6,海运报价!$D$2:$D$2000,BE6,海运报价!$E$2:$E$2000,BF6)=0,"",SUMIFS(海运报价!$F$2:$F$2000,海运报价!$C$2:$C$2000,BH6,海运报价!$D$2:$D$2000,BE6,海运报价!$E$2:$E$2000,BF6)),""),IFERROR(IF(SUMIFS(海运下拉!$H$2:$H$311,海运下拉!$F$2:$F$311,BE6,海运下拉!$G$2:$G$311,BF6)=0,"",SUMIFS(海运下拉!$H$2:$H$311,海运下拉!$F$2:$F$311,BE6,海运下拉!$G$2:$G$311,BF6)),""))) | BJ6: =IF(C6="","",VLOOKUP($C6,箱规!$A$2:$S$23,18,FALSE)) | BK6: =IF(OR(BI6="",BJ6=""),"",BJ6*(BI6+IF(AND(BH6<>"",BH6<>"（最低价）"),IFERROR(AVERAGEIFS(海运报价!$H$2:$H$2000,海运报价!$C$2:$C$2000,BH6,海运报价!$D$2:$D$2000,BE6,海运报价!$E$2:$E$2000,BF6),0),IFERROR(SUMIFS(海运下拉!$J$2:$J$311,海运下拉!$F$2:$F$311,BE6,海运下拉!$G$2:$G$311,BF6),0)))) | BM6: =IF(OR(BE6="",BF6=""),"请选起运地+FBA仓",IF(AND(AND(BH6<>"",BH6<>"（最低价）"),BI6=""),"⚠该渠道不服务此仓：请重选渠道，或选「（最低价）」",IF(BI6="","无报价：请换起运地/仓库",IF(AND(BH6<>"",BH6<>"（最低价）"),"按你选的渠道「"&BH6&"」计价","按最低价「"&IFERROR(SUMIFS(海运下拉!$I$2:$I$311,海运下拉!$F$2:$F$311,BE6,海运下拉!$G$2:$G$311,BF6),"")&"」（渠道默认最低价）")))) | BO6: =IF(OR($BE6="",$BF6=""),"",IFERROR(INDEX(海运报价!$C$2:$C$2000,AGGREGATE(15,6,(ROW(海运报价!$C$2:$C$2000)-ROW(海运报价!$C$2)+1)/((海运报价!$D$2:$D$2000=$BE6)*(海运报价!$E$2:$E$2000=$BF6)),1)),"")) | BP6: =IF(OR($BE6="",$BF6=""),"",IFERROR(INDEX(海运报价!$C$2:$C$2000,AGGREGATE(15,6,(ROW(海运报价!$C$2:$C$2000)-ROW(海运报价!$C$2)+1)/((海运报价!$D$2:$D$2000=$BE6)*(海运报价!$E$2:$E$2000=$BF6)),2)),"")) | BQ6: =IF(OR($BE6="",$BF6=""),"",IFERROR(INDEX(海运报价!$C$2:$C$2000,AGGREGATE(15,6,(ROW(海运报价!$C$2:$C$2000)-ROW(海运报价!$C$2)+1)/((海运报价!$D$2:$D$2000=$BE6)*(海运报价!$E$2:$E$2000=$BF6)),3)),"")) | BR6: =IF(OR($BE6="",$BF6=""),"",IFERROR(INDEX(海运报价!$C$2:$C$2000,AGGREGATE(15,6,(ROW(海运报价!$C$2:$C$2000)-ROW(海运报价!$C$2)+1)/((海运报价!$D$2:$D$2000=$BE6)*(海运报价!$E$2:$E$2000=$BF6)),4)),"")) | BS6: =IF(OR($BE6="",$BF6=""),"",IFERROR(INDEX(海运报价!$C$2:$C$2000,AGGREGATE(15,6,(ROW(海运报价!$C$2:$C$2000)-ROW(海运报价!$C$2)+1)/((海运报价!$D$2:$D$2000=$BE6)*(海运报价!$E$2:$E$2000=$BF6)),5)),"")) | BT6: =IF(OR($BE6="",$BF6=""),"",IFERROR(INDEX(海运报价!$C$2:$C$2000,AGGREGATE(15,6,(ROW(海运报价!$C$2:$C$2000)-ROW(海运报价!$C$2)+1)/((海运报价!$D$2:$D$2000=$BE6)*(海运报价!$E$2:$E$2000=$BF6)),6)),"")) | BU6: =IF(OR($BE6="",$BF6=""),"",IFERROR(INDEX(海运报价!$C$2:$C$2000,AGGREGATE(15,6,(ROW(海运报价!$C$2:$C$2000)-ROW(海运报价!$C$2)+1)/((海运报价!$D$2:$D$2000=$BE6)*(海运报价!$E$2:$E$2000=$BF6)),7)),"")) | BV6: =IF(OR($BE6="",$BF6=""),"",IFERROR(INDEX(海运报价!$C$2:$C$2000,AGGREGATE(15,6,(ROW(海运报价!$C$2:$C$2000)-ROW(海运报价!$C$2)+1)/((海运报价!$D$2:$D$2000=$BE6)*(海运报价!$E$2:$E$2000=$BF6)),8)),"")) | BW6: =IF(OR($BE6="",$BF6=""),"",IFERROR(INDEX(海运报价!$C$2:$C$2000,AGGREGATE(15,6,(ROW(海运报价!$C$2:$C$2000)-ROW(海运报价!$C$2)+1)/((海运报价!$D$2:$D$2000=$BE6)*(海运报价!$E$2:$E$2000=$BF6)),9)),"")) | BX6: =IF(OR($BE6="",$BF6=""),"",IFERROR(INDEX(海运报价!$C$2:$C$2000,AGGREGATE(15,6,(ROW(海运报价!$C$2:$C$2000)-ROW(海运报价!$C$2)+1)/((海运报价!$D$2:$D$2000=$BE6)*(海运报价!$E$2:$E$2000=$BF6)),10)),"")) | BY6: =IF(OR($BE6="",$BF6=""),"",IFERROR(INDEX(海运报价!$C$2:$C$2000,AGGREGATE(15,6,(ROW(海运报价!$C$2:$C$2000)-ROW(海运报价!$C$2)+1)/((海运报价!$D$2:$D$2000=$BE6)*(海运报价!$E$2:$E$2000=$BF6)),11)),"")) | BZ6: =IF(OR($BE6="",$BF6=""),"",IFERROR(INDEX(海运报价!$C$2:$C$2000,AGGREGATE(15,6,(ROW(海运报价!$C$2:$C$2000)-ROW(海运报价!$C$2)+1)/((海运报价!$D$2:$D$2000=$BE6)*(海运报价!$E$2:$E$2000=$BF6)),12)),"")) | CA6: =IF(OR($BE6="",$BF6=""),"",IFERROR(INDEX(海运报价!$C$2:$C$2000,AGGREGATE(15,6,(ROW(海运报价!$C$2:$C$2000)-ROW(海运报价!$C$2)+1)/((海运报价!$D$2:$D$2000=$BE6)*(海运报价!$E$2:$E$2000=$BF6)),13)),"")) | CB6: =IF(OR($BE6="",$BF6=""),"",IFERROR(INDEX(海运报价!$C$2:$C$2000,AGGREGATE(15,6,(ROW(海运报价!$C$2:$C$2000)-ROW(海运报价!$C$2)+1)/((海运报价!$D$2:$D$2000=$BE6)*(海运报价!$E$2:$E$2000=$BF6)),14)),"")) | CC6: =IF(OR($BE6="",$BF6=""),"",IFERROR(INDEX(海运报价!$C$2:$C$2000,AGGREGATE(15,6,(ROW(海运报价!$C$2:$C$2000)-ROW(海运报价!$C$2)+1)/((海运报价!$D$2:$D$2000=$BE6)*(海运报价!$E$2:$E$2000=$BF6)),15)),"")) | CD6: =IF(OR(X6="",M6=""),"",X6+IF(OR(AA6="",M6=""),0,AA6/M6)+IF(AB6="",0,AB6)+IF(AI6="",0,AI6)+IF(Z6="",0,Z6)) | CE6: =I6+J6+K6+L6+AG6
C7: 2'8' | D7: =IF(C7="","",VLOOKUP($C7,箱规!$A$2:$S$23,9,FALSE)) | G7: =IF(OR(CD7="",CE7="",CE7>=1,X7=""),"",ROUNDUP((CD7-0.13*X7/1.13)/(1-CE7),2)) | H7: =IF(OR(CD7="",CE7="",X7=""),"",IF((1-CE7-参数!$B$16)<=0,"费率过高",ROUND((CD7-0.13*X7/1.13)/(1-CE7-参数!$B$16),2))) | I7: 0.15 | J7: 0.07 | K7: 0.15 | L7: 0.01 | M7: =参数!$B$2 | N7: =IF(C7="","",VLOOKUP($C7,箱规!$A$2:$S$23,14,FALSE)) | O7: =IF(C7="","",VLOOKUP($C7,箱规!$A$2:$S$23,5,FALSE)) | P7: =IF(C7="","",VLOOKUP($C7,箱规!$A$2:$S$23,6,FALSE)) | Q7: =IF(C7="","",VLOOKUP($C7,箱规!$A$2:$S$23,7,FALSE)) | R7: =IF(OR(N7="",O7="",P7="",Q7=""),"",MAX(N7*FBA规则!$B$6,(O7/FBA规则!$B$5)*(P7/FBA规则!$B$5)*(Q7/FBA规则!$B$5)/FBA规则!$B$7)) | S7: =IF(R7="","",IF(AND(N7*FBA规则!$B$6<=1,MAX(O7,P7,Q7)/FBA规则!$B$5<=15,MEDIAN(O7,P7,Q7)/FBA规则!$B$5<=12,MIN(O7,P7,Q7)/FBA规则!$B$5<=0.75),"小标准",IF(AND(R7<=20,MAX(O7,P7,Q7)/FBA规则!$B$5<=18,MEDIAN(O7,P7,Q7)/FBA规则!$B$5<=14,MIN(O7,P7,Q7)/FBA规则!$B$5<=8),"大标准",IF(AND(R7<=50,MAX(O7,P7,Q7)/FBA规则!$B$5<=59,MEDIAN(O7,P7,Q7)/FBA规则!$B$5<=33,MIN(O7,P7,Q7)/FBA规则!$B$5<=33,T7<=130),"大件",IF(R7<=50,"超大0-50lb",IF(R7<=70,"超大50-70lb",IF(R7<=150,"超大70-150lb","超大150lb+"))))))) | T7: =IF(OR(O7="",P7="",Q7=""),"",MAX(O7,P7,Q7)/FBA规则!$B$5+2*((MEDIAN(O7,P7,Q7)+MIN(O7,P7,Q7))/FBA规则!$B$5)) | U7: =参数!$B$15 | V7: =IF(OR(C7="",U7=""),"",(IF(OR(VLOOKUP($C7,箱规!$A$2:$S$23,4,FALSE)="",VLOOKUP($C7,箱规!$A$2:$S$23,4,FALSE)=0),VLOOKUP($C7,箱规!$A$2:$S$23,2,FALSE)*VLOOKUP($C7,箱规!$A$2:$S$23,3,FALSE)/10000,VLOOKUP($C7,箱规!$A$2:$S$23,4,FALSE)))*U7) | X7: =IF(AND(V7<>"",M7<>""),V7/M7,IF(AND(W7<>"",M7<>""),W7*1.13/M7,"")) | Y7: =IF(OR(X7="",G7=""),"",X7/G7) | AA7: =IF(OR(D7="",D7=0),"",IF(BG7="陆运",IF(BL7="",0,BL7)/D7,IF(BG7="海运",IF(BK7="",0,BK7)/D7,IF(BG7="海运+陆运",(IF(BK7="",0,BK7)+IF(BL7="",0,BL7))/D7,IF(BK7="",0,BK7)/D7)))) | AB7: =IF(OR(S7="",R7="",参数!$B$23=""),"",IF(S7="小标准",IFERROR(INDEX(FBA规则!$B$58:$C$65,MATCH(N7*FBA规则!$B$6*16,FBA规则!$A$58:$A$65,1),IF(参数!$B$23="旺季",2,1)),INDEX(FBA规则!$B$65:$C$65,1,IF(参数!$B$23="旺季",2,1))),IF(S7="大标准",IF(R7<=3,IFERROR(INDEX(FBA规则!$B$35:$C$46,MATCH(R7,FBA规则!$A$35:$A$46,1),IF(参数!$B$23="旺季",2,1)),INDEX(FBA规则!$B$46:$C$46,1,IF(参数!$B$23="旺季",2,1))),INDEX(FBA规则!$B$47:$C$47,1,IF(参数!$B$23="旺季",2,1))+FBA规则!$D$47*CEILING((R7-3)*4,1)),IF(S7="大件",INDEX(FBA规则!$B$50:$C$50,1,IF(参数!$B$23="旺季",2,1))+FBA规则!$D$50*MAX(0,CEILING(R7,1)-1),IF(S7="超大0-50lb",INDEX(FBA规则!$B$51:$C$51,1,IF(参数!$B$23="旺季",2,1))+FBA规则!$D$51*MAX(0,CEILING(R7,1)-1),IF(S7="超大50-70lb",INDEX(FBA规则!$B$52:$C$52,1,IF(参数!$B$23="旺季",2,1))+FBA规则!$D$52*MAX(0,R7-FBA规则!$F$52),IF(S7="超大70-150lb",INDEX(FBA规则!$B$53:$C$53,1,IF(参数!$B$23="旺季",2,1))+FBA规则!$D$53*MAX(0,R7-FBA规则!$F$53),INDEX(FBA规则!$B$54:$C$54,1,IF(参数!$B$23="旺季",2,1))+FBA规则!$D$54*MAX(0,R7-FBA规则!$F$54)))))))) | AC7: =IF(OR(G7="",I7=""),"",G7*I7) | AD7: =IF(OR(G7="",J7=""),"",G7*J7) | AE7: =IF(OR(G7="",K7=""),"",G7*K7) | AF7: =IF(OR(G7="",L7=""),"",G7*L7) | AG7: 0.02 | AH7: =IF(OR(G7="",AG7=""),"",G7*AG7) | AJ7: =IF(X7="","",X7+IF(OR(AA7="",M7=""),0,AA7/M7)+SUM(AB7:AF7)+IF(AH7="",0,AH7)+IF(AI7="",0,AI7)) | AK7: =IF(X7="","",0.13*X7/1.13) | AL7: =IF(OR(G7="",AJ7=""),"",G7+AK7-AJ7) | AM7: =IF(OR(AL7="",G7=""),"",AL7/G7) | AN7: =IF(OR(X7="",H7=""),"",X7/H7) | AP7: =AA7 | AQ7: =IF(OR(S7="",R7="",参数!$B$23=""),"",IF(S7="小标准",IFERROR(INDEX(FBA规则!$B$58:$C$65,MATCH(N7*FBA规则!$B$6*16,FBA规则!$A$58:$A$65,1),IF(参数!$B$23="旺季",2,1)),INDEX(FBA规则!$B$65:$C$65,1,IF(参数!$B$23="旺季",2,1))),IF(S7="大标准",IF(R7<=3,IFERROR(INDEX(FBA规则!$B$35:$C$46,MATCH(R7,FBA规则!$A$35:$A$46,1),IF(参数!$B$23="旺季",2,1)),INDEX(FBA规则!$B$46:$C$46,1,IF(参数!$B$23="旺季",2,1))),INDEX(FBA规则!$B$47:$C$47,1,IF(参数!$B$23="旺季",2,1))+FBA规则!$D$47*CEILING((R7-3)*4,1)),IF(S7="大件",INDEX(FBA规则!$B$50:$C$50,1,IF(参数!$B$23="旺季",2,1))+FBA规则!$D$50*MAX(0,CEILING(R7,1)-1),IF(S7="超大0-50lb",INDEX(FBA规则!$B$51:$C$51,1,IF(参数!$B$23="旺季",2,1))+FBA规则!$D$51*MAX(0,CEILING(R7,1)-1),IF(S7="超大50-70lb",INDEX(FBA规则!$B$52:$C$52,1,IF(参数!$B$23="旺季",2,1))+FBA规则!$D$52*MAX(0,R7-FBA规则!$F$52),IF(S7="超大70-150lb",INDEX(FBA规则!$B$53:$C$53,1,IF(参数!$B$23="旺季",2,1))+FBA规则!$D$53*MAX(0,R7-FBA规则!$F$53),INDEX(FBA规则!$B$54:$C$54,1,IF(参数!$B$23="旺季",2,1))+FBA规则!$D$54*MAX(0,R7-FBA规则!$F$54)))))))) | AR7: =IF(OR(H7="",I7=""),"",H7*I7) | AS7: =IF(OR(H7="",J7=""),"",H7*J7) | AT7: =IF(OR(H7="",K7=""),"",H7*K7) | AU7: =IF(OR(H7="",L7=""),"",H7*L7) | AV7: 0.02 | AW7: =IF(OR(H7="",AV7=""),"",H7*AV7) | AY7: =IF(X7="","",X7+IF(OR(AP7="",M7=""),0,AP7/M7)+SUM(AQ7:AU7)+IF(AW7="",0,AW7)+IF(AX7="",0,AX7)) | AZ7: =IF(X7="","",0.13*X7/1.13) | BA7: =IF(OR(H7="",AY7=""),"",H7+AZ7-AY7) | BB7: =IF(OR(BA7="",H7=""),"",BA7/H7) | BC7: =IF(OR(H7="",AY7=""),"",H7-AY7) | BD7: =IF(OR(BC7="",H7=""),"",BC7/H7) | BE7: 义乌 | BF7: ABE8 | BG7: 海运 | BH7: （最低价） | BI7: =IF(OR(BE7="",BF7=""),"",IF(AND(BH7<>"",BH7<>"（最低价）"),IFERROR(IF(SUMIFS(海运报价!$F$2:$F$2000,海运报价!$C$2:$C$2000,BH7,海运报价!$D$2:$D$2000,BE7,海运报价!$E$2:$E$2000,BF7)=0,"",SUMIFS(海运报价!$F$2:$F$2000,海运报价!$C$2:$C$2000,BH7,海运报价!$D$2:$D$2000,BE7,海运报价!$E$2:$E$2000,BF7)),""),IFERROR(IF(SUMIFS(海运下拉!$H$2:$H$311,海运下拉!$F$2:$F$311,BE7,海运下拉!$G$2:$G$311,BF7)=0,"",SUMIFS(海运下拉!$H$2:$H$311,海运下拉!$F$2:$F$311,BE7,海运下拉!$G$2:$G$311,BF7)),""))) | BJ7: =IF(C7="","",VLOOKUP($C7,箱规!$A$2:$S$23,18,FALSE)) | BK7: =IF(OR(BI7="",BJ7=""),"",BJ7*(BI7+IF(AND(BH7<>"",BH7<>"（最低价）"),IFERROR(AVERAGEIFS(海运报价!$H$2:$H$2000,海运报价!$C$2:$C$2000,BH7,海运报价!$D$2:$D$2000,BE7,海运报价!$E$2:$E$2000,BF7),0),IFERROR(SUMIFS(海运下拉!$J$2:$J$311,海运下拉!$F$2:$F$311,BE7,海运下拉!$G$2:$G$311,BF7),0)))) | BM7: =IF(OR(BE7="",BF7=""),"请选起运地+FBA仓",IF(AND(AND(BH7<>"",BH7<>"（最低价）"),BI7=""),"⚠该渠道不服务此仓：请重选渠道，或选「（最低价）」",IF(BI7="","无报价：请换起运地/仓库",IF(AND(BH7<>"",BH7<>"（最低价）"),"按你选的渠道「"&BH7&"」计价","按最低价「"&IFERROR(SUMIFS(海运下拉!$I$2:$I$311,海运下拉!$F$2:$F$311,BE7,海运下拉!$G$2:$G$311,BF7),"")&"」（渠道默认最低价）")))) | BO7: =IF(OR($BE7="",$BF7=""),"",IFERROR(INDEX(海运报价!$C$2:$C$2000,AGGREGATE(15,6,(ROW(海运报价!$C$2:$C$2000)-ROW(海运报价!$C$2)+1)/((海运报价!$D$2:$D$2000=$BE7)*(海运报价!$E$2:$E$2000=$BF7)),1)),"")) | BP7: =IF(OR($BE7="",$BF7=""),"",IFERROR(INDEX(海运报价!$C$2:$C$2000,AGGREGATE(15,6,(ROW(海运报价!$C$2:$C$2000)-ROW(海运报价!$C$2)+1)/((海运报价!$D$2:$D$2000=$BE7)*(海运报价!$E$2:$E$2000=$BF7)),2)),"")) | BQ7: =IF(OR($BE7="",$BF7=""),"",IFERROR(INDEX(海运报价!$C$2:$C$2000,AGGREGATE(15,6,(ROW(海运报价!$C$2:$C$2000)-ROW(海运报价!$C$2)+1)/((海运报价!$D$2:$D$2000=$BE7)*(海运报价!$E$2:$E$2000=$BF7)),3)),"")) | BR7: =IF(OR($BE7="",$BF7=""),"",IFERROR(INDEX(海运报价!$C$2:$C$2000,AGGREGATE(15,6,(ROW(海运报价!$C$2:$C$2000)-ROW(海运报价!$C$2)+1)/((海运报价!$D$2:$D$2000=$BE7)*(海运报价!$E$2:$E$2000=$BF7)),4)),"")) | BS7: =IF(OR($BE7="",$BF7=""),"",IFERROR(INDEX(海运报价!$C$2:$C$2000,AGGREGATE(15,6,(ROW(海运报价!$C$2:$C$2000)-ROW(海运报价!$C$2)+1)/((海运报价!$D$2:$D$2000=$BE7)*(海运报价!$E$2:$E$2000=$BF7)),5)),"")) | BT7: =IF(OR($BE7="",$BF7=""),"",IFERROR(INDEX(海运报价!$C$2:$C$2000,AGGREGATE(15,6,(ROW(海运报价!$C$2:$C$2000)-ROW(海运报价!$C$2)+1)/((海运报价!$D$2:$D$2000=$BE7)*(海运报价!$E$2:$E$2000=$BF7)),6)),"")) | BU7: =IF(OR($BE7="",$BF7=""),"",IFERROR(INDEX(海运报价!$C$2:$C$2000,AGGREGATE(15,6,(ROW(海运报价!$C$2:$C$2000)-ROW(海运报价!$C$2)+1)/((海运报价!$D$2:$D$2000=$BE7)*(海运报价!$E$2:$E$2000=$BF7)),7)),"")) | BV7: =IF(OR($BE7="",$BF7=""),"",IFERROR(INDEX(海运报价!$C$2:$C$2000,AGGREGATE(15,6,(ROW(海运报价!$C$2:$C$2000)-ROW(海运报价!$C$2)+1)/((海运报价!$D$2:$D$2000=$BE7)*(海运报价!$E$2:$E$2000=$BF7)),8)),"")) | BW7: =IF(OR($BE7="",$BF7=""),"",IFERROR(INDEX(海运报价!$C$2:$C$2000,AGGREGATE(15,6,(ROW(海运报价!$C$2:$C$2000)-ROW(海运报价!$C$2)+1)/((海运报价!$D$2:$D$2000=$BE7)*(海运报价!$E$2:$E$2000=$BF7)),9)),"")) | BX7: =IF(OR($BE7="",$BF7=""),"",IFERROR(INDEX(海运报价!$C$2:$C$2000,AGGREGATE(15,6,(ROW(海运报价!$C$2:$C$2000)-ROW(海运报价!$C$2)+1)/((海运报价!$D$2:$D$2000=$BE7)*(海运报价!$E$2:$E$2000=$BF7)),10)),"")) | BY7: =IF(OR($BE7="",$BF7=""),"",IFERROR(INDEX(海运报价!$C$2:$C$2000,AGGREGATE(15,6,(ROW(海运报价!$C$2:$C$2000)-ROW(海运报价!$C$2)+1)/((海运报价!$D$2:$D$2000=$BE7)*(海运报价!$E$2:$E$2000=$BF7)),11)),"")) | BZ7: =IF(OR($BE7="",$BF7=""),"",IFERROR(INDEX(海运报价!$C$2:$C$2000,AGGREGATE(15,6,(ROW(海运报价!$C$2:$C$2000)-ROW(海运报价!$C$2)+1)/((海运报价!$D$2:$D$2000=$BE7)*(海运报价!$E$2:$E$2000=$BF7)),12)),"")) | CA7: =IF(OR($BE7="",$BF7=""),"",IFERROR(INDEX(海运报价!$C$2:$C$2000,AGGREGATE(15,6,(ROW(海运报价!$C$2:$C$2000)-ROW(海运报价!$C$2)+1)/((海运报价!$D$2:$D$2000=$BE7)*(海运报价!$E$2:$E$2000=$BF7)),13)),"")) | CB7: =IF(OR($BE7="",$BF7=""),"",IFERROR(INDEX(海运报价!$C$2:$C$2000,AGGREGATE(15,6,(ROW(海运报价!$C$2:$C$2000)-ROW(海运报价!$C$2)+1)/((海运报价!$D$2:$D$2000=$BE7)*(海运报价!$E$2:$E$2000=$BF7)),14)),"")) | CC7: =IF(OR($BE7="",$BF7=""),"",IFERROR(INDEX(海运报价!$C$2:$C$2000,AGGREGATE(15,6,(ROW(海运报价!$C$2:$C$2000)-ROW(海运报价!$C$2)+1)/((海运报价!$D$2:$D$2000=$BE7)*(海运报价!$E$2:$E$2000=$BF7)),15)),"")) | CD7: =IF(OR(X7="",M7=""),"",X7+IF(OR(AA7="",M7=""),0,AA7/M7)+IF(AB7="",0,AB7)+IF(AI7="",0,AI7)+IF(Z7="",0,Z7)) | CE7: =I7+J7+K7+L7+AG7
C8: 2'10' | D8: =IF(C8="","",VLOOKUP($C8,箱规!$A$2:$S$23,9,FALSE)) | G8: =IF(OR(CD8="",CE8="",CE8>=1,X8=""),"",ROUNDUP((CD8-0.13*X8/1.13)/(1-CE8),2)) | H8: =IF(OR(CD8="",CE8="",X8=""),"",IF((1-CE8-参数!$B$16)<=0,"费率过高",ROUND((CD8-0.13*X8/1.13)/(1-CE8-参数!$B$16),2))) | I8: 0.15 | J8: 0.07 | K8: 0.15 | L8: 0.01 | M8: =参数!$B$2 | N8: =IF(C8="","",VLOOKUP($C8,箱规!$A$2:$S$23,14,FALSE)) | O8: =IF(C8="","",VLOOKUP($C8,箱规!$A$2:$S$23,5,FALSE)) | P8: =IF(C8="","",VLOOKUP($C8,箱规!$A$2:$S$23,6,FALSE)) | Q8: =IF(C8="","",VLOOKUP($C8,箱规!$A$2:$S$23,7,FALSE)) | R8: =IF(OR(N8="",O8="",P8="",Q8=""),"",MAX(N8*FBA规则!$B$6,(O8/FBA规则!$B$5)*(P8/FBA规则!$B$5)*(Q8/FBA规则!$B$5)/FBA规则!$B$7)) | S8: =IF(R8="","",IF(AND(N8*FBA规则!$B$6<=1,MAX(O8,P8,Q8)/FBA规则!$B$5<=15,MEDIAN(O8,P8,Q8)/FBA规则!$B$5<=12,MIN(O8,P8,Q8)/FBA规则!$B$5<=0.75),"小标准",IF(AND(R8<=20,MAX(O8,P8,Q8)/FBA规则!$B$5<=18,MEDIAN(O8,P8,Q8)/FBA规则!$B$5<=14,MIN(O8,P8,Q8)/FBA规则!$B$5<=8),"大标准",IF(AND(R8<=50,MAX(O8,P8,Q8)/FBA规则!$B$5<=59,MEDIAN(O8,P8,Q8)/FBA规则!$B$5<=33,MIN(O8,P8,Q8)/FBA规则!$B$5<=33,T8<=130),"大件",IF(R8<=50,"超大0-50lb",IF(R8<=70,"超大50-70lb",IF(R8<=150,"超大70-150lb","超大150lb+"))))))) | T8: =IF(OR(O8="",P8="",Q8=""),"",MAX(O8,P8,Q8)/FBA规则!$B$5+2*((MEDIAN(O8,P8,Q8)+MIN(O8,P8,Q8))/FBA规则!$B$5)) | U8: =参数!$B$15 | V8: =IF(OR(C8="",U8=""),"",(IF(OR(VLOOKUP($C8,箱规!$A$2:$S$23,4,FALSE)="",VLOOKUP($C8,箱规!$A$2:$S$23,4,FALSE)=0),VLOOKUP($C8,箱规!$A$2:$S$23,2,FALSE)*VLOOKUP($C8,箱规!$A$2:$S$23,3,FALSE)/10000,VLOOKUP($C8,箱规!$A$2:$S$23,4,FALSE)))*U8) | X8: =IF(AND(V8<>"",M8<>""),V8/M8,IF(AND(W8<>"",M8<>""),W8*1.13/M8,"")) | Y8: =IF(OR(X8="",G8=""),"",X8/G8) | AA8: =IF(OR(D8="",D8=0),"",IF(BG8="陆运",IF(BL8="",0,BL8)/D8,IF(BG8="海运",IF(BK8="",0,BK8)/D8,IF(BG8="海运+陆运",(IF(BK8="",0,BK8)+IF(BL8="",0,BL8))/D8,IF(BK8="",0,BK8)/D8)))) | AB8: =IF(OR(S8="",R8="",参数!$B$23=""),"",IF(S8="小标准",IFERROR(INDEX(FBA规则!$B$58:$C$65,MATCH(N8*FBA规则!$B$6*16,FBA规则!$A$58:$A$65,1),IF(参数!$B$23="旺季",2,1)),INDEX(FBA规则!$B$65:$C$65,1,IF(参数!$B$23="旺季",2,1))),IF(S8="大标准",IF(R8<=3,IFERROR(INDEX(FBA规则!$B$35:$C$46,MATCH(R8,FBA规则!$A$35:$A$46,1),IF(参数!$B$23="旺季",2,1)),INDEX(FBA规则!$B$46:$C$46,1,IF(参数!$B$23="旺季",2,1))),INDEX(FBA规则!$B$47:$C$47,1,IF(参数!$B$23="旺季",2,1))+FBA规则!$D$47*CEILING((R8-3)*4,1)),IF(S8="大件",INDEX(FBA规则!$B$50:$C$50,1,IF(参数!$B$23="旺季",2,1))+FBA规则!$D$50*MAX(0,CEILING(R8,1)-1),IF(S8="超大0-50lb",INDEX(FBA规则!$B$51:$C$51,1,IF(参数!$B$23="旺季",2,1))+FBA规则!$D$51*MAX(0,CEILING(R8,1)-1),IF(S8="超大50-70lb",INDEX(FBA规则!$B$52:$C$52,1,IF(参数!$B$23="旺季",2,1))+FBA规则!$D$52*MAX(0,R8-FBA规则!$F$52),IF(S8="超大70-150lb",INDEX(FBA规则!$B$53:$C$53,1,IF(参数!$B$23="旺季",2,1))+FBA规则!$D$53*MAX(0,R8-FBA规则!$F$53),INDEX(FBA规则!$B$54:$C$54,1,IF(参数!$B$23="旺季",2,1))+FBA规则!$D$54*MAX(0,R8-FBA规则!$F$54)))))))) | AC8: =IF(OR(G8="",I8=""),"",G8*I8) | AD8: =IF(OR(G8="",J8=""),"",G8*J8) | AE8: =IF(OR(G8="",K8=""),"",G8*K8) | AF8: =IF(OR(G8="",L8=""),"",G8*L8) | AG8: 0.02 | AH8: =IF(OR(G8="",AG8=""),"",G8*AG8) | AJ8: =IF(X8="","",X8+IF(OR(AA8="",M8=""),0,AA8/M8)+SUM(AB8:AF8)+IF(AH8="",0,AH8)+IF(AI8="",0,AI8)) | AK8: =IF(X8="","",0.13*X8/1.13) | AL8: =IF(OR(G8="",AJ8=""),"",G8+AK8-AJ8) | AM8: =IF(OR(AL8="",G8=""),"",AL8/G8) | AN8: =IF(OR(X8="",H8=""),"",X8/H8) | AP8: =AA8 | AQ8: =IF(OR(S8="",R8="",参数!$B$23=""),"",IF(S8="小标准",IFERROR(INDEX(FBA规则!$B$58:$C$65,MATCH(N8*FBA规则!$B$6*16,FBA规则!$A$58:$A$65,1),IF(参数!$B$23="旺季",2,1)),INDEX(FBA规则!$B$65:$C$65,1,IF(参数!$B$23="旺季",2,1))),IF(S8="大标准",IF(R8<=3,IFERROR(INDEX(FBA规则!$B$35:$C$46,MATCH(R8,FBA规则!$A$35:$A$46,1),IF(参数!$B$23="旺季",2,1)),INDEX(FBA规则!$B$46:$C$46,1,IF(参数!$B$23="旺季",2,1))),INDEX(FBA规则!$B$47:$C$47,1,IF(参数!$B$23="旺季",2,1))+FBA规则!$D$47*CEILING((R8-3)*4,1)),IF(S8="大件",INDEX(FBA规则!$B$50:$C$50,1,IF(参数!$B$23="旺季",2,1))+FBA规则!$D$50*MAX(0,CEILING(R8,1)-1),IF(S8="超大0-50lb",INDEX(FBA规则!$B$51:$C$51,1,IF(参数!$B$23="旺季",2,1))+FBA规则!$D$51*MAX(0,CEILING(R8,1)-1),IF(S8="超大50-70lb",INDEX(FBA规则!$B$52:$C$52,1,IF(参数!$B$23="旺季",2,1))+FBA规则!$D$52*MAX(0,R8-FBA规则!$F$52),IF(S8="超大70-150lb",INDEX(FBA规则!$B$53:$C$53,1,IF(参数!$B$23="旺季",2,1))+FBA规则!$D$53*MAX(0,R8-FBA规则!$F$53),INDEX(FBA规则!$B$54:$C$54,1,IF(参数!$B$23="旺季",2,1))+FBA规则!$D$54*MAX(0,R8-FBA规则!$F$54)))))))) | AR8: =IF(OR(H8="",I8=""),"",H8*I8) | AS8: =IF(OR(H8="",J8=""),"",H8*J8) | AT8: =IF(OR(H8="",K8=""),"",H8*K8) | AU8: =IF(OR(H8="",L8=""),"",H8*L8) | AV8: 0.02 | AW8: =IF(OR(H8="",AV8=""),"",H8*AV8) | AY8: =IF(X8="","",X8+IF(OR(AP8="",M8=""),0,AP8/M8)+SUM(AQ8:AU8)+IF(AW8="",0,AW8)+IF(AX8="",0,AX8)) | AZ8: =IF(X8="","",0.13*X8/1.13) | BA8: =IF(OR(H8="",AY8=""),"",H8+AZ8-AY8) | BB8: =IF(OR(BA8="",H8=""),"",BA8/H8) | BC8: =IF(OR(H8="",AY8=""),"",H8-AY8) | BD8: =IF(OR(BC8="",H8=""),"",BC8/H8) | BE8: 义乌 | BF8: ABE8 | BG8: 海运 | BH8: （最低价） | BI8: =IF(OR(BE8="",BF8=""),"",IF(AND(BH8<>"",BH8<>"（最低价）"),IFERROR(IF(SUMIFS(海运报价!$F$2:$F$2000,海运报价!$C$2:$C$2000,BH8,海运报价!$D$2:$D$2000,BE8,海运报价!$E$2:$E$2000,BF8)=0,"",SUMIFS(海运报价!$F$2:$F$2000,海运报价!$C$2:$C$2000,BH8,海运报价!$D$2:$D$2000,BE8,海运报价!$E$2:$E$2000,BF8)),""),IFERROR(IF(SUMIFS(海运下拉!$H$2:$H$311,海运下拉!$F$2:$F$311,BE8,海运下拉!$G$2:$G$311,BF8)=0,"",SUMIFS(海运下拉!$H$2:$H$311,海运下拉!$F$2:$F$311,BE8,海运下拉!$G$2:$G$311,BF8)),""))) | BJ8: =IF(C8="","",VLOOKUP($C8,箱规!$A$2:$S$23,18,FALSE)) | BK8: =IF(OR(BI8="",BJ8=""),"",BJ8*(BI8+IF(AND(BH8<>"",BH8<>"（最低价）"),IFERROR(AVERAGEIFS(海运报价!$H$2:$H$2000,海运报价!$C$2:$C$2000,BH8,海运报价!$D$2:$D$2000,BE8,海运报价!$E$2:$E$2000,BF8),0),IFERROR(SUMIFS(海运下拉!$J$2:$J$311,海运下拉!$F$2:$F$311,BE8,海运下拉!$G$2:$G$311,BF8),0)))) | BM8: =IF(OR(BE8="",BF8=""),"请选起运地+FBA仓",IF(AND(AND(BH8<>"",BH8<>"（最低价）"),BI8=""),"⚠该渠道不服务此仓：请重选渠道，或选「（最低价）」",IF(BI8="","无报价：请换起运地/仓库",IF(AND(BH8<>"",BH8<>"（最低价）"),"按你选的渠道「"&BH8&"」计价","按最低价「"&IFERROR(SUMIFS(海运下拉!$I$2:$I$311,海运下拉!$F$2:$F$311,BE8,海运下拉!$G$2:$G$311,BF8),"")&"」（渠道默认最低价）")))) | BO8: =IF(OR($BE8="",$BF8=""),"",IFERROR(INDEX(海运报价!$C$2:$C$2000,AGGREGATE(15,6,(ROW(海运报价!$C$2:$C$2000)-ROW(海运报价!$C$2)+1)/((海运报价!$D$2:$D$2000=$BE8)*(海运报价!$E$2:$E$2000=$BF8)),1)),"")) | BP8: =IF(OR($BE8="",$BF8=""),"",IFERROR(INDEX(海运报价!$C$2:$C$2000,AGGREGATE(15,6,(ROW(海运报价!$C$2:$C$2000)-ROW(海运报价!$C$2)+1)/((海运报价!$D$2:$D$2000=$BE8)*(海运报价!$E$2:$E$2000=$BF8)),2)),"")) | BQ8: =IF(OR($BE8="",$BF8=""),"",IFERROR(INDEX(海运报价!$C$2:$C$2000,AGGREGATE(15,6,(ROW(海运报价!$C$2:$C$2000)-ROW(海运报价!$C$2)+1)/((海运报价!$D$2:$D$2000=$BE8)*(海运报价!$E$2:$E$2000=$BF8)),3)),"")) | BR8: =IF(OR($BE8="",$BF8=""),"",IFERROR(INDEX(海运报价!$C$2:$C$2000,AGGREGATE(15,6,(ROW(海运报价!$C$2:$C$2000)-ROW(海运报价!$C$2)+1)/((海运报价!$D$2:$D$2000=$BE8)*(海运报价!$E$2:$E$2000=$BF8)),4)),"")) | BS8: =IF(OR($BE8="",$BF8=""),"",IFERROR(INDEX(海运报价!$C$2:$C$2000,AGGREGATE(15,6,(ROW(海运报价!$C$2:$C$2000)-ROW(海运报价!$C$2)+1)/((海运报价!$D$2:$D$2000=$BE8)*(海运报价!$E$2:$E$2000=$BF8)),5)),"")) | BT8: =IF(OR($BE8="",$BF8=""),"",IFERROR(INDEX(海运报价!$C$2:$C$2000,AGGREGATE(15,6,(ROW(海运报价!$C$2:$C$2000)-ROW(海运报价!$C$2)+1)/((海运报价!$D$2:$D$2000=$BE8)*(海运报价!$E$2:$E$2000=$BF8)),6)),"")) | BU8: =IF(OR($BE8="",$BF8=""),"",IFERROR(INDEX(海运报价!$C$2:$C$2000,AGGREGATE(15,6,(ROW(海运报价!$C$2:$C$2000)-ROW(海运报价!$C$2)+1)/((海运报价!$D$2:$D$2000=$BE8)*(海运报价!$E$2:$E$2000=$BF8)),7)),"")) | BV8: =IF(OR($BE8="",$BF8=""),"",IFERROR(INDEX(海运报价!$C$2:$C$2000,AGGREGATE(15,6,(ROW(海运报价!$C$2:$C$2000)-ROW(海运报价!$C$2)+1)/((海运报价!$D$2:$D$2000=$BE8)*(海运报价!$E$2:$E$2000=$BF8)),8)),"")) | BW8: =IF(OR($BE8="",$BF8=""),"",IFERROR(INDEX(海运报价!$C$2:$C$2000,AGGREGATE(15,6,(ROW(海运报价!$C$2:$C$2000)-ROW(海运报价!$C$2)+1)/((海运报价!$D$2:$D$2000=$BE8)*(海运报价!$E$2:$E$2000=$BF8)),9)),"")) | BX8: =IF(OR($BE8="",$BF8=""),"",IFERROR(INDEX(海运报价!$C$2:$C$2000,AGGREGATE(15,6,(ROW(海运报价!$C$2:$C$2000)-ROW(海运报价!$C$2)+1)/((海运报价!$D$2:$D$2000=$BE8)*(海运报价!$E$2:$E$2000=$BF8)),10)),"")) | BY8: =IF(OR($BE8="",$BF8=""),"",IFERROR(INDEX(海运报价!$C$2:$C$2000,AGGREGATE(15,6,(ROW(海运报价!$C$2:$C$2000)-ROW(海运报价!$C$2)+1)/((海运报价!$D$2:$D$2000=$BE8)*(海运报价!$E$2:$E$2000=$BF8)),11)),"")) | BZ8: =IF(OR($BE8="",$BF8=""),"",IFERROR(INDEX(海运报价!$C$2:$C$2000,AGGREGATE(15,6,(ROW(海运报价!$C$2:$C$2000)-ROW(海运报价!$C$2)+1)/((海运报价!$D$2:$D$2000=$BE8)*(海运报价!$E$2:$E$2000=$BF8)),12)),"")) | CA8: =IF(OR($BE8="",$BF8=""),"",IFERROR(INDEX(海运报价!$C$2:$C$2000,AGGREGATE(15,6,(ROW(海运报价!$C$2:$C$2000)-ROW(海运报价!$C$2)+1)/((海运报价!$D$2:$D$2000=$BE8)*(海运报价!$E$2:$E$2000=$BF8)),13)),"")) | CB8: =IF(OR($BE8="",$BF8=""),"",IFERROR(INDEX(海运报价!$C$2:$C$2000,AGGREGATE(15,6,(ROW(海运报价!$C$2:$C$2000)-ROW(海运报价!$C$2)+1)/((海运报价!$D$2:$D$2000=$BE8)*(海运报价!$E$2:$E$2000=$BF8)),14)),"")) | CC8: =IF(OR($BE8="",$BF8=""),"",IFERROR(INDEX(海运报价!$C$2:$C$2000,AGGREGATE(15,6,(ROW(海运报价!$C$2:$C$2000)-ROW(海运报价!$C$2)+1)/((海运报价!$D$2:$D$2000=$BE8)*(海运报价!$E$2:$E$2000=$BF8)),15)),"")) | CD8: =IF(OR(X8="",M8=""),"",X8+IF(OR(AA8="",M8=""),0,AA8/M8)+IF(AB8="",0,AB8)+IF(AI8="",0,AI8)+IF(Z8="",0,Z8)) | CE8: =I8+J8+K8+L8+AG8
C9: 3'5' | D9: =IF(C9="","",VLOOKUP($C9,箱规!$A$2:$S$23,9,FALSE)) | G9: =IF(OR(CD9="",CE9="",CE9>=1,X9=""),"",ROUNDUP((CD9-0.13*X9/1.13)/(1-CE9),2)) | H9: =IF(OR(CD9="",CE9="",X9=""),"",IF((1-CE9-参数!$B$16)<=0,"费率过高",ROUND((CD9-0.13*X9/1.13)/(1-CE9-参数!$B$16),2))) | I9: 0.15 | J9: 0.07 | K9: 0.15 | L9: 0.01 | M9: =参数!$B$2 | N9: =IF(C9="","",VLOOKUP($C9,箱规!$A$2:$S$23,14,FALSE)) | O9: =IF(C9="","",VLOOKUP($C9,箱规!$A$2:$S$23,5,FALSE)) | P9: =IF(C9="","",VLOOKUP($C9,箱规!$A$2:$S$23,6,FALSE)) | Q9: =IF(C9="","",VLOOKUP($C9,箱规!$A$2:$S$23,7,FALSE)) | R9: =IF(OR(N9="",O9="",P9="",Q9=""),"",MAX(N9*FBA规则!$B$6,(O9/FBA规则!$B$5)*(P9/FBA规则!$B$5)*(Q9/FBA规则!$B$5)/FBA规则!$B$7)) | S9: =IF(R9="","",IF(AND(N9*FBA规则!$B$6<=1,MAX(O9,P9,Q9)/FBA规则!$B$5<=15,MEDIAN(O9,P9,Q9)/FBA规则!$B$5<=12,MIN(O9,P9,Q9)/FBA规则!$B$5<=0.75),"小标准",IF(AND(R9<=20,MAX(O9,P9,Q9)/FBA规则!$B$5<=18,MEDIAN(O9,P9,Q9)/FBA规则!$B$5<=14,MIN(O9,P9,Q9)/FBA规则!$B$5<=8),"大标准",IF(AND(R9<=50,MAX(O9,P9,Q9)/FBA规则!$B$5<=59,MEDIAN(O9,P9,Q9)/FBA规则!$B$5<=33,MIN(O9,P9,Q9)/FBA规则!$B$5<=33,T9<=130),"大件",IF(R9<=50,"超大0-50lb",IF(R9<=70,"超大50-70lb",IF(R9<=150,"超大70-150lb","超大150lb+"))))))) | T9: =IF(OR(O9="",P9="",Q9=""),"",MAX(O9,P9,Q9)/FBA规则!$B$5+2*((MEDIAN(O9,P9,Q9)+MIN(O9,P9,Q9))/FBA规则!$B$5)) | U9: =参数!$B$15 | V9: =IF(OR(C9="",U9=""),"",(IF(OR(VLOOKUP($C9,箱规!$A$2:$S$23,4,FALSE)="",VLOOKUP($C9,箱规!$A$2:$S$23,4,FALSE)=0),VLOOKUP($C9,箱规!$A$2:$S$23,2,FALSE)*VLOOKUP($C9,箱规!$A$2:$S$23,3,FALSE)/10000,VLOOKUP($C9,箱规!$A$2:$S$23,4,FALSE)))*U9) | X9: =IF(AND(V9<>"",M9<>""),V9/M9,IF(AND(W9<>"",M9<>""),W9*1.13/M9,"")) | Y9: =IF(OR(X9="",G9=""),"",X9/G9) | AA9: =IF(OR(D9="",D9=0),"",IF(BG9="陆运",IF(BL9="",0,BL9)/D9,IF(BG9="海运",IF(BK9="",0,BK9)/D9,IF(BG9="海运+陆运",(IF(BK9="",0,BK9)+IF(BL9="",0,BL9))/D9,IF(BK9="",0,BK9)/D9)))) | AB9: =IF(OR(S9="",R9="",参数!$B$23=""),"",IF(S9="小标准",IFERROR(INDEX(FBA规则!$B$58:$C$65,MATCH(N9*FBA规则!$B$6*16,FBA规则!$A$58:$A$65,1),IF(参数!$B$23="旺季",2,1)),INDEX(FBA规则!$B$65:$C$65,1,IF(参数!$B$23="旺季",2,1))),IF(S9="大标准",IF(R9<=3,IFERROR(INDEX(FBA规则!$B$35:$C$46,MATCH(R9,FBA规则!$A$35:$A$46,1),IF(参数!$B$23="旺季",2,1)),INDEX(FBA规则!$B$46:$C$46,1,IF(参数!$B$23="旺季",2,1))),INDEX(FBA规则!$B$47:$C$47,1,IF(参数!$B$23="旺季",2,1))+FBA规则!$D$47*CEILING((R9-3)*4,1)),IF(S9="大件",INDEX(FBA规则!$B$50:$C$50,1,IF(参数!$B$23="旺季",2,1))+FBA规则!$D$50*MAX(0,CEILING(R9,1)-1),IF(S9="超大0-50lb",INDEX(FBA规则!$B$51:$C$51,1,IF(参数!$B$23="旺季",2,1))+FBA规则!$D$51*MAX(0,CEILING(R9,1)-1),IF(S9="超大50-70lb",INDEX(FBA规则!$B$52:$C$52,1,IF(参数!$B$23="旺季",2,1))+FBA规则!$D$52*MAX(0,R9-FBA规则!$F$52),IF(S9="超大70-150lb",INDEX(FBA规则!$B$53:$C$53,1,IF(参数!$B$23="旺季",2,1))+FBA规则!$D$53*MAX(0,R9-FBA规则!$F$53),INDEX(FBA规则!$B$54:$C$54,1,IF(参数!$B$23="旺季",2,1))+FBA规则!$D$54*MAX(0,R9-FBA规则!$F$54)))))))) | AC9: =IF(OR(G9="",I9=""),"",G9*I9) | AD9: =IF(OR(G9="",J9=""),"",G9*J9) | AE9: =IF(OR(G9="",K9=""),"",G9*K9) | AF9: =IF(OR(G9="",L9=""),"",G9*L9) | AG9: 0.02 | AH9: =IF(OR(G9="",AG9=""),"",G9*AG9) | AJ9: =IF(X9="","",X9+IF(OR(AA9="",M9=""),0,AA9/M9)+SUM(AB9:AF9)+IF(AH9="",0,AH9)+IF(AI9="",0,AI9)) | AK9: =IF(X9="","",0.13*X9/1.13) | AL9: =IF(OR(G9="",AJ9=""),"",G9+AK9-AJ9) | AM9: =IF(OR(AL9="",G9=""),"",AL9/G9) | AN9: =IF(OR(X9="",H9=""),"",X9/H9) | AP9: =AA9 | AQ9: =IF(OR(S9="",R9="",参数!$B$23=""),"",IF(S9="小标准",IFERROR(INDEX(FBA规则!$B$58:$C$65,MATCH(N9*FBA规则!$B$6*16,FBA规则!$A$58:$A$65,1),IF(参数!$B$23="旺季",2,1)),INDEX(FBA规则!$B$65:$C$65,1,IF(参数!$B$23="旺季",2,1))),IF(S9="大标准",IF(R9<=3,IFERROR(INDEX(FBA规则!$B$35:$C$46,MATCH(R9,FBA规则!$A$35:$A$46,1),IF(参数!$B$23="旺季",2,1)),INDEX(FBA规则!$B$46:$C$46,1,IF(参数!$B$23="旺季",2,1))),INDEX(FBA规则!$B$47:$C$47,1,IF(参数!$B$23="旺季",2,1))+FBA规则!$D$47*CEILING((R9-3)*4,1)),IF(S9="大件",INDEX(FBA规则!$B$50:$C$50,1,IF(参数!$B$23="旺季",2,1))+FBA规则!$D$50*MAX(0,CEILING(R9,1)-1),IF(S9="超大0-50lb",INDEX(FBA规则!$B$51:$C$51,1,IF(参数!$B$23="旺季",2,1))+FBA规则!$D$51*MAX(0,CEILING(R9,1)-1),IF(S9="超大50-70lb",INDEX(FBA规则!$B$52:$C$52,1,IF(参数!$B$23="旺季",2,1))+FBA规则!$D$52*MAX(0,R9-FBA规则!$F$52),IF(S9="超大70-150lb",INDEX(FBA规则!$B$53:$C$53,1,IF(参数!$B$23="旺季",2,1))+FBA规则!$D$53*MAX(0,R9-FBA规则!$F$53),INDEX(FBA规则!$B$54:$C$54,1,IF(参数!$B$23="旺季",2,1))+FBA规则!$D$54*MAX(0,R9-FBA规则!$F$54)))))))) | AR9: =IF(OR(H9="",I9=""),"",H9*I9) | AS9: =IF(OR(H9="",J9=""),"",H9*J9) | AT9: =IF(OR(H9="",K9=""),"",H9*K9) | AU9: =IF(OR(H9="",L9=""),"",H9*L9) | AV9: 0.02 | AW9: =IF(OR(H9="",AV9=""),"",H9*AV9) | AY9: =IF(X9="","",X9+IF(OR(AP9="",M9=""),0,AP9/M9)+SUM(AQ9:AU9)+IF(AW9="",0,AW9)+IF(AX9="",0,AX9)) | AZ9: =IF(X9="","",0.13*X9/1.13) | BA9: =IF(OR(H9="",AY9=""),"",H9+AZ9-AY9) | BB9: =IF(OR(BA9="",H9=""),"",BA9/H9) | BC9: =IF(OR(H9="",AY9=""),"",H9-AY9) | BD9: =IF(OR(BC9="",H9=""),"",BC9/H9) | BE9: 义乌 | BF9: ABE8 | BG9: 海运 | BH9: （最低价） | BI9: =IF(OR(BE9="",BF9=""),"",IF(AND(BH9<>"",BH9<>"（最低价）"),IFERROR(IF(SUMIFS(海运报价!$F$2:$F$2000,海运报价!$C$2:$C$2000,BH9,海运报价!$D$2:$D$2000,BE9,海运报价!$E$2:$E$2000,BF9)=0,"",SUMIFS(海运报价!$F$2:$F$2000,海运报价!$C$2:$C$2000,BH9,海运报价!$D$2:$D$2000,BE9,海运报价!$E$2:$E$2000,BF9)),""),IFERROR(IF(SUMIFS(海运下拉!$H$2:$H$311,海运下拉!$F$2:$F$311,BE9,海运下拉!$G$2:$G$311,BF9)=0,"",SUMIFS(海运下拉!$H$2:$H$311,海运下拉!$F$2:$F$311,BE9,海运下拉!$G$2:$G$311,BF9)),""))) | BJ9: =IF(C9="","",VLOOKUP($C9,箱规!$A$2:$S$23,18,FALSE)) | BK9: =IF(OR(BI9="",BJ9=""),"",BJ9*(BI9+IF(AND(BH9<>"",BH9<>"（最低价）"),IFERROR(AVERAGEIFS(海运报价!$H$2:$H$2000,海运报价!$C$2:$C$2000,BH9,海运报价!$D$2:$D$2000,BE9,海运报价!$E$2:$E$2000,BF9),0),IFERROR(SUMIFS(海运下拉!$J$2:$J$311,海运下拉!$F$2:$F$311,BE9,海运下拉!$G$2:$G$311,BF9),0)))) | BM9: =IF(OR(BE9="",BF9=""),"请选起运地+FBA仓",IF(AND(AND(BH9<>"",BH9<>"（最低价）"),BI9=""),"⚠该渠道不服务此仓：请重选渠道，或选「（最低价）」",IF(BI9="","无报价：请换起运地/仓库",IF(AND(BH9<>"",BH9<>"（最低价）"),"按你选的渠道「"&BH9&"」计价","按最低价「"&IFERROR(SUMIFS(海运下拉!$I$2:$I$311,海运下拉!$F$2:$F$311,BE9,海运下拉!$G$2:$G$311,BF9),"")&"」（渠道默认最低价）")))) | BO9: =IF(OR($BE9="",$BF9=""),"",IFERROR(INDEX(海运报价!$C$2:$C$2000,AGGREGATE(15,6,(ROW(海运报价!$C$2:$C$2000)-ROW(海运报价!$C$2)+1)/((海运报价!$D$2:$D$2000=$BE9)*(海运报价!$E$2:$E$2000=$BF9)),1)),"")) | BP9: =IF(OR($BE9="",$BF9=""),"",IFERROR(INDEX(海运报价!$C$2:$C$2000,AGGREGATE(15,6,(ROW(海运报价!$C$2:$C$2000)-ROW(海运报价!$C$2)+1)/((海运报价!$D$2:$D$2000=$BE9)*(海运报价!$E$2:$E$2000=$BF9)),2)),"")) | BQ9: =IF(OR($BE9="",$BF9=""),"",IFERROR(INDEX(海运报价!$C$2:$C$2000,AGGREGATE(15,6,(ROW(海运报价!$C$2:$C$2000)-ROW(海运报价!$C$2)+1)/((海运报价!$D$2:$D$2000=$BE9)*(海运报价!$E$2:$E$2000=$BF9)),3)),"")) | BR9: =IF(OR($BE9="",$BF9=""),"",IFERROR(INDEX(海运报价!$C$2:$C$2000,AGGREGATE(15,6,(ROW(海运报价!$C$2:$C$2000)-ROW(海运报价!$C$2)+1)/((海运报价!$D$2:$D$2000=$BE9)*(海运报价!$E$2:$E$2000=$BF9)),4)),"")) | BS9: =IF(OR($BE9="",$BF9=""),"",IFERROR(INDEX(海运报价!$C$2:$C$2000,AGGREGATE(15,6,(ROW(海运报价!$C$2:$C$2000)-ROW(海运报价!$C$2)+1)/((海运报价!$D$2:$D$2000=$BE9)*(海运报价!$E$2:$E$2000=$BF9)),5)),"")) | BT9: =IF(OR($BE9="",$BF9=""),"",IFERROR(INDEX(海运报价!$C$2:$C$2000,AGGREGATE(15,6,(ROW(海运报价!$C$2:$C$2000)-ROW(海运报价!$C$2)+1)/((海运报价!$D$2:$D$2000=$BE9)*(海运报价!$E$2:$E$2000=$BF9)),6)),"")) | BU9: =IF(OR($BE9="",$BF9=""),"",IFERROR(INDEX(海运报价!$C$2:$C$2000,AGGREGATE(15,6,(ROW(海运报价!$C$2:$C$2000)-ROW(海运报价!$C$2)+1)/((海运报价!$D$2:$D$2000=$BE9)*(海运报价!$E$2:$E$2000=$BF9)),7)),"")) | BV9: =IF(OR($BE9="",$BF9=""),"",IFERROR(INDEX(海运报价!$C$2:$C$2000,AGGREGATE(15,6,(ROW(海运报价!$C$2:$C$2000)-ROW(海运报价!$C$2)+1)/((海运报价!$D$2:$D$2000=$BE9)*(海运报价!$E$2:$E$2000=$BF9)),8)),"")) | BW9: =IF(OR($BE9="",$BF9=""),"",IFERROR(INDEX(海运报价!$C$2:$C$2000,AGGREGATE(15,6,(ROW(海运报价!$C$2:$C$2000)-ROW(海运报价!$C$2)+1)/((海运报价!$D$2:$D$2000=$BE9)*(海运报价!$E$2:$E$2000=$BF9)),9)),"")) | BX9: =IF(OR($BE9="",$BF9=""),"",IFERROR(INDEX(海运报价!$C$2:$C$2000,AGGREGATE(15,6,(ROW(海运报价!$C$2:$C$2000)-ROW(海运报价!$C$2)+1)/((海运报价!$D$2:$D$2000=$BE9)*(海运报价!$E$2:$E$2000=$BF9)),10)),"")) | BY9: =IF(OR($BE9="",$BF9=""),"",IFERROR(INDEX(海运报价!$C$2:$C$2000,AGGREGATE(15,6,(ROW(海运报价!$C$2:$C$2000)-ROW(海运报价!$C$2)+1)/((海运报价!$D$2:$D$2000=$BE9)*(海运报价!$E$2:$E$2000=$BF9)),11)),"")) | BZ9: =IF(OR($BE9="",$BF9=""),"",IFERROR(INDEX(海运报价!$C$2:$C$2000,AGGREGATE(15,6,(ROW(海运报价!$C$2:$C$2000)-ROW(海运报价!$C$2)+1)/((海运报价!$D$2:$D$2000=$BE9)*(海运报价!$E$2:$E$2000=$BF9)),12)),"")) | CA9: =IF(OR($BE9="",$BF9=""),"",IFERROR(INDEX(海运报价!$C$2:$C$2000,AGGREGATE(15,6,(ROW(海运报价!$C$2:$C$2000)-ROW(海运报价!$C$2)+1)/((海运报价!$D$2:$D$2000=$BE9)*(海运报价!$E$2:$E$2000=$BF9)),13)),"")) | CB9: =IF(OR($BE9="",$BF9=""),"",IFERROR(INDEX(海运报价!$C$2:$C$2000,AGGREGATE(15,6,(ROW(海运报价!$C$2:$C$2000)-ROW(海运报价!$C$2)+1)/((海运报价!$D$2:$D$2000=$BE9)*(海运报价!$E$2:$E$2000=$BF9)),14)),"")) | CC9: =IF(OR($BE9="",$BF9=""),"",IFERROR(INDEX(海运报价!$C$2:$C$2000,AGGREGATE(15,6,(ROW(海运报价!$C$2:$C$2000)-ROW(海运报价!$C$2)+1)/((海运报价!$D$2:$D$2000=$BE9)*(海运报价!$E$2:$E$2000=$BF9)),15)),"")) | CD9: =IF(OR(X9="",M9=""),"",X9+IF(OR(AA9="",M9=""),0,AA9/M9)+IF(AB9="",0,AB9)+IF(AI9="",0,AI9)+IF(Z9="",0,Z9)) | CE9: =I9+J9+K9+L9+AG9
C10: 4'6' | D10: =IF(C10="","",VLOOKUP($C10,箱规!$A$2:$S$23,9,FALSE)) | G10: =IF(OR(CD10="",CE10="",CE10>=1,X10=""),"",ROUNDUP((CD10-0.13*X10/1.13)/(1-CE10),2)) | H10: =IF(OR(CD10="",CE10="",X10=""),"",IF((1-CE10-参数!$B$16)<=0,"费率过高",ROUND((CD10-0.13*X10/1.13)/(1-CE10-参数!$B$16),2))) | I10: 0.15 | J10: 0.07 | K10: 0.15 | L10: 0.01 | M10: =参数!$B$2 | N10: =IF(C10="","",VLOOKUP($C10,箱规!$A$2:$S$23,14,FALSE)) | O10: =IF(C10="","",VLOOKUP($C10,箱规!$A$2:$S$23,5,FALSE)) | P10: =IF(C10="","",VLOOKUP($C10,箱规!$A$2:$S$23,6,FALSE)) | Q10: =IF(C10="","",VLOOKUP($C10,箱规!$A$2:$S$23,7,FALSE)) | R10: =IF(OR(N10="",O10="",P10="",Q10=""),"",MAX(N10*FBA规则!$B$6,(O10/FBA规则!$B$5)*(P10/FBA规则!$B$5)*(Q10/FBA规则!$B$5)/FBA规则!$B$7)) | S10: =IF(R10="","",IF(AND(N10*FBA规则!$B$6<=1,MAX(O10,P10,Q10)/FBA规则!$B$5<=15,MEDIAN(O10,P10,Q10)/FBA规则!$B$5<=12,MIN(O10,P10,Q10)/FBA规则!$B$5<=0.75),"小标准",IF(AND(R10<=20,MAX(O10,P10,Q10)/FBA规则!$B$5<=18,MEDIAN(O10,P10,Q10)/FBA规则!$B$5<=14,MIN(O10,P10,Q10)/FBA规则!$B$5<=8),"大标准",IF(AND(R10<=50,MAX(O10,P10,Q10)/FBA规则!$B$5<=59,MEDIAN(O10,P10,Q10)/FBA规则!$B$5<=33,MIN(O10,P10,Q10)/FBA规则!$B$5<=33,T10<=130),"大件",IF(R10<=50,"超大0-50lb",IF(R10<=70,"超大50-70lb",IF(R10<=150,"超大70-150lb","超大150lb+"))))))) | T10: =IF(OR(O10="",P10="",Q10=""),"",MAX(O10,P10,Q10)/FBA规则!$B$5+2*((MEDIAN(O10,P10,Q10)+MIN(O10,P10,Q10))/FBA规则!$B$5)) | U10: =参数!$B$15 | V10: =IF(OR(C10="",U10=""),"",(IF(OR(VLOOKUP($C10,箱规!$A$2:$S$23,4,FALSE)="",VLOOKUP($C10,箱规!$A$2:$S$23,4,FALSE)=0),VLOOKUP($C10,箱规!$A$2:$S$23,2,FALSE)*VLOOKUP($C10,箱规!$A$2:$S$23,3,FALSE)/10000,VLOOKUP($C10,箱规!$A$2:$S$23,4,FALSE)))*U10) | X10: =IF(AND(V10<>"",M10<>""),V10/M10,IF(AND(W10<>"",M10<>""),W10*1.13/M10,"")) | Y10: =IF(OR(X10="",G10=""),"",X10/G10) | AA10: =IF(OR(D10="",D10=0),"",IF(BG10="陆运",IF(BL10="",0,BL10)/D10,IF(BG10="海运",IF(BK10="",0,BK10)/D10,IF(BG10="海运+陆运",(IF(BK10="",0,BK10)+IF(BL10="",0,BL10))/D10,IF(BK10="",0,BK10)/D10)))) | AB10: =IF(OR(S10="",R10="",参数!$B$23=""),"",IF(S10="小标准",IFERROR(INDEX(FBA规则!$B$58:$C$65,MATCH(N10*FBA规则!$B$6*16,FBA规则!$A$58:$A$65,1),IF(参数!$B$23="旺季",2,1)),INDEX(FBA规则!$B$65:$C$65,1,IF(参数!$B$23="旺季",2,1))),IF(S10="大标准",IF(R10<=3,IFERROR(INDEX(FBA规则!$B$35:$C$46,MATCH(R10,FBA规则!$A$35:$A$46,1),IF(参数!$B$23="旺季",2,1)),INDEX(FBA规则!$B$46:$C$46,1,IF(参数!$B$23="旺季",2,1))),INDEX(FBA规则!$B$47:$C$47,1,IF(参数!$B$23="旺季",2,1))+FBA规则!$D$47*CEILING((R10-3)*4,1)),IF(S10="大件",INDEX(FBA规则!$B$50:$C$50,1,IF(参数!$B$23="旺季",2,1))+FBA规则!$D$50*MAX(0,CEILING(R10,1)-1),IF(S10="超大0-50lb",INDEX(FBA规则!$B$51:$C$51,1,IF(参数!$B$23="旺季",2,1))+FBA规则!$D$51*MAX(0,CEILING(R10,1)-1),IF(S10="超大50-70lb",INDEX(FBA规则!$B$52:$C$52,1,IF(参数!$B$23="旺季",2,1))+FBA规则!$D$52*MAX(0,R10-FBA规则!$F$52),IF(S10="超大70-150lb",INDEX(FBA规则!$B$53:$C$53,1,IF(参数!$B$23="旺季",2,1))+FBA规则!$D$53*MAX(0,R10-FBA规则!$F$53),INDEX(FBA规则!$B$54:$C$54,1,IF(参数!$B$23="旺季",2,1))+FBA规则!$D$54*MAX(0,R10-FBA规则!$F$54)))))))) | AC10: =IF(OR(G10="",I10=""),"",G10*I10) | AD10: =IF(OR(G10="",J10=""),"",G10*J10) | AE10: =IF(OR(G10="",K10=""),"",G10*K10) | AF10: =IF(OR(G10="",L10=""),"",G10*L10) | AG10: 0.02 | AH10: =IF(OR(G10="",AG10=""),"",G10*AG10) | AJ10: =IF(X10="","",X10+IF(OR(AA10="",M10=""),0,AA10/M10)+SUM(AB10:AF10)+IF(AH10="",0,AH10)+IF(AI10="",0,AI10)) | AK10: =IF(X10="","",0.13*X10/1.13) | AL10: =IF(OR(G10="",AJ10=""),"",G10+AK10-AJ10) | AM10: =IF(OR(AL10="",G10=""),"",AL10/G10) | AN10: =IF(OR(X10="",H10=""),"",X10/H10) | AP10: =AA10 | AQ10: =IF(OR(S10="",R10="",参数!$B$23=""),"",IF(S10="小标准",IFERROR(INDEX(FBA规则!$B$58:$C$65,MATCH(N10*FBA规则!$B$6*16,FBA规则!$A$58:$A$65,1),IF(参数!$B$23="旺季",2,1)),INDEX(FBA规则!$B$65:$C$65,1,IF(参数!$B$23="旺季",2,1))),IF(S10="大标准",IF(R10<=3,IFERROR(INDEX(FBA规则!$B$35:$C$46,MATCH(R10,FBA规则!$A$35:$A$46,1),IF(参数!$B$23="旺季",2,1)),INDEX(FBA规则!$B$46:$C$46,1,IF(参数!$B$23="旺季",2,1))),INDEX(FBA规则!$B$47:$C$47,1,IF(参数!$B$23="旺季",2,1))+FBA规则!$D$47*CEILING((R10-3)*4,1)),IF(S10="大件",INDEX(FBA规则!$B$50:$C$50,1,IF(参数!$B$23="旺季",2,1))+FBA规则!$D$50*MAX(0,CEILING(R10,1)-1),IF(S10="超大0-50lb",INDEX(FBA规则!$B$51:$C$51,1,IF(参数!$B$23="旺季",2,1))+FBA规则!$D$51*MAX(0,CEILING(R10,1)-1),IF(S10="超大50-70lb",INDEX(FBA规则!$B$52:$C$52,1,IF(参数!$B$23="旺季",2,1))+FBA规则!$D$52*MAX(0,R10-FBA规则!$F$52),IF(S10="超大70-150lb",INDEX(FBA规则!$B$53:$C$53,1,IF(参数!$B$23="旺季",2,1))+FBA规则!$D$53*MAX(0,R10-FBA规则!$F$53),INDEX(FBA规则!$B$54:$C$54,1,IF(参数!$B$23="旺季",2,1))+FBA规则!$D$54*MAX(0,R10-FBA规则!$F$54)))))))) | AR10: =IF(OR(H10="",I10=""),"",H10*I10) | AS10: =IF(OR(H10="",J10=""),"",H10*J10) | AT10: =IF(OR(H10="",K10=""),"",H10*K10) | AU10: =IF(OR(H10="",L10=""),"",H10*L10) | AV10: 0.02 | AW10: =IF(OR(H10="",AV10=""),"",H10*AV10) | AY10: =IF(X10="","",X10+IF(OR(AP10="",M10=""),0,AP10/M10)+SUM(AQ10:AU10)+IF(AW10="",0,AW10)+IF(AX10="",0,AX10)) | AZ10: =IF(X10="","",0.13*X10/1.13) | BA10: =IF(OR(H10="",AY10=""),"",H10+AZ10-AY10) | BB10: =IF(OR(BA10="",H10=""),"",BA10/H10) | BC10: =IF(OR(H10="",AY10=""),"",H10-AY10) | BD10: =IF(OR(BC10="",H10=""),"",BC10/H10) | BE10: 义乌 | BF10: ABE8 | BG10: 海运 | BH10: （最低价） | BI10: =IF(OR(BE10="",BF10=""),"",IF(AND(BH10<>"",BH10<>"（最低价）"),IFERROR(IF(SUMIFS(海运报价!$F$2:$F$2000,海运报价!$C$2:$C$2000,BH10,海运报价!$D$2:$D$2000,BE10,海运报价!$E$2:$E$2000,BF10)=0,"",SUMIFS(海运报价!$F$2:$F$2000,海运报价!$C$2:$C$2000,BH10,海运报价!$D$2:$D$2000,BE10,海运报价!$E$2:$E$2000,BF10)),""),IFERROR(IF(SUMIFS(海运下拉!$H$2:$H$311,海运下拉!$F$2:$F$311,BE10,海运下拉!$G$2:$G$311,BF10)=0,"",SUMIFS(海运下拉!$H$2:$H$311,海运下拉!$F$2:$F$311,BE10,海运下拉!$G$2:$G$311,BF10)),""))) | BJ10: =IF(C10="","",VLOOKUP($C10,箱规!$A$2:$S$23,18,FALSE)) | BK10: =IF(OR(BI10="",BJ10=""),"",BJ10*(BI10+IF(AND(BH10<>"",BH10<>"（最低价）"),IFERROR(AVERAGEIFS(海运报价!$H$2:$H$2000,海运报价!$C$2:$C$2000,BH10,海运报价!$D$2:$D$2000,BE10,海运报价!$E$2:$E$2000,BF10),0),IFERROR(SUMIFS(海运下拉!$J$2:$J$311,海运下拉!$F$2:$F$311,BE10,海运下拉!$G$2:$G$311,BF10),0)))) | BM10: =IF(OR(BE10="",BF10=""),"请选起运地+FBA仓",IF(AND(AND(BH10<>"",BH10<>"（最低价）"),BI10=""),"⚠该渠道不服务此仓：请重选渠道，或选「（最低价）」",IF(BI10="","无报价：请换起运地/仓库",IF(AND(BH10<>"",BH10<>"（最低价）"),"按你选的渠道「"&BH10&"」计价","按最低价「"&IFERROR(SUMIFS(海运下拉!$I$2:$I$311,海运下拉!$F$2:$F$311,BE10,海运下拉!$G$2:$G$311,BF10),"")&"」（渠道默认最低价）")))) | BO10: =IF(OR($BE10="",$BF10=""),"",IFERROR(INDEX(海运报价!$C$2:$C$2000,AGGREGATE(15,6,(ROW(海运报价!$C$2:$C$2000)-ROW(海运报价!$C$2)+1)/((海运报价!$D$2:$D$2000=$BE10)*(海运报价!$E$2:$E$2000=$BF10)),1)),"")) | BP10: =IF(OR($BE10="",$BF10=""),"",IFERROR(INDEX(海运报价!$C$2:$C$2000,AGGREGATE(15,6,(ROW(海运报价!$C$2:$C$2000)-ROW(海运报价!$C$2)+1)/((海运报价!$D$2:$D$2000=$BE10)*(海运报价!$E$2:$E$2000=$BF10)),2)),"")) | BQ10: =IF(OR($BE10="",$BF10=""),"",IFERROR(INDEX(海运报价!$C$2:$C$2000,AGGREGATE(15,6,(ROW(海运报价!$C$2:$C$2000)-ROW(海运报价!$C$2)+1)/((海运报价!$D$2:$D$2000=$BE10)*(海运报价!$E$2:$E$2000=$BF10)),3)),"")) | BR10: =IF(OR($BE10="",$BF10=""),"",IFERROR(INDEX(海运报价!$C$2:$C$2000,AGGREGATE(15,6,(ROW(海运报价!$C$2:$C$2000)-ROW(海运报价!$C$2)+1)/((海运报价!$D$2:$D$2000=$BE10)*(海运报价!$E$2:$E$2000=$BF10)),4)),"")) | BS10: =IF(OR($BE10="",$BF10=""),"",IFERROR(INDEX(海运报价!$C$2:$C$2000,AGGREGATE(15,6,(ROW(海运报价!$C$2:$C$2000)-ROW(海运报价!$C$2)+1)/((海运报价!$D$2:$D$2000=$BE10)*(海运报价!$E$2:$E$2000=$BF10)),5)),"")) | BT10: =IF(OR($BE10="",$BF10=""),"",IFERROR(INDEX(海运报价!$C$2:$C$2000,AGGREGATE(15,6,(ROW(海运报价!$C$2:$C$2000)-ROW(海运报价!$C$2)+1)/((海运报价!$D$2:$D$2000=$BE10)*(海运报价!$E$2:$E$2000=$BF10)),6)),"")) | BU10: =IF(OR($BE10="",$BF10=""),"",IFERROR(INDEX(海运报价!$C$2:$C$2000,AGGREGATE(15,6,(ROW(海运报价!$C$2:$C$2000)-ROW(海运报价!$C$2)+1)/((海运报价!$D$2:$D$2000=$BE10)*(海运报价!$E$2:$E$2000=$BF10)),7)),"")) | BV10: =IF(OR($BE10="",$BF10=""),"",IFERROR(INDEX(海运报价!$C$2:$C$2000,AGGREGATE(15,6,(ROW(海运报价!$C$2:$C$2000)-ROW(海运报价!$C$2)+1)/((海运报价!$D$2:$D$2000=$BE10)*(海运报价!$E$2:$E$2000=$BF10)),8)),"")) | BW10: =IF(OR($BE10="",$BF10=""),"",IFERROR(INDEX(海运报价!$C$2:$C$2000,AGGREGATE(15,6,(ROW(海运报价!$C$2:$C$2000)-ROW(海运报价!$C$2)+1)/((海运报价!$D$2:$D$2000=$BE10)*(海运报价!$E$2:$E$2000=$BF10)),9)),"")) | BX10: =IF(OR($BE10="",$BF10=""),"",IFERROR(INDEX(海运报价!$C$2:$C$2000,AGGREGATE(15,6,(ROW(海运报价!$C$2:$C$2000)-ROW(海运报价!$C$2)+1)/((海运报价!$D$2:$D$2000=$BE10)*(海运报价!$E$2:$E$2000=$BF10)),10)),"")) | BY10: =IF(OR($BE10="",$BF10=""),"",IFERROR(INDEX(海运报价!$C$2:$C$2000,AGGREGATE(15,6,(ROW(海运报价!$C$2:$C$2000)-ROW(海运报价!$C$2)+1)/((海运报价!$D$2:$D$2000=$BE10)*(海运报价!$E$2:$E$2000=$BF10)),11)),"")) | BZ10: =IF(OR($BE10="",$BF10=""),"",IFERROR(INDEX(海运报价!$C$2:$C$2000,AGGREGATE(15,6,(ROW(海运报价!$C$2:$C$2000)-ROW(海运报价!$C$2)+1)/((海运报价!$D$2:$D$2000=$BE10)*(海运报价!$E$2:$E$2000=$BF10)),12)),"")) | CA10: =IF(OR($BE10="",$BF10=""),"",IFERROR(INDEX(海运报价!$C$2:$C$2000,AGGREGATE(15,6,(ROW(海运报价!$C$2:$C$2000)-ROW(海运报价!$C$2)+1)/((海运报价!$D$2:$D$2000=$BE10)*(海运报价!$E$2:$E$2000=$BF10)),13)),"")) | CB10: =IF(OR($BE10="",$BF10=""),"",IFERROR(INDEX(海运报价!$C$2:$C$2000,AGGREGATE(15,6,(ROW(海运报价!$C$2:$C$2000)-ROW(海运报价!$C$2)+1)/((海运报价!$D$2:$D$2000=$BE10)*(海运报价!$E$2:$E$2000=$BF10)),14)),"")) | CC10: =IF(OR($BE10="",$BF10=""),"",IFERROR(INDEX(海运报价!$C$2:$C$2000,AGGREGATE(15,6,(ROW(海运报价!$C$2:$C$2000)-ROW(海运报价!$C$2)+1)/((海运报价!$D$2:$D$2000=$BE10)*(海运报价!$E$2:$E$2000=$BF10)),15)),"")) | CD10: =IF(OR(X10="",M10=""),"",X10+IF(OR(AA10="",M10=""),0,AA10/M10)+IF(AB10="",0,AB10)+IF(AI10="",0,AI10)+IF(Z10="",0,Z10)) | CE10: =I10+J10+K10+L10+AG10
C11: 5'7' | D11: =IF(C11="","",VLOOKUP($C11,箱规!$A$2:$S$23,9,FALSE)) | G11: =IF(OR(CD11="",CE11="",CE11>=1,X11=""),"",ROUNDUP((CD11-0.13*X11/1.13)/(1-CE11),2)) | H11: =IF(OR(CD11="",CE11="",X11=""),"",IF((1-CE11-参数!$B$16)<=0,"费率过高",ROUND((CD11-0.13*X11/1.13)/(1-CE11-参数!$B$16),2))) | I11: 0.15 | J11: 0.07 | K11: 0.15 | L11: 0.01 | M11: =参数!$B$2 | N11: =IF(C11="","",VLOOKUP($C11,箱规!$A$2:$S$23,14,FALSE)) | O11: =IF(C11="","",VLOOKUP($C11,箱规!$A$2:$S$23,5,FALSE)) | P11: =IF(C11="","",VLOOKUP($C11,箱规!$A$2:$S$23,6,FALSE)) | Q11: =IF(C11="","",VLOOKUP($C11,箱规!$A$2:$S$23,7,FALSE)) | R11: =IF(OR(N11="",O11="",P11="",Q11=""),"",MAX(N11*FBA规则!$B$6,(O11/FBA规则!$B$5)*(P11/FBA规则!$B$5)*(Q11/FBA规则!$B$5)/FBA规则!$B$7)) | S11: =IF(R11="","",IF(AND(N11*FBA规则!$B$6<=1,MAX(O11,P11,Q11)/FBA规则!$B$5<=15,MEDIAN(O11,P11,Q11)/FBA规则!$B$5<=12,MIN(O11,P11,Q11)/FBA规则!$B$5<=0.75),"小标准",IF(AND(R11<=20,MAX(O11,P11,Q11)/FBA规则!$B$5<=18,MEDIAN(O11,P11,Q11)/FBA规则!$B$5<=14,MIN(O11,P11,Q11)/FBA规则!$B$5<=8),"大标准",IF(AND(R11<=50,MAX(O11,P11,Q11)/FBA规则!$B$5<=59,MEDIAN(O11,P11,Q11)/FBA规则!$B$5<=33,MIN(O11,P11,Q11)/FBA规则!$B$5<=33,T11<=130),"大件",IF(R11<=50,"超大0-50lb",IF(R11<=70,"超大50-70lb",IF(R11<=150,"超大70-150lb","超大150lb+"))))))) | T11: =IF(OR(O11="",P11="",Q11=""),"",MAX(O11,P11,Q11)/FBA规则!$B$5+2*((MEDIAN(O11,P11,Q11)+MIN(O11,P11,Q11))/FBA规则!$B$5)) | U11: =参数!$B$15 | V11: =IF(OR(C11="",U11=""),"",(IF(OR(VLOOKUP($C11,箱规!$A$2:$S$23,4,FALSE)="",VLOOKUP($C11,箱规!$A$2:$S$23,4,FALSE)=0),VLOOKUP($C11,箱规!$A$2:$S$23,2,FALSE)*VLOOKUP($C11,箱规!$A$2:$S$23,3,FALSE)/10000,VLOOKUP($C11,箱规!$A$2:$S$23,4,FALSE)))*U11) | X11: =IF(AND(V11<>"",M11<>""),V11/M11,IF(AND(W11<>"",M11<>""),W11*1.13/M11,"")) | Y11: =IF(OR(X11="",G11=""),"",X11/G11) | AA11: =IF(OR(D11="",D11=0),"",IF(BG11="陆运",IF(BL11="",0,BL11)/D11,IF(BG11="海运",IF(BK11="",0,BK11)/D11,IF(BG11="海运+陆运",(IF(BK11="",0,BK11)+IF(BL11="",0,BL11))/D11,IF(BK11="",0,BK11)/D11)))) | AB11: =IF(OR(S11="",R11="",参数!$B$23=""),"",IF(S11="小标准",IFERROR(INDEX(FBA规则!$B$58:$C$65,MATCH(N11*FBA规则!$B$6*16,FBA规则!$A$58:$A$65,1),IF(参数!$B$23="旺季",2,1)),INDEX(FBA规则!$B$65:$C$65,1,IF(参数!$B$23="旺季",2,1))),IF(S11="大标准",IF(R11<=3,IFERROR(INDEX(FBA规则!$B$35:$C$46,MATCH(R11,FBA规则!$A$35:$A$46,1),IF(参数!$B$23="旺季",2,1)),INDEX(FBA规则!$B$46:$C$46,1,IF(参数!$B$23="旺季",2,1))),INDEX(FBA规则!$B$47:$C$47,1,IF(参数!$B$23="旺季",2,1))+FBA规则!$D$47*CEILING((R11-3)*4,1)),IF(S11="大件",INDEX(FBA规则!$B$50:$C$50,1,IF(参数!$B$23="旺季",2,1))+FBA规则!$D$50*MAX(0,CEILING(R11,1)-1),IF(S11="超大0-50lb",INDEX(FBA规则!$B$51:$C$51,1,IF(参数!$B$23="旺季",2,1))+FBA规则!$D$51*MAX(0,CEILING(R11,1)-1),IF(S11="超大50-70lb",INDEX(FBA规则!$B$52:$C$52,1,IF(参数!$B$23="旺季",2,1))+FBA规则!$D$52*MAX(0,R11-FBA规则!$F$52),IF(S11="超大70-150lb",INDEX(FBA规则!$B$53:$C$53,1,IF(参数!$B$23="旺季",2,1))+FBA规则!$D$53*MAX(0,R11-FBA规则!$F$53),INDEX(FBA规则!$B$54:$C$54,1,IF(参数!$B$23="旺季",2,1))+FBA规则!$D$54*MAX(0,R11-FBA规则!$F$54)))))))) | AC11: =IF(OR(G11="",I11=""),"",G11*I11) | AD11: =IF(OR(G11="",J11=""),"",G11*J11) | AE11: =IF(OR(G11="",K11=""),"",G11*K11) | AF11: =IF(OR(G11="",L11=""),"",G11*L11) | AG11: 0.02 | AH11: =IF(OR(G11="",AG11=""),"",G11*AG11) | AJ11: =IF(X11="","",X11+IF(OR(AA11="",M11=""),0,AA11/M11)+SUM(AB11:AF11)+IF(AH11="",0,AH11)+IF(AI11="",0,AI11)) | AK11: =IF(X11="","",0.13*X11/1.13) | AL11: =IF(OR(G11="",AJ11=""),"",G11+AK11-AJ11) | AM11: =IF(OR(AL11="",G11=""),"",AL11/G11) | AN11: =IF(OR(X11="",H11=""),"",X11/H11) | AP11: =AA11 | AQ11: =IF(OR(S11="",R11="",参数!$B$23=""),"",IF(S11="小标准",IFERROR(INDEX(FBA规则!$B$58:$C$65,MATCH(N11*FBA规则!$B$6*16,FBA规则!$A$58:$A$65,1),IF(参数!$B$23="旺季",2,1)),INDEX(FBA规则!$B$65:$C$65,1,IF(参数!$B$23="旺季",2,1))),IF(S11="大标准",IF(R11<=3,IFERROR(INDEX(FBA规则!$B$35:$C$46,MATCH(R11,FBA规则!$A$35:$A$46,1),IF(参数!$B$23="旺季",2,1)),INDEX(FBA规则!$B$46:$C$46,1,IF(参数!$B$23="旺季",2,1))),INDEX(FBA规则!$B$47:$C$47,1,IF(参数!$B$23="旺季",2,1))+FBA规则!$D$47*CEILING((R11-3)*4,1)),IF(S11="大件",INDEX(FBA规则!$B$50:$C$50,1,IF(参数!$B$23="旺季",2,1))+FBA规则!$D$50*MAX(0,CEILING(R11,1)-1),IF(S11="超大0-50lb",INDEX(FBA规则!$B$51:$C$51,1,IF(参数!$B$23="旺季",2,1))+FBA规则!$D$51*MAX(0,CEILING(R11,1)-1),IF(S11="超大50-70lb",INDEX(FBA规则!$B$52:$C$52,1,IF(参数!$B$23="旺季",2,1))+FBA规则!$D$52*MAX(0,R11-FBA规则!$F$52),IF(S11="超大70-150lb",INDEX(FBA规则!$B$53:$C$53,1,IF(参数!$B$23="旺季",2,1))+FBA规则!$D$53*MAX(0,R11-FBA规则!$F$53),INDEX(FBA规则!$B$54:$C$54,1,IF(参数!$B$23="旺季",2,1))+FBA规则!$D$54*MAX(0,R11-FBA规则!$F$54)))))))) | AR11: =IF(OR(H11="",I11=""),"",H11*I11) | AS11: =IF(OR(H11="",J11=""),"",H11*J11) | AT11: =IF(OR(H11="",K11=""),"",H11*K11) | AU11: =IF(OR(H11="",L11=""),"",H11*L11) | AV11: 0.02 | AW11: =IF(OR(H11="",AV11=""),"",H11*AV11) | AY11: =IF(X11="","",X11+IF(OR(AP11="",M11=""),0,AP11/M11)+SUM(AQ11:AU11)+IF(AW11="",0,AW11)+IF(AX11="",0,AX11)) | AZ11: =IF(X11="","",0.13*X11/1.13) | BA11: =IF(OR(H11="",AY11=""),"",H11+AZ11-AY11) | BB11: =IF(OR(BA11="",H11=""),"",BA11/H11) | BC11: =IF(OR(H11="",AY11=""),"",H11-AY11) | BD11: =IF(OR(BC11="",H11=""),"",BC11/H11) | BE11: 义乌 | BF11: ABE8 | BG11: 海运 | BH11: （最低价） | BI11: =IF(OR(BE11="",BF11=""),"",IF(AND(BH11<>"",BH11<>"（最低价）"),IFERROR(IF(SUMIFS(海运报价!$F$2:$F$2000,海运报价!$C$2:$C$2000,BH11,海运报价!$D$2:$D$2000,BE11,海运报价!$E$2:$E$2000,BF11)=0,"",SUMIFS(海运报价!$F$2:$F$2000,海运报价!$C$2:$C$2000,BH11,海运报价!$D$2:$D$2000,BE11,海运报价!$E$2:$E$2000,BF11)),""),IFERROR(IF(SUMIFS(海运下拉!$H$2:$H$311,海运下拉!$F$2:$F$311,BE11,海运下拉!$G$2:$G$311,BF11)=0,"",SUMIFS(海运下拉!$H$2:$H$311,海运下拉!$F$2:$F$311,BE11,海运下拉!$G$2:$G$311,BF11)),""))) | BJ11: =IF(C11="","",VLOOKUP($C11,箱规!$A$2:$S$23,18,FALSE)) | BK11: =IF(OR(BI11="",BJ11=""),"",BJ11*(BI11+IF(AND(BH11<>"",BH11<>"（最低价）"),IFERROR(AVERAGEIFS(海运报价!$H$2:$H$2000,海运报价!$C$2:$C$2000,BH11,海运报价!$D$2:$D$2000,BE11,海运报价!$E$2:$E$2000,BF11),0),IFERROR(SUMIFS(海运下拉!$J$2:$J$311,海运下拉!$F$2:$F$311,BE11,海运下拉!$G$2:$G$311,BF11),0)))) | BM11: =IF(OR(BE11="",BF11=""),"请选起运地+FBA仓",IF(AND(AND(BH11<>"",BH11<>"（最低价）"),BI11=""),"⚠该渠道不服务此仓：请重选渠道，或选「（最低价）」",IF(BI11="","无报价：请换起运地/仓库",IF(AND(BH11<>"",BH11<>"（最低价）"),"按你选的渠道「"&BH11&"」计价","按最低价「"&IFERROR(SUMIFS(海运下拉!$I$2:$I$311,海运下拉!$F$2:$F$311,BE11,海运下拉!$G$2:$G$311,BF11),"")&"」（渠道默认最低价）")))) | BO11: =IF(OR($BE11="",$BF11=""),"",IFERROR(INDEX(海运报价!$C$2:$C$2000,AGGREGATE(15,6,(ROW(海运报价!$C$2:$C$2000)-ROW(海运报价!$C$2)+1)/((海运报价!$D$2:$D$2000=$BE11)*(海运报价!$E$2:$E$2000=$BF11)),1)),"")) | BP11: =IF(OR($BE11="",$BF11=""),"",IFERROR(INDEX(海运报价!$C$2:$C$2000,AGGREGATE(15,6,(ROW(海运报价!$C$2:$C$2000)-ROW(海运报价!$C$2)+1)/((海运报价!$D$2:$D$2000=$BE11)*(海运报价!$E$2:$E$2000=$BF11)),2)),"")) | BQ11: =IF(OR($BE11="",$BF11=""),"",IFERROR(INDEX(海运报价!$C$2:$C$2000,AGGREGATE(15,6,(ROW(海运报价!$C$2:$C$2000)-ROW(海运报价!$C$2)+1)/((海运报价!$D$2:$D$2000=$BE11)*(海运报价!$E$2:$E$2000=$BF11)),3)),"")) | BR11: =IF(OR($BE11="",$BF11=""),"",IFERROR(INDEX(海运报价!$C$2:$C$2000,AGGREGATE(15,6,(ROW(海运报价!$C$2:$C$2000)-ROW(海运报价!$C$2)+1)/((海运报价!$D$2:$D$2000=$BE11)*(海运报价!$E$2:$E$2000=$BF11)),4)),"")) | BS11: =IF(OR($BE11="",$BF11=""),"",IFERROR(INDEX(海运报价!$C$2:$C$2000,AGGREGATE(15,6,(ROW(海运报价!$C$2:$C$2000)-ROW(海运报价!$C$2)+1)/((海运报价!$D$2:$D$2000=$BE11)*(海运报价!$E$2:$E$2000=$BF11)),5)),"")) | BT11: =IF(OR($BE11="",$BF11=""),"",IFERROR(INDEX(海运报价!$C$2:$C$2000,AGGREGATE(15,6,(ROW(海运报价!$C$2:$C$2000)-ROW(海运报价!$C$2)+1)/((海运报价!$D$2:$D$2000=$BE11)*(海运报价!$E$2:$E$2000=$BF11)),6)),"")) | BU11: =IF(OR($BE11="",$BF11=""),"",IFERROR(INDEX(海运报价!$C$2:$C$2000,AGGREGATE(15,6,(ROW(海运报价!$C$2:$C$2000)-ROW(海运报价!$C$2)+1)/((海运报价!$D$2:$D$2000=$BE11)*(海运报价!$E$2:$E$2000=$BF11)),7)),"")) | BV11: =IF(OR($BE11="",$BF11=""),"",IFERROR(INDEX(海运报价!$C$2:$C$2000,AGGREGATE(15,6,(ROW(海运报价!$C$2:$C$2000)-ROW(海运报价!$C$2)+1)/((海运报价!$D$2:$D$2000=$BE11)*(海运报价!$E$2:$E$2000=$BF11)),8)),"")) | BW11: =IF(OR($BE11="",$BF11=""),"",IFERROR(INDEX(海运报价!$C$2:$C$2000,AGGREGATE(15,6,(ROW(海运报价!$C$2:$C$2000)-ROW(海运报价!$C$2)+1)/((海运报价!$D$2:$D$2000=$BE11)*(海运报价!$E$2:$E$2000=$BF11)),9)),"")) | BX11: =IF(OR($BE11="",$BF11=""),"",IFERROR(INDEX(海运报价!$C$2:$C$2000,AGGREGATE(15,6,(ROW(海运报价!$C$2:$C$2000)-ROW(海运报价!$C$2)+1)/((海运报价!$D$2:$D$2000=$BE11)*(海运报价!$E$2:$E$2000=$BF11)),10)),"")) | BY11: =IF(OR($BE11="",$BF11=""),"",IFERROR(INDEX(海运报价!$C$2:$C$2000,AGGREGATE(15,6,(ROW(海运报价!$C$2:$C$2000)-ROW(海运报价!$C$2)+1)/((海运报价!$D$2:$D$2000=$BE11)*(海运报价!$E$2:$E$2000=$BF11)),11)),"")) | BZ11: =IF(OR($BE11="",$BF11=""),"",IFERROR(INDEX(海运报价!$C$2:$C$2000,AGGREGATE(15,6,(ROW(海运报价!$C$2:$C$2000)-ROW(海运报价!$C$2)+1)/((海运报价!$D$2:$D$2000=$BE11)*(海运报价!$E$2:$E$2000=$BF11)),12)),"")) | CA11: =IF(OR($BE11="",$BF11=""),"",IFERROR(INDEX(海运报价!$C$2:$C$2000,AGGREGATE(15,6,(ROW(海运报价!$C$2:$C$2000)-ROW(海运报价!$C$2)+1)/((海运报价!$D$2:$D$2000=$BE11)*(海运报价!$E$2:$E$2000=$BF11)),13)),"")) | CB11: =IF(OR($BE11="",$BF11=""),"",IFERROR(INDEX(海运报价!$C$2:$C$2000,AGGREGATE(15,6,(ROW(海运报价!$C$2:$C$2000)-ROW(海运报价!$C$2)+1)/((海运报价!$D$2:$D$2000=$BE11)*(海运报价!$E$2:$E$2000=$BF11)),14)),"")) | CC11: =IF(OR($BE11="",$BF11=""),"",IFERROR(INDEX(海运报价!$C$2:$C$2000,AGGREGATE(15,6,(ROW(海运报价!$C$2:$C$2000)-ROW(海运报价!$C$2)+1)/((海运报价!$D$2:$D$2000=$BE11)*(海运报价!$E$2:$E$2000=$BF11)),15)),"")) | CD11: =IF(OR(X11="",M11=""),"",X11+IF(OR(AA11="",M11=""),0,AA11/M11)+IF(AB11="",0,AB11)+IF(AI11="",0,AI11)+IF(Z11="",0,Z11)) | CE11: =I11+J11+K11+L11+AG11
C12: 5'8' | D12: =IF(C12="","",VLOOKUP($C12,箱规!$A$2:$S$23,9,FALSE)) | G12: =IF(OR(CD12="",CE12="",CE12>=1,X12=""),"",ROUNDUP((CD12-0.13*X12/1.13)/(1-CE12),2)) | H12: =IF(OR(CD12="",CE12="",X12=""),"",IF((1-CE12-参数!$B$16)<=0,"费率过高",ROUND((CD12-0.13*X12/1.13)/(1-CE12-参数!$B$16),2))) | I12: 0.15 | J12: 0.07 | K12: 0.15 | L12: 0.01 | M12: =参数!$B$2 | N12: =IF(C12="","",VLOOKUP($C12,箱规!$A$2:$S$23,14,FALSE)) | O12: =IF(C12="","",VLOOKUP($C12,箱规!$A$2:$S$23,5,FALSE)) | P12: =IF(C12="","",VLOOKUP($C12,箱规!$A$2:$S$23,6,FALSE)) | Q12: =IF(C12="","",VLOOKUP($C12,箱规!$A$2:$S$23,7,FALSE)) | R12: =IF(OR(N12="",O12="",P12="",Q12=""),"",MAX(N12*FBA规则!$B$6,(O12/FBA规则!$B$5)*(P12/FBA规则!$B$5)*(Q12/FBA规则!$B$5)/FBA规则!$B$7)) | S12: =IF(R12="","",IF(AND(N12*FBA规则!$B$6<=1,MAX(O12,P12,Q12)/FBA规则!$B$5<=15,MEDIAN(O12,P12,Q12)/FBA规则!$B$5<=12,MIN(O12,P12,Q12)/FBA规则!$B$5<=0.75),"小标准",IF(AND(R12<=20,MAX(O12,P12,Q12)/FBA规则!$B$5<=18,MEDIAN(O12,P12,Q12)/FBA规则!$B$5<=14,MIN(O12,P12,Q12)/FBA规则!$B$5<=8),"大标准",IF(AND(R12<=50,MAX(O12,P12,Q12)/FBA规则!$B$5<=59,MEDIAN(O12,P12,Q12)/FBA规则!$B$5<=33,MIN(O12,P12,Q12)/FBA规则!$B$5<=33,T12<=130),"大件",IF(R12<=50,"超大0-50lb",IF(R12<=70,"超大50-70lb",IF(R12<=150,"超大70-150lb","超大150lb+"))))))) | T12: =IF(OR(O12="",P12="",Q12=""),"",MAX(O12,P12,Q12)/FBA规则!$B$5+2*((MEDIAN(O12,P12,Q12)+MIN(O12,P12,Q12))/FBA规则!$B$5)) | U12: =参数!$B$15 | V12: =IF(OR(C12="",U12=""),"",(IF(OR(VLOOKUP($C12,箱规!$A$2:$S$23,4,FALSE)="",VLOOKUP($C12,箱规!$A$2:$S$23,4,FALSE)=0),VLOOKUP($C12,箱规!$A$2:$S$23,2,FALSE)*VLOOKUP($C12,箱规!$A$2:$S$23,3,FALSE)/10000,VLOOKUP($C12,箱规!$A$2:$S$23,4,FALSE)))*U12) | X12: =IF(AND(V12<>"",M12<>""),V12/M12,IF(AND(W12<>"",M12<>""),W12*1.13/M12,"")) | Y12: =IF(OR(X12="",G12=""),"",X12/G12) | AA12: =IF(OR(D12="",D12=0),"",IF(BG12="陆运",IF(BL12="",0,BL12)/D12,IF(BG12="海运",IF(BK12="",0,BK12)/D12,IF(BG12="海运+陆运",(IF(BK12="",0,BK12)+IF(BL12="",0,BL12))/D12,IF(BK12="",0,BK12)/D12)))) | AB12: =IF(OR(S12="",R12="",参数!$B$23=""),"",IF(S12="小标准",IFERROR(INDEX(FBA规则!$B$58:$C$65,MATCH(N12*FBA规则!$B$6*16,FBA规则!$A$58:$A$65,1),IF(参数!$B$23="旺季",2,1)),INDEX(FBA规则!$B$65:$C$65,1,IF(参数!$B$23="旺季",2,1))),IF(S12="大标准",IF(R12<=3,IFERROR(INDEX(FBA规则!$B$35:$C$46,MATCH(R12,FBA规则!$A$35:$A$46,1),IF(参数!$B$23="旺季",2,1)),INDEX(FBA规则!$B$46:$C$46,1,IF(参数!$B$23="旺季",2,1))),INDEX(FBA规则!$B$47:$C$47,1,IF(参数!$B$23="旺季",2,1))+FBA规则!$D$47*CEILING((R12-3)*4,1)),IF(S12="大件",INDEX(FBA规则!$B$50:$C$50,1,IF(参数!$B$23="旺季",2,1))+FBA规则!$D$50*MAX(0,CEILING(R12,1)-1),IF(S12="超大0-50lb",INDEX(FBA规则!$B$51:$C$51,1,IF(参数!$B$23="旺季",2,1))+FBA规则!$D$51*MAX(0,CEILING(R12,1)-1),IF(S12="超大50-70lb",INDEX(FBA规则!$B$52:$C$52,1,IF(参数!$B$23="旺季",2,1))+FBA规则!$D$52*MAX(0,R12-FBA规则!$F$52),IF(S12="超大70-150lb",INDEX(FBA规则!$B$53:$C$53,1,IF(参数!$B$23="旺季",2,1))+FBA规则!$D$53*MAX(0,R12-FBA规则!$F$53),INDEX(FBA规则!$B$54:$C$54,1,IF(参数!$B$23="旺季",2,1))+FBA规则!$D$54*MAX(0,R12-FBA规则!$F$54)))))))) | AC12: =IF(OR(G12="",I12=""),"",G12*I12) | AD12: =IF(OR(G12="",J12=""),"",G12*J12) | AE12: =IF(OR(G12="",K12=""),"",G12*K12) | AF12: =IF(OR(G12="",L12=""),"",G12*L12) | AG12: 0.02 | AH12: =IF(OR(G12="",AG12=""),"",G12*AG12) | AJ12: =IF(X12="","",X12+IF(OR(AA12="",M12=""),0,AA12/M12)+SUM(AB12:AF12)+IF(AH12="",0,AH12)+IF(AI12="",0,AI12)) | AK12: =IF(X12="","",0.13*X12/1.13) | AL12: =IF(OR(G12="",AJ12=""),"",G12+AK12-AJ12) | AM12: =IF(OR(AL12="",G12=""),"",AL12/G12) | AN12: =IF(OR(X12="",H12=""),"",X12/H12) | AP12: =AA12 | AQ12: =IF(OR(S12="",R12="",参数!$B$23=""),"",IF(S12="小标准",IFERROR(INDEX(FBA规则!$B$58:$C$65,MATCH(N12*FBA规则!$B$6*16,FBA规则!$A$58:$A$65,1),IF(参数!$B$23="旺季",2,1)),INDEX(FBA规则!$B$65:$C$65,1,IF(参数!$B$23="旺季",2,1))),IF(S12="大标准",IF(R12<=3,IFERROR(INDEX(FBA规则!$B$35:$C$46,MATCH(R12,FBA规则!$A$35:$A$46,1),IF(参数!$B$23="旺季",2,1)),INDEX(FBA规则!$B$46:$C$46,1,IF(参数!$B$23="旺季",2,1))),INDEX(FBA规则!$B$47:$C$47,1,IF(参数!$B$23="旺季",2,1))+FBA规则!$D$47*CEILING((R12-3)*4,1)),IF(S12="大件",INDEX(FBA规则!$B$50:$C$50,1,IF(参数!$B$23="旺季",2,1))+FBA规则!$D$50*MAX(0,CEILING(R12,1)-1),IF(S12="超大0-50lb",INDEX(FBA规则!$B$51:$C$51,1,IF(参数!$B$23="旺季",2,1))+FBA规则!$D$51*MAX(0,CEILING(R12,1)-1),IF(S12="超大50-70lb",INDEX(FBA规则!$B$52:$C$52,1,IF(参数!$B$23="旺季",2,1))+FBA规则!$D$52*MAX(0,R12-FBA规则!$F$52),IF(S12="超大70-150lb",INDEX(FBA规则!$B$53:$C$53,1,IF(参数!$B$23="旺季",2,1))+FBA规则!$D$53*MAX(0,R12-FBA规则!$F$53),INDEX(FBA规则!$B$54:$C$54,1,IF(参数!$B$23="旺季",2,1))+FBA规则!$D$54*MAX(0,R12-FBA规则!$F$54)))))))) | AR12: =IF(OR(H12="",I12=""),"",H12*I12) | AS12: =IF(OR(H12="",J12=""),"",H12*J12) | AT12: =IF(OR(H12="",K12=""),"",H12*K12) | AU12: =IF(OR(H12="",L12=""),"",H12*L12) | AV12: 0.02 | AW12: =IF(OR(H12="",AV12=""),"",H12*AV12) | AY12: =IF(X12="","",X12+IF(OR(AP12="",M12=""),0,AP12/M12)+SUM(AQ12:AU12)+IF(AW12="",0,AW12)+IF(AX12="",0,AX12)) | AZ12: =IF(X12="","",0.13*X12/1.13) | BA12: =IF(OR(H12="",AY12=""),"",H12+AZ12-AY12) | BB12: =IF(OR(BA12="",H12=""),"",BA12/H12) | BC12: =IF(OR(H12="",AY12=""),"",H12-AY12) | BD12: =IF(OR(BC12="",H12=""),"",BC12/H12) | BE12: 义乌 | BF12: ABE8 | BG12: 海运 | BH12: （最低价） | BI12: =IF(OR(BE12="",BF12=""),"",IF(AND(BH12<>"",BH12<>"（最低价）"),IFERROR(IF(SUMIFS(海运报价!$F$2:$F$2000,海运报价!$C$2:$C$2000,BH12,海运报价!$D$2:$D$2000,BE12,海运报价!$E$2:$E$2000,BF12)=0,"",SUMIFS(海运报价!$F$2:$F$2000,海运报价!$C$2:$C$2000,BH12,海运报价!$D$2:$D$2000,BE12,海运报价!$E$2:$E$2000,BF12)),""),IFERROR(IF(SUMIFS(海运下拉!$H$2:$H$311,海运下拉!$F$2:$F$311,BE12,海运下拉!$G$2:$G$311,BF12)=0,"",SUMIFS(海运下拉!$H$2:$H$311,海运下拉!$F$2:$F$311,BE12,海运下拉!$G$2:$G$311,BF12)),""))) | BJ12: =IF(C12="","",VLOOKUP($C12,箱规!$A$2:$S$23,18,FALSE)) | BK12: =IF(OR(BI12="",BJ12=""),"",BJ12*(BI12+IF(AND(BH12<>"",BH12<>"（最低价）"),IFERROR(AVERAGEIFS(海运报价!$H$2:$H$2000,海运报价!$C$2:$C$2000,BH12,海运报价!$D$2:$D$2000,BE12,海运报价!$E$2:$E$2000,BF12),0),IFERROR(SUMIFS(海运下拉!$J$2:$J$311,海运下拉!$F$2:$F$311,BE12,海运下拉!$G$2:$G$311,BF12),0)))) | BM12: =IF(OR(BE12="",BF12=""),"请选起运地+FBA仓",IF(AND(AND(BH12<>"",BH12<>"（最低价）"),BI12=""),"⚠该渠道不服务此仓：请重选渠道，或选「（最低价）」",IF(BI12="","无报价：请换起运地/仓库",IF(AND(BH12<>"",BH12<>"（最低价）"),"按你选的渠道「"&BH12&"」计价","按最低价「"&IFERROR(SUMIFS(海运下拉!$I$2:$I$311,海运下拉!$F$2:$F$311,BE12,海运下拉!$G$2:$G$311,BF12),"")&"」（渠道默认最低价）")))) | BO12: =IF(OR($BE12="",$BF12=""),"",IFERROR(INDEX(海运报价!$C$2:$C$2000,AGGREGATE(15,6,(ROW(海运报价!$C$2:$C$2000)-ROW(海运报价!$C$2)+1)/((海运报价!$D$2:$D$2000=$BE12)*(海运报价!$E$2:$E$2000=$BF12)),1)),"")) | BP12: =IF(OR($BE12="",$BF12=""),"",IFERROR(INDEX(海运报价!$C$2:$C$2000,AGGREGATE(15,6,(ROW(海运报价!$C$2:$C$2000)-ROW(海运报价!$C$2)+1)/((海运报价!$D$2:$D$2000=$BE12)*(海运报价!$E$2:$E$2000=$BF12)),2)),"")) | BQ12: =IF(OR($BE12="",$BF12=""),"",IFERROR(INDEX(海运报价!$C$2:$C$2000,AGGREGATE(15,6,(ROW(海运报价!$C$2:$C$2000)-ROW(海运报价!$C$2)+1)/((海运报价!$D$2:$D$2000=$BE12)*(海运报价!$E$2:$E$2000=$BF12)),3)),"")) | BR12: =IF(OR($BE12="",$BF12=""),"",IFERROR(INDEX(海运报价!$C$2:$C$2000,AGGREGATE(15,6,(ROW(海运报价!$C$2:$C$2000)-ROW(海运报价!$C$2)+1)/((海运报价!$D$2:$D$2000=$BE12)*(海运报价!$E$2:$E$2000=$BF12)),4)),"")) | BS12: =IF(OR($BE12="",$BF12=""),"",IFERROR(INDEX(海运报价!$C$2:$C$2000,AGGREGATE(15,6,(ROW(海运报价!$C$2:$C$2000)-ROW(海运报价!$C$2)+1)/((海运报价!$D$2:$D$2000=$BE12)*(海运报价!$E$2:$E$2000=$BF12)),5)),"")) | BT12: =IF(OR($BE12="",$BF12=""),"",IFERROR(INDEX(海运报价!$C$2:$C$2000,AGGREGATE(15,6,(ROW(海运报价!$C$2:$C$2000)-ROW(海运报价!$C$2)+1)/((海运报价!$D$2:$D$2000=$BE12)*(海运报价!$E$2:$E$2000=$BF12)),6)),"")) | BU12: =IF(OR($BE12="",$BF12=""),"",IFERROR(INDEX(海运报价!$C$2:$C$2000,AGGREGATE(15,6,(ROW(海运报价!$C$2:$C$2000)-ROW(海运报价!$C$2)+1)/((海运报价!$D$2:$D$2000=$BE12)*(海运报价!$E$2:$E$2000=$BF12)),7)),"")) | BV12: =IF(OR($BE12="",$BF12=""),"",IFERROR(INDEX(海运报价!$C$2:$C$2000,AGGREGATE(15,6,(ROW(海运报价!$C$2:$C$2000)-ROW(海运报价!$C$2)+1)/((海运报价!$D$2:$D$2000=$BE12)*(海运报价!$E$2:$E$2000=$BF12)),8)),"")) | BW12: =IF(OR($BE12="",$BF12=""),"",IFERROR(INDEX(海运报价!$C$2:$C$2000,AGGREGATE(15,6,(ROW(海运报价!$C$2:$C$2000)-ROW(海运报价!$C$2)+1)/((海运报价!$D$2:$D$2000=$BE12)*(海运报价!$E$2:$E$2000=$BF12)),9)),"")) | BX12: =IF(OR($BE12="",$BF12=""),"",IFERROR(INDEX(海运报价!$C$2:$C$2000,AGGREGATE(15,6,(ROW(海运报价!$C$2:$C$2000)-ROW(海运报价!$C$2)+1)/((海运报价!$D$2:$D$2000=$BE12)*(海运报价!$E$2:$E$2000=$BF12)),10)),"")) | BY12: =IF(OR($BE12="",$BF12=""),"",IFERROR(INDEX(海运报价!$C$2:$C$2000,AGGREGATE(15,6,(ROW(海运报价!$C$2:$C$2000)-ROW(海运报价!$C$2)+1)/((海运报价!$D$2:$D$2000=$BE12)*(海运报价!$E$2:$E$2000=$BF12)),11)),"")) | BZ12: =IF(OR($BE12="",$BF12=""),"",IFERROR(INDEX(海运报价!$C$2:$C$2000,AGGREGATE(15,6,(ROW(海运报价!$C$2:$C$2000)-ROW(海运报价!$C$2)+1)/((海运报价!$D$2:$D$2000=$BE12)*(海运报价!$E$2:$E$2000=$BF12)),12)),"")) | CA12: =IF(OR($BE12="",$BF12=""),"",IFERROR(INDEX(海运报价!$C$2:$C$2000,AGGREGATE(15,6,(ROW(海运报价!$C$2:$C$2000)-ROW(海运报价!$C$2)+1)/((海运报价!$D$2:$D$2000=$BE12)*(海运报价!$E$2:$E$2000=$BF12)),13)),"")) | CB12: =IF(OR($BE12="",$BF12=""),"",IFERROR(INDEX(海运报价!$C$2:$C$2000,AGGREGATE(15,6,(ROW(海运报价!$C$2:$C$2000)-ROW(海运报价!$C$2)+1)/((海运报价!$D$2:$D$2000=$BE12)*(海运报价!$E$2:$E$2000=$BF12)),14)),"")) | CC12: =IF(OR($BE12="",$BF12=""),"",IFERROR(INDEX(海运报价!$C$2:$C$2000,AGGREGATE(15,6,(ROW(海运报价!$C$2:$C$2000)-ROW(海运报价!$C$2)+1)/((海运报价!$D$2:$D$2000=$BE12)*(海运报价!$E$2:$E$2000=$BF12)),15)),"")) | CD12: =IF(OR(X12="",M12=""),"",X12+IF(OR(AA12="",M12=""),0,AA12/M12)+IF(AB12="",0,AB12)+IF(AI12="",0,AI12)+IF(Z12="",0,Z12)) | CE12: =I12+J12+K12+L12+AG12
C13: 6'9' | D13: =IF(C13="","",VLOOKUP($C13,箱规!$A$2:$S$23,9,FALSE)) | G13: =IF(OR(CD13="",CE13="",CE13>=1,X13=""),"",ROUNDUP((CD13-0.13*X13/1.13)/(1-CE13),2)) | H13: =IF(OR(CD13="",CE13="",X13=""),"",IF((1-CE13-参数!$B$16)<=0,"费率过高",ROUND((CD13-0.13*X13/1.13)/(1-CE13-参数!$B$16),2))) | I13: 0.15 | J13: 0.07 | K13: 0.15 | L13: 0.01 | M13: =参数!$B$2 | N13: =IF(C13="","",VLOOKUP($C13,箱规!$A$2:$S$23,14,FALSE)) | O13: =IF(C13="","",VLOOKUP($C13,箱规!$A$2:$S$23,5,FALSE)) | P13: =IF(C13="","",VLOOKUP($C13,箱规!$A$2:$S$23,6,FALSE)) | Q13: =IF(C13="","",VLOOKUP($C13,箱规!$A$2:$S$23,7,FALSE)) | R13: =IF(OR(N13="",O13="",P13="",Q13=""),"",MAX(N13*FBA规则!$B$6,(O13/FBA规则!$B$5)*(P13/FBA规则!$B$5)*(Q13/FBA规则!$B$5)/FBA规则!$B$7)) | S13: =IF(R13="","",IF(AND(N13*FBA规则!$B$6<=1,MAX(O13,P13,Q13)/FBA规则!$B$5<=15,MEDIAN(O13,P13,Q13)/FBA规则!$B$5<=12,MIN(O13,P13,Q13)/FBA规则!$B$5<=0.75),"小标准",IF(AND(R13<=20,MAX(O13,P13,Q13)/FBA规则!$B$5<=18,MEDIAN(O13,P13,Q13)/FBA规则!$B$5<=14,MIN(O13,P13,Q13)/FBA规则!$B$5<=8),"大标准",IF(AND(R13<=50,MAX(O13,P13,Q13)/FBA规则!$B$5<=59,MEDIAN(O13,P13,Q13)/FBA规则!$B$5<=33,MIN(O13,P13,Q13)/FBA规则!$B$5<=33,T13<=130),"大件",IF(R13<=50,"超大0-50lb",IF(R13<=70,"超大50-70lb",IF(R13<=150,"超大70-150lb","超大150lb+"))))))) | T13: =IF(OR(O13="",P13="",Q13=""),"",MAX(O13,P13,Q13)/FBA规则!$B$5+2*((MEDIAN(O13,P13,Q13)+MIN(O13,P13,Q13))/FBA规则!$B$5)) | U13: =参数!$B$15 | V13: =IF(OR(C13="",U13=""),"",(IF(OR(VLOOKUP($C13,箱规!$A$2:$S$23,4,FALSE)="",VLOOKUP($C13,箱规!$A$2:$S$23,4,FALSE)=0),VLOOKUP($C13,箱规!$A$2:$S$23,2,FALSE)*VLOOKUP($C13,箱规!$A$2:$S$23,3,FALSE)/10000,VLOOKUP($C13,箱规!$A$2:$S$23,4,FALSE)))*U13) | X13: =IF(AND(V13<>"",M13<>""),V13/M13,IF(AND(W13<>"",M13<>""),W13*1.13/M13,"")) | Y13: =IF(OR(X13="",G13=""),"",X13/G13) | AA13: =IF(OR(D13="",D13=0),"",IF(BG13="陆运",IF(BL13="",0,BL13)/D13,IF(BG13="海运",IF(BK13="",0,BK13)/D13,IF(BG13="海运+陆运",(IF(BK13="",0,BK13)+IF(BL13="",0,BL13))/D13,IF(BK13="",0,BK13)/D13)))) | AB13: =IF(OR(S13="",R13="",参数!$B$23=""),"",IF(S13="小标准",IFERROR(INDEX(FBA规则!$B$58:$C$65,MATCH(N13*FBA规则!$B$6*16,FBA规则!$A$58:$A$65,1),IF(参数!$B$23="旺季",2,1)),INDEX(FBA规则!$B$65:$C$65,1,IF(参数!$B$23="旺季",2,1))),IF(S13="大标准",IF(R13<=3,IFERROR(INDEX(FBA规则!$B$35:$C$46,MATCH(R13,FBA规则!$A$35:$A$46,1),IF(参数!$B$23="旺季",2,1)),INDEX(FBA规则!$B$46:$C$46,1,IF(参数!$B$23="旺季",2,1))),INDEX(FBA规则!$B$47:$C$47,1,IF(参数!$B$23="旺季",2,1))+FBA规则!$D$47*CEILING((R13-3)*4,1)),IF(S13="大件",INDEX(FBA规则!$B$50:$C$50,1,IF(参数!$B$23="旺季",2,1))+FBA规则!$D$50*MAX(0,CEILING(R13,1)-1),IF(S13="超大0-50lb",INDEX(FBA规则!$B$51:$C$51,1,IF(参数!$B$23="旺季",2,1))+FBA规则!$D$51*MAX(0,CEILING(R13,1)-1),IF(S13="超大50-70lb",INDEX(FBA规则!$B$52:$C$52,1,IF(参数!$B$23="旺季",2,1))+FBA规则!$D$52*MAX(0,R13-FBA规则!$F$52),IF(S13="超大70-150lb",INDEX(FBA规则!$B$53:$C$53,1,IF(参数!$B$23="旺季",2,1))+FBA规则!$D$53*MAX(0,R13-FBA规则!$F$53),INDEX(FBA规则!$B$54:$C$54,1,IF(参数!$B$23="旺季",2,1))+FBA规则!$D$54*MAX(0,R13-FBA规则!$F$54)))))))) | AC13: =IF(OR(G13="",I13=""),"",G13*I13) | AD13: =IF(OR(G13="",J13=""),"",G13*J13) | AE13: =IF(OR(G13="",K13=""),"",G13*K13) | AF13: =IF(OR(G13="",L13=""),"",G13*L13) | AG13: 0.02 | AH13: =IF(OR(G13="",AG13=""),"",G13*AG13) | AJ13: =IF(X13="","",X13+IF(OR(AA13="",M13=""),0,AA13/M13)+SUM(AB13:AF13)+IF(AH13="",0,AH13)+IF(AI13="",0,AI13)) | AK13: =IF(X13="","",0.13*X13/1.13) | AL13: =IF(OR(G13="",AJ13=""),"",G13+AK13-AJ13) | AM13: =IF(OR(AL13="",G13=""),"",AL13/G13) | AN13: =IF(OR(X13="",H13=""),"",X13/H13) | AP13: =AA13 | AQ13: =IF(OR(S13="",R13="",参数!$B$23=""),"",IF(S13="小标准",IFERROR(INDEX(FBA规则!$B$58:$C$65,MATCH(N13*FBA规则!$B$6*16,FBA规则!$A$58:$A$65,1),IF(参数!$B$23="旺季",2,1)),INDEX(FBA规则!$B$65:$C$65,1,IF(参数!$B$23="旺季",2,1))),IF(S13="大标准",IF(R13<=3,IFERROR(INDEX(FBA规则!$B$35:$C$46,MATCH(R13,FBA规则!$A$35:$A$46,1),IF(参数!$B$23="旺季",2,1)),INDEX(FBA规则!$B$46:$C$46,1,IF(参数!$B$23="旺季",2,1))),INDEX(FBA规则!$B$47:$C$47,1,IF(参数!$B$23="旺季",2,1))+FBA规则!$D$47*CEILING((R13-3)*4,1)),IF(S13="大件",INDEX(FBA规则!$B$50:$C$50,1,IF(参数!$B$23="旺季",2,1))+FBA规则!$D$50*MAX(0,CEILING(R13,1)-1),IF(S13="超大0-50lb",INDEX(FBA规则!$B$51:$C$51,1,IF(参数!$B$23="旺季",2,1))+FBA规则!$D$51*MAX(0,CEILING(R13,1)-1),IF(S13="超大50-70lb",INDEX(FBA规则!$B$52:$C$52,1,IF(参数!$B$23="旺季",2,1))+FBA规则!$D$52*MAX(0,R13-FBA规则!$F$52),IF(S13="超大70-150lb",INDEX(FBA规则!$B$53:$C$53,1,IF(参数!$B$23="旺季",2,1))+FBA规则!$D$53*MAX(0,R13-FBA规则!$F$53),INDEX(FBA规则!$B$54:$C$54,1,IF(参数!$B$23="旺季",2,1))+FBA规则!$D$54*MAX(0,R13-FBA规则!$F$54)))))))) | AR13: =IF(OR(H13="",I13=""),"",H13*I13) | AS13: =IF(OR(H13="",J13=""),"",H13*J13) | AT13: =IF(OR(H13="",K13=""),"",H13*K13) | AU13: =IF(OR(H13="",L13=""),"",H13*L13) | AV13: 0.02 | AW13: =IF(OR(H13="",AV13=""),"",H13*AV13) | AY13: =IF(X13="","",X13+IF(OR(AP13="",M13=""),0,AP13/M13)+SUM(AQ13:AU13)+IF(AW13="",0,AW13)+IF(AX13="",0,AX13)) | AZ13: =IF(X13="","",0.13*X13/1.13) | BA13: =IF(OR(H13="",AY13=""),"",H13+AZ13-AY13) | BB13: =IF(OR(BA13="",H13=""),"",BA13/H13) | BC13: =IF(OR(H13="",AY13=""),"",H13-AY13) | BD13: =IF(OR(BC13="",H13=""),"",BC13/H13) | BE13: 义乌 | BF13: ABE8 | BG13: 海运 | BH13: （最低价） | BI13: =IF(OR(BE13="",BF13=""),"",IF(AND(BH13<>"",BH13<>"（最低价）"),IFERROR(IF(SUMIFS(海运报价!$F$2:$F$2000,海运报价!$C$2:$C$2000,BH13,海运报价!$D$2:$D$2000,BE13,海运报价!$E$2:$E$2000,BF13)=0,"",SUMIFS(海运报价!$F$2:$F$2000,海运报价!$C$2:$C$2000,BH13,海运报价!$D$2:$D$2000,BE13,海运报价!$E$2:$E$2000,BF13)),""),IFERROR(IF(SUMIFS(海运下拉!$H$2:$H$311,海运下拉!$F$2:$F$311,BE13,海运下拉!$G$2:$G$311,BF13)=0,"",SUMIFS(海运下拉!$H$2:$H$311,海运下拉!$F$2:$F$311,BE13,海运下拉!$G$2:$G$311,BF13)),""))) | BJ13: =IF(C13="","",VLOOKUP($C13,箱规!$A$2:$S$23,18,FALSE)) | BK13: =IF(OR(BI13="",BJ13=""),"",BJ13*(BI13+IF(AND(BH13<>"",BH13<>"（最低价）"),IFERROR(AVERAGEIFS(海运报价!$H$2:$H$2000,海运报价!$C$2:$C$2000,BH13,海运报价!$D$2:$D$2000,BE13,海运报价!$E$2:$E$2000,BF13),0),IFERROR(SUMIFS(海运下拉!$J$2:$J$311,海运下拉!$F$2:$F$311,BE13,海运下拉!$G$2:$G$311,BF13),0)))) | BM13: =IF(OR(BE13="",BF13=""),"请选起运地+FBA仓",IF(AND(AND(BH13<>"",BH13<>"（最低价）"),BI13=""),"⚠该渠道不服务此仓：请重选渠道，或选「（最低价）」",IF(BI13="","无报价：请换起运地/仓库",IF(AND(BH13<>"",BH13<>"（最低价）"),"按你选的渠道「"&BH13&"」计价","按最低价「"&IFERROR(SUMIFS(海运下拉!$I$2:$I$311,海运下拉!$F$2:$F$311,BE13,海运下拉!$G$2:$G$311,BF13),"")&"」（渠道默认最低价）")))) | BO13: =IF(OR($BE13="",$BF13=""),"",IFERROR(INDEX(海运报价!$C$2:$C$2000,AGGREGATE(15,6,(ROW(海运报价!$C$2:$C$2000)-ROW(海运报价!$C$2)+1)/((海运报价!$D$2:$D$2000=$BE13)*(海运报价!$E$2:$E$2000=$BF13)),1)),"")) | BP13: =IF(OR($BE13="",$BF13=""),"",IFERROR(INDEX(海运报价!$C$2:$C$2000,AGGREGATE(15,6,(ROW(海运报价!$C$2:$C$2000)-ROW(海运报价!$C$2)+1)/((海运报价!$D$2:$D$2000=$BE13)*(海运报价!$E$2:$E$2000=$BF13)),2)),"")) | BQ13: =IF(OR($BE13="",$BF13=""),"",IFERROR(INDEX(海运报价!$C$2:$C$2000,AGGREGATE(15,6,(ROW(海运报价!$C$2:$C$2000)-ROW(海运报价!$C$2)+1)/((海运报价!$D$2:$D$2000=$BE13)*(海运报价!$E$2:$E$2000=$BF13)),3)),"")) | BR13: =IF(OR($BE13="",$BF13=""),"",IFERROR(INDEX(海运报价!$C$2:$C$2000,AGGREGATE(15,6,(ROW(海运报价!$C$2:$C$2000)-ROW(海运报价!$C$2)+1)/((海运报价!$D$2:$D$2000=$BE13)*(海运报价!$E$2:$E$2000=$BF13)),4)),"")) | BS13: =IF(OR($BE13="",$BF13=""),"",IFERROR(INDEX(海运报价!$C$2:$C$2000,AGGREGATE(15,6,(ROW(海运报价!$C$2:$C$2000)-ROW(海运报价!$C$2)+1)/((海运报价!$D$2:$D$2000=$BE13)*(海运报价!$E$2:$E$2000=$BF13)),5)),"")) | BT13: =IF(OR($BE13="",$BF13=""),"",IFERROR(INDEX(海运报价!$C$2:$C$2000,AGGREGATE(15,6,(ROW(海运报价!$C$2:$C$2000)-ROW(海运报价!$C$2)+1)/((海运报价!$D$2:$D$2000=$BE13)*(海运报价!$E$2:$E$2000=$BF13)),6)),"")) | BU13: =IF(OR($BE13="",$BF13=""),"",IFERROR(INDEX(海运报价!$C$2:$C$2000,AGGREGATE(15,6,(ROW(海运报价!$C$2:$C$2000)-ROW(海运报价!$C$2)+1)/((海运报价!$D$2:$D$2000=$BE13)*(海运报价!$E$2:$E$2000=$BF13)),7)),"")) | BV13: =IF(OR($BE13="",$BF13=""),"",IFERROR(INDEX(海运报价!$C$2:$C$2000,AGGREGATE(15,6,(ROW(海运报价!$C$2:$C$2000)-ROW(海运报价!$C$2)+1)/((海运报价!$D$2:$D$2000=$BE13)*(海运报价!$E$2:$E$2000=$BF13)),8)),"")) | BW13: =IF(OR($BE13="",$BF13=""),"",IFERROR(INDEX(海运报价!$C$2:$C$2000,AGGREGATE(15,6,(ROW(海运报价!$C$2:$C$2000)-ROW(海运报价!$C$2)+1)/((海运报价!$D$2:$D$2000=$BE13)*(海运报价!$E$2:$E$2000=$BF13)),9)),"")) | BX13: =IF(OR($BE13="",$BF13=""),"",IFERROR(INDEX(海运报价!$C$2:$C$2000,AGGREGATE(15,6,(ROW(海运报价!$C$2:$C$2000)-ROW(海运报价!$C$2)+1)/((海运报价!$D$2:$D$2000=$BE13)*(海运报价!$E$2:$E$2000=$BF13)),10)),"")) | BY13: =IF(OR($BE13="",$BF13=""),"",IFERROR(INDEX(海运报价!$C$2:$C$2000,AGGREGATE(15,6,(ROW(海运报价!$C$2:$C$2000)-ROW(海运报价!$C$2)+1)/((海运报价!$D$2:$D$2000=$BE13)*(海运报价!$E$2:$E$2000=$BF13)),11)),"")) | BZ13: =IF(OR($BE13="",$BF13=""),"",IFERROR(INDEX(海运报价!$C$2:$C$2000,AGGREGATE(15,6,(ROW(海运报价!$C$2:$C$2000)-ROW(海运报价!$C$2)+1)/((海运报价!$D$2:$D$2000=$BE13)*(海运报价!$E$2:$E$2000=$BF13)),12)),"")) | CA13: =IF(OR($BE13="",$BF13=""),"",IFERROR(INDEX(海运报价!$C$2:$C$2000,AGGREGATE(15,6,(ROW(海运报价!$C$2:$C$2000)-ROW(海运报价!$C$2)+1)/((海运报价!$D$2:$D$2000=$BE13)*(海运报价!$E$2:$E$2000=$BF13)),13)),"")) | CB13: =IF(OR($BE13="",$BF13=""),"",IFERROR(INDEX(海运报价!$C$2:$C$2000,AGGREGATE(15,6,(ROW(海运报价!$C$2:$C$2000)-ROW(海运报价!$C$2)+1)/((海运报价!$D$2:$D$2000=$BE13)*(海运报价!$E$2:$E$2000=$BF13)),14)),"")) | CC13: =IF(OR($BE13="",$BF13=""),"",IFERROR(INDEX(海运报价!$C$2:$C$2000,AGGREGATE(15,6,(ROW(海运报价!$C$2:$C$2000)-ROW(海运报价!$C$2)+1)/((海运报价!$D$2:$D$2000=$BE13)*(海运报价!$E$2:$E$2000=$BF13)),15)),"")) | CD13: =IF(OR(X13="",M13=""),"",X13+IF(OR(AA13="",M13=""),0,AA13/M13)+IF(AB13="",0,AB13)+IF(AI13="",0,AI13)+IF(Z13="",0,Z13)) | CE13: =I13+J13+K13+L13+AG13
C14: 7'9' | D14: =IF(C14="","",VLOOKUP($C14,箱规!$A$2:$S$23,9,FALSE)) | G14: =IF(OR(CD14="",CE14="",CE14>=1,X14=""),"",ROUNDUP((CD14-0.13*X14/1.13)/(1-CE14),2)) | H14: =IF(OR(CD14="",CE14="",X14=""),"",IF((1-CE14-参数!$B$16)<=0,"费率过高",ROUND((CD14-0.13*X14/1.13)/(1-CE14-参数!$B$16),2))) | I14: 0.15 | J14: 0.07 | K14: 0.15 | L14: 0.01 | M14: =参数!$B$2 | N14: =IF(C14="","",VLOOKUP($C14,箱规!$A$2:$S$23,14,FALSE)) | O14: =IF(C14="","",VLOOKUP($C14,箱规!$A$2:$S$23,5,FALSE)) | P14: =IF(C14="","",VLOOKUP($C14,箱规!$A$2:$S$23,6,FALSE)) | Q14: =IF(C14="","",VLOOKUP($C14,箱规!$A$2:$S$23,7,FALSE)) | R14: =IF(OR(N14="",O14="",P14="",Q14=""),"",MAX(N14*FBA规则!$B$6,(O14/FBA规则!$B$5)*(P14/FBA规则!$B$5)*(Q14/FBA规则!$B$5)/FBA规则!$B$7)) | S14: =IF(R14="","",IF(AND(N14*FBA规则!$B$6<=1,MAX(O14,P14,Q14)/FBA规则!$B$5<=15,MEDIAN(O14,P14,Q14)/FBA规则!$B$5<=12,MIN(O14,P14,Q14)/FBA规则!$B$5<=0.75),"小标准",IF(AND(R14<=20,MAX(O14,P14,Q14)/FBA规则!$B$5<=18,MEDIAN(O14,P14,Q14)/FBA规则!$B$5<=14,MIN(O14,P14,Q14)/FBA规则!$B$5<=8),"大标准",IF(AND(R14<=50,MAX(O14,P14,Q14)/FBA规则!$B$5<=59,MEDIAN(O14,P14,Q14)/FBA规则!$B$5<=33,MIN(O14,P14,Q14)/FBA规则!$B$5<=33,T14<=130),"大件",IF(R14<=50,"超大0-50lb",IF(R14<=70,"超大50-70lb",IF(R14<=150,"超大70-150lb","超大150lb+"))))))) | T14: =IF(OR(O14="",P14="",Q14=""),"",MAX(O14,P14,Q14)/FBA规则!$B$5+2*((MEDIAN(O14,P14,Q14)+MIN(O14,P14,Q14))/FBA规则!$B$5)) | U14: =参数!$B$15 | V14: =IF(OR(C14="",U14=""),"",(IF(OR(VLOOKUP($C14,箱规!$A$2:$S$23,4,FALSE)="",VLOOKUP($C14,箱规!$A$2:$S$23,4,FALSE)=0),VLOOKUP($C14,箱规!$A$2:$S$23,2,FALSE)*VLOOKUP($C14,箱规!$A$2:$S$23,3,FALSE)/10000,VLOOKUP($C14,箱规!$A$2:$S$23,4,FALSE)))*U14) | X14: =IF(AND(V14<>"",M14<>""),V14/M14,IF(AND(W14<>"",M14<>""),W14*1.13/M14,"")) | Y14: =IF(OR(X14="",G14=""),"",X14/G14) | AA14: =IF(OR(D14="",D14=0),"",IF(BG14="陆运",IF(BL14="",0,BL14)/D14,IF(BG14="海运",IF(BK14="",0,BK14)/D14,IF(BG14="海运+陆运",(IF(BK14="",0,BK14)+IF(BL14="",0,BL14))/D14,IF(BK14="",0,BK14)/D14)))) | AB14: =IF(OR(S14="",R14="",参数!$B$23=""),"",IF(S14="小标准",IFERROR(INDEX(FBA规则!$B$58:$C$65,MATCH(N14*FBA规则!$B$6*16,FBA规则!$A$58:$A$65,1),IF(参数!$B$23="旺季",2,1)),INDEX(FBA规则!$B$65:$C$65,1,IF(参数!$B$23="旺季",2,1))),IF(S14="大标准",IF(R14<=3,IFERROR(INDEX(FBA规则!$B$35:$C$46,MATCH(R14,FBA规则!$A$35:$A$46,1),IF(参数!$B$23="旺季",2,1)),INDEX(FBA规则!$B$46:$C$46,1,IF(参数!$B$23="旺季",2,1))),INDEX(FBA规则!$B$47:$C$47,1,IF(参数!$B$23="旺季",2,1))+FBA规则!$D$47*CEILING((R14-3)*4,1)),IF(S14="大件",INDEX(FBA规则!$B$50:$C$50,1,IF(参数!$B$23="旺季",2,1))+FBA规则!$D$50*MAX(0,CEILING(R14,1)-1),IF(S14="超大0-50lb",INDEX(FBA规则!$B$51:$C$51,1,IF(参数!$B$23="旺季",2,1))+FBA规则!$D$51*MAX(0,CEILING(R14,1)-1),IF(S14="超大50-70lb",INDEX(FBA规则!$B$52:$C$52,1,IF(参数!$B$23="旺季",2,1))+FBA规则!$D$52*MAX(0,R14-FBA规则!$F$52),IF(S14="超大70-150lb",INDEX(FBA规则!$B$53:$C$53,1,IF(参数!$B$23="旺季",2,1))+FBA规则!$D$53*MAX(0,R14-FBA规则!$F$53),INDEX(FBA规则!$B$54:$C$54,1,IF(参数!$B$23="旺季",2,1))+FBA规则!$D$54*MAX(0,R14-FBA规则!$F$54)))))))) | AC14: =IF(OR(G14="",I14=""),"",G14*I14) | AD14: =IF(OR(G14="",J14=""),"",G14*J14) | AE14: =IF(OR(G14="",K14=""),"",G14*K14) | AF14: =IF(OR(G14="",L14=""),"",G14*L14) | AG14: 0.02 | AH14: =IF(OR(G14="",AG14=""),"",G14*AG14) | AJ14: =IF(X14="","",X14+IF(OR(AA14="",M14=""),0,AA14/M14)+SUM(AB14:AF14)+IF(AH14="",0,AH14)+IF(AI14="",0,AI14)) | AK14: =IF(X14="","",0.13*X14/1.13) | AL14: =IF(OR(G14="",AJ14=""),"",G14+AK14-AJ14) | AM14: =IF(OR(AL14="",G14=""),"",AL14/G14) | AN14: =IF(OR(X14="",H14=""),"",X14/H14) | AP14: =AA14 | AQ14: =IF(OR(S14="",R14="",参数!$B$23=""),"",IF(S14="小标准",IFERROR(INDEX(FBA规则!$B$58:$C$65,MATCH(N14*FBA规则!$B$6*16,FBA规则!$A$58:$A$65,1),IF(参数!$B$23="旺季",2,1)),INDEX(FBA规则!$B$65:$C$65,1,IF(参数!$B$23="旺季",2,1))),IF(S14="大标准",IF(R14<=3,IFERROR(INDEX(FBA规则!$B$35:$C$46,MATCH(R14,FBA规则!$A$35:$A$46,1),IF(参数!$B$23="旺季",2,1)),INDEX(FBA规则!$B$46:$C$46,1,IF(参数!$B$23="旺季",2,1))),INDEX(FBA规则!$B$47:$C$47,1,IF(参数!$B$23="旺季",2,1))+FBA规则!$D$47*CEILING((R14-3)*4,1)),IF(S14="大件",INDEX(FBA规则!$B$50:$C$50,1,IF(参数!$B$23="旺季",2,1))+FBA规则!$D$50*MAX(0,CEILING(R14,1)-1),IF(S14="超大0-50lb",INDEX(FBA规则!$B$51:$C$51,1,IF(参数!$B$23="旺季",2,1))+FBA规则!$D$51*MAX(0,CEILING(R14,1)-1),IF(S14="超大50-70lb",INDEX(FBA规则!$B$52:$C$52,1,IF(参数!$B$23="旺季",2,1))+FBA规则!$D$52*MAX(0,R14-FBA规则!$F$52),IF(S14="超大70-150lb",INDEX(FBA规则!$B$53:$C$53,1,IF(参数!$B$23="旺季",2,1))+FBA规则!$D$53*MAX(0,R14-FBA规则!$F$53),INDEX(FBA规则!$B$54:$C$54,1,IF(参数!$B$23="旺季",2,1))+FBA规则!$D$54*MAX(0,R14-FBA规则!$F$54)))))))) | AR14: =IF(OR(H14="",I14=""),"",H14*I14) | AS14: =IF(OR(H14="",J14=""),"",H14*J14) | AT14: =IF(OR(H14="",K14=""),"",H14*K14) | AU14: =IF(OR(H14="",L14=""),"",H14*L14) | AV14: 0.02 | AW14: =IF(OR(H14="",AV14=""),"",H14*AV14) | AY14: =IF(X14="","",X14+IF(OR(AP14="",M14=""),0,AP14/M14)+SUM(AQ14:AU14)+IF(AW14="",0,AW14)+IF(AX14="",0,AX14)) | AZ14: =IF(X14="","",0.13*X14/1.13) | BA14: =IF(OR(H14="",AY14=""),"",H14+AZ14-AY14) | BB14: =IF(OR(BA14="",H14=""),"",BA14/H14) | BC14: =IF(OR(H14="",AY14=""),"",H14-AY14) | BD14: =IF(OR(BC14="",H14=""),"",BC14/H14) | BE14: 义乌 | BF14: ABE8 | BG14: 海运 | BH14: （最低价） | BI14: =IF(OR(BE14="",BF14=""),"",IF(AND(BH14<>"",BH14<>"（最低价）"),IFERROR(IF(SUMIFS(海运报价!$F$2:$F$2000,海运报价!$C$2:$C$2000,BH14,海运报价!$D$2:$D$2000,BE14,海运报价!$E$2:$E$2000,BF14)=0,"",SUMIFS(海运报价!$F$2:$F$2000,海运报价!$C$2:$C$2000,BH14,海运报价!$D$2:$D$2000,BE14,海运报价!$E$2:$E$2000,BF14)),""),IFERROR(IF(SUMIFS(海运下拉!$H$2:$H$311,海运下拉!$F$2:$F$311,BE14,海运下拉!$G$2:$G$311,BF14)=0,"",SUMIFS(海运下拉!$H$2:$H$311,海运下拉!$F$2:$F$311,BE14,海运下拉!$G$2:$G$311,BF14)),""))) | BJ14: =IF(C14="","",VLOOKUP($C14,箱规!$A$2:$S$23,18,FALSE)) | BK14: =IF(OR(BI14="",BJ14=""),"",BJ14*(BI14+IF(AND(BH14<>"",BH14<>"（最低价）"),IFERROR(AVERAGEIFS(海运报价!$H$2:$H$2000,海运报价!$C$2:$C$2000,BH14,海运报价!$D$2:$D$2000,BE14,海运报价!$E$2:$E$2000,BF14),0),IFERROR(SUMIFS(海运下拉!$J$2:$J$311,海运下拉!$F$2:$F$311,BE14,海运下拉!$G$2:$G$311,BF14),0)))) | BM14: =IF(OR(BE14="",BF14=""),"请选起运地+FBA仓",IF(AND(AND(BH14<>"",BH14<>"（最低价）"),BI14=""),"⚠该渠道不服务此仓：请重选渠道，或选「（最低价）」",IF(BI14="","无报价：请换起运地/仓库",IF(AND(BH14<>"",BH14<>"（最低价）"),"按你选的渠道「"&BH14&"」计价","按最低价「"&IFERROR(SUMIFS(海运下拉!$I$2:$I$311,海运下拉!$F$2:$F$311,BE14,海运下拉!$G$2:$G$311,BF14),"")&"」（渠道默认最低价）")))) | BO14: =IF(OR($BE14="",$BF14=""),"",IFERROR(INDEX(海运报价!$C$2:$C$2000,AGGREGATE(15,6,(ROW(海运报价!$C$2:$C$2000)-ROW(海运报价!$C$2)+1)/((海运报价!$D$2:$D$2000=$BE14)*(海运报价!$E$2:$E$2000=$BF14)),1)),"")) | BP14: =IF(OR($BE14="",$BF14=""),"",IFERROR(INDEX(海运报价!$C$2:$C$2000,AGGREGATE(15,6,(ROW(海运报价!$C$2:$C$2000)-ROW(海运报价!$C$2)+1)/((海运报价!$D$2:$D$2000=$BE14)*(海运报价!$E$2:$E$2000=$BF14)),2)),"")) | BQ14: =IF(OR($BE14="",$BF14=""),"",IFERROR(INDEX(海运报价!$C$2:$C$2000,AGGREGATE(15,6,(ROW(海运报价!$C$2:$C$2000)-ROW(海运报价!$C$2)+1)/((海运报价!$D$2:$D$2000=$BE14)*(海运报价!$E$2:$E$2000=$BF14)),3)),"")) | BR14: =IF(OR($BE14="",$BF14=""),"",IFERROR(INDEX(海运报价!$C$2:$C$2000,AGGREGATE(15,6,(ROW(海运报价!$C$2:$C$2000)-ROW(海运报价!$C$2)+1)/((海运报价!$D$2:$D$2000=$BE14)*(海运报价!$E$2:$E$2000=$BF14)),4)),"")) | BS14: =IF(OR($BE14="",$BF14=""),"",IFERROR(INDEX(海运报价!$C$2:$C$2000,AGGREGATE(15,6,(ROW(海运报价!$C$2:$C$2000)-ROW(海运报价!$C$2)+1)/((海运报价!$D$2:$D$2000=$BE14)*(海运报价!$E$2:$E$2000=$BF14)),5)),"")) | BT14: =IF(OR($BE14="",$BF14=""),"",IFERROR(INDEX(海运报价!$C$2:$C$2000,AGGREGATE(15,6,(ROW(海运报价!$C$2:$C$2000)-ROW(海运报价!$C$2)+1)/((海运报价!$D$2:$D$2000=$BE14)*(海运报价!$E$2:$E$2000=$BF14)),6)),"")) | BU14: =IF(OR($BE14="",$BF14=""),"",IFERROR(INDEX(海运报价!$C$2:$C$2000,AGGREGATE(15,6,(ROW(海运报价!$C$2:$C$2000)-ROW(海运报价!$C$2)+1)/((海运报价!$D$2:$D$2000=$BE14)*(海运报价!$E$2:$E$2000=$BF14)),7)),"")) | BV14: =IF(OR($BE14="",$BF14=""),"",IFERROR(INDEX(海运报价!$C$2:$C$2000,AGGREGATE(15,6,(ROW(海运报价!$C$2:$C$2000)-ROW(海运报价!$C$2)+1)/((海运报价!$D$2:$D$2000=$BE14)*(海运报价!$E$2:$E$2000=$BF14)),8)),"")) | BW14: =IF(OR($BE14="",$BF14=""),"",IFERROR(INDEX(海运报价!$C$2:$C$2000,AGGREGATE(15,6,(ROW(海运报价!$C$2:$C$2000)-ROW(海运报价!$C$2)+1)/((海运报价!$D$2:$D$2000=$BE14)*(海运报价!$E$2:$E$2000=$BF14)),9)),"")) | BX14: =IF(OR($BE14="",$BF14=""),"",IFERROR(INDEX(海运报价!$C$2:$C$2000,AGGREGATE(15,6,(ROW(海运报价!$C$2:$C$2000)-ROW(海运报价!$C$2)+1)/((海运报价!$D$2:$D$2000=$BE14)*(海运报价!$E$2:$E$2000=$BF14)),10)),"")) | BY14: =IF(OR($BE14="",$BF14=""),"",IFERROR(INDEX(海运报价!$C$2:$C$2000,AGGREGATE(15,6,(ROW(海运报价!$C$2:$C$2000)-ROW(海运报价!$C$2)+1)/((海运报价!$D$2:$D$2000=$BE14)*(海运报价!$E$2:$E$2000=$BF14)),11)),"")) | BZ14: =IF(OR($BE14="",$BF14=""),"",IFERROR(INDEX(海运报价!$C$2:$C$2000,AGGREGATE(15,6,(ROW(海运报价!$C$2:$C$2000)-ROW(海运报价!$C$2)+1)/((海运报价!$D$2:$D$2000=$BE14)*(海运报价!$E$2:$E$2000=$BF14)),12)),"")) | CA14: =IF(OR($BE14="",$BF14=""),"",IFERROR(INDEX(海运报价!$C$2:$C$2000,AGGREGATE(15,6,(ROW(海运报价!$C$2:$C$2000)-ROW(海运报价!$C$2)+1)/((海运报价!$D$2:$D$2000=$BE14)*(海运报价!$E$2:$E$2000=$BF14)),13)),"")) | CB14: =IF(OR($BE14="",$BF14=""),"",IFERROR(INDEX(海运报价!$C$2:$C$2000,AGGREGATE(15,6,(ROW(海运报价!$C$2:$C$2000)-ROW(海运报价!$C$2)+1)/((海运报价!$D$2:$D$2000=$BE14)*(海运报价!$E$2:$E$2000=$BF14)),14)),"")) | CC14: =IF(OR($BE14="",$BF14=""),"",IFERROR(INDEX(海运报价!$C$2:$C$2000,AGGREGATE(15,6,(ROW(海运报价!$C$2:$C$2000)-ROW(海运报价!$C$2)+1)/((海运报价!$D$2:$D$2000=$BE14)*(海运报价!$E$2:$E$2000=$BF14)),15)),"")) | CD14: =IF(OR(X14="",M14=""),"",X14+IF(OR(AA14="",M14=""),0,AA14/M14)+IF(AB14="",0,AB14)+IF(AI14="",0,AI14)+IF(Z14="",0,Z14)) | CE14: =I14+J14+K14+L14+AG14
C15: 8'10' | D15: =IF(C15="","",VLOOKUP($C15,箱规!$A$2:$S$23,9,FALSE)) | G15: =IF(OR(CD15="",CE15="",CE15>=1,X15=""),"",ROUNDUP((CD15-0.13*X15/1.13)/(1-CE15),2)) | H15: =IF(OR(CD15="",CE15="",X15=""),"",IF((1-CE15-参数!$B$16)<=0,"费率过高",ROUND((CD15-0.13*X15/1.13)/(1-CE15-参数!$B$16),2))) | I15: 0.15 | J15: 0.07 | K15: 0.15 | L15: 0.01 | M15: =参数!$B$2 | N15: =IF(C15="","",VLOOKUP($C15,箱规!$A$2:$S$23,14,FALSE)) | O15: =IF(C15="","",VLOOKUP($C15,箱规!$A$2:$S$23,5,FALSE)) | P15: =IF(C15="","",VLOOKUP($C15,箱规!$A$2:$S$23,6,FALSE)) | Q15: =IF(C15="","",VLOOKUP($C15,箱规!$A$2:$S$23,7,FALSE)) | R15: =IF(OR(N15="",O15="",P15="",Q15=""),"",MAX(N15*FBA规则!$B$6,(O15/FBA规则!$B$5)*(P15/FBA规则!$B$5)*(Q15/FBA规则!$B$5)/FBA规则!$B$7)) | S15: =IF(R15="","",IF(AND(N15*FBA规则!$B$6<=1,MAX(O15,P15,Q15)/FBA规则!$B$5<=15,MEDIAN(O15,P15,Q15)/FBA规则!$B$5<=12,MIN(O15,P15,Q15)/FBA规则!$B$5<=0.75),"小标准",IF(AND(R15<=20,MAX(O15,P15,Q15)/FBA规则!$B$5<=18,MEDIAN(O15,P15,Q15)/FBA规则!$B$5<=14,MIN(O15,P15,Q15)/FBA规则!$B$5<=8),"大标准",IF(AND(R15<=50,MAX(O15,P15,Q15)/FBA规则!$B$5<=59,MEDIAN(O15,P15,Q15)/FBA规则!$B$5<=33,MIN(O15,P15,Q15)/FBA规则!$B$5<=33,T15<=130),"大件",IF(R15<=50,"超大0-50lb",IF(R15<=70,"超大50-70lb",IF(R15<=150,"超大70-150lb","超大150lb+"))))))) | T15: =IF(OR(O15="",P15="",Q15=""),"",MAX(O15,P15,Q15)/FBA规则!$B$5+2*((MEDIAN(O15,P15,Q15)+MIN(O15,P15,Q15))/FBA规则!$B$5)) | U15: =参数!$B$15 | V15: =IF(OR(C15="",U15=""),"",(IF(OR(VLOOKUP($C15,箱规!$A$2:$S$23,4,FALSE)="",VLOOKUP($C15,箱规!$A$2:$S$23,4,FALSE)=0),VLOOKUP($C15,箱规!$A$2:$S$23,2,FALSE)*VLOOKUP($C15,箱规!$A$2:$S$23,3,FALSE)/10000,VLOOKUP($C15,箱规!$A$2:$S$23,4,FALSE)))*U15) | X15: =IF(AND(V15<>"",M15<>""),V15/M15,IF(AND(W15<>"",M15<>""),W15*1.13/M15,"")) | Y15: =IF(OR(X15="",G15=""),"",X15/G15) | AA15: =IF(OR(D15="",D15=0),"",IF(BG15="陆运",IF(BL15="",0,BL15)/D15,IF(BG15="海运",IF(BK15="",0,BK15)/D15,IF(BG15="海运+陆运",(IF(BK15="",0,BK15)+IF(BL15="",0,BL15))/D15,IF(BK15="",0,BK15)/D15)))) | AB15: =IF(OR(S15="",R15="",参数!$B$23=""),"",IF(S15="小标准",IFERROR(INDEX(FBA规则!$B$58:$C$65,MATCH(N15*FBA规则!$B$6*16,FBA规则!$A$58:$A$65,1),IF(参数!$B$23="旺季",2,1)),INDEX(FBA规则!$B$65:$C$65,1,IF(参数!$B$23="旺季",2,1))),IF(S15="大标准",IF(R15<=3,IFERROR(INDEX(FBA规则!$B$35:$C$46,MATCH(R15,FBA规则!$A$35:$A$46,1),IF(参数!$B$23="旺季",2,1)),INDEX(FBA规则!$B$46:$C$46,1,IF(参数!$B$23="旺季",2,1))),INDEX(FBA规则!$B$47:$C$47,1,IF(参数!$B$23="旺季",2,1))+FBA规则!$D$47*CEILING((R15-3)*4,1)),IF(S15="大件",INDEX(FBA规则!$B$50:$C$50,1,IF(参数!$B$23="旺季",2,1))+FBA规则!$D$50*MAX(0,CEILING(R15,1)-1),IF(S15="超大0-50lb",INDEX(FBA规则!$B$51:$C$51,1,IF(参数!$B$23="旺季",2,1))+FBA规则!$D$51*MAX(0,CEILING(R15,1)-1),IF(S15="超大50-70lb",INDEX(FBA规则!$B$52:$C$52,1,IF(参数!$B$23="旺季",2,1))+FBA规则!$D$52*MAX(0,R15-FBA规则!$F$52),IF(S15="超大70-150lb",INDEX(FBA规则!$B$53:$C$53,1,IF(参数!$B$23="旺季",2,1))+FBA规则!$D$53*MAX(0,R15-FBA规则!$F$53),INDEX(FBA规则!$B$54:$C$54,1,IF(参数!$B$23="旺季",2,1))+FBA规则!$D$54*MAX(0,R15-FBA规则!$F$54)))))))) | AC15: =IF(OR(G15="",I15=""),"",G15*I15) | AD15: =IF(OR(G15="",J15=""),"",G15*J15) | AE15: =IF(OR(G15="",K15=""),"",G15*K15) | AF15: =IF(OR(G15="",L15=""),"",G15*L15) | AG15: 0.02 | AH15: =IF(OR(G15="",AG15=""),"",G15*AG15) | AJ15: =IF(X15="","",X15+IF(OR(AA15="",M15=""),0,AA15/M15)+SUM(AB15:AF15)+IF(AH15="",0,AH15)+IF(AI15="",0,AI15)) | AK15: =IF(X15="","",0.13*X15/1.13) | AL15: =IF(OR(G15="",AJ15=""),"",G15+AK15-AJ15) | AM15: =IF(OR(AL15="",G15=""),"",AL15/G15) | AN15: =IF(OR(X15="",H15=""),"",X15/H15) | AP15: =AA15 | AQ15: =IF(OR(S15="",R15="",参数!$B$23=""),"",IF(S15="小标准",IFERROR(INDEX(FBA规则!$B$58:$C$65,MATCH(N15*FBA规则!$B$6*16,FBA规则!$A$58:$A$65,1),IF(参数!$B$23="旺季",2,1)),INDEX(FBA规则!$B$65:$C$65,1,IF(参数!$B$23="旺季",2,1))),IF(S15="大标准",IF(R15<=3,IFERROR(INDEX(FBA规则!$B$35:$C$46,MATCH(R15,FBA规则!$A$35:$A$46,1),IF(参数!$B$23="旺季",2,1)),INDEX(FBA规则!$B$46:$C$46,1,IF(参数!$B$23="旺季",2,1))),INDEX(FBA规则!$B$47:$C$47,1,IF(参数!$B$23="旺季",2,1))+FBA规则!$D$47*CEILING((R15-3)*4,1)),IF(S15="大件",INDEX(FBA规则!$B$50:$C$50,1,IF(参数!$B$23="旺季",2,1))+FBA规则!$D$50*MAX(0,CEILING(R15,1)-1),IF(S15="超大0-50lb",INDEX(FBA规则!$B$51:$C$51,1,IF(参数!$B$23="旺季",2,1))+FBA规则!$D$51*MAX(0,CEILING(R15,1)-1),IF(S15="超大50-70lb",INDEX(FBA规则!$B$52:$C$52,1,IF(参数!$B$23="旺季",2,1))+FBA规则!$D$52*MAX(0,R15-FBA规则!$F$52),IF(S15="超大70-150lb",INDEX(FBA规则!$B$53:$C$53,1,IF(参数!$B$23="旺季",2,1))+FBA规则!$D$53*MAX(0,R15-FBA规则!$F$53),INDEX(FBA规则!$B$54:$C$54,1,IF(参数!$B$23="旺季",2,1))+FBA规则!$D$54*MAX(0,R15-FBA规则!$F$54)))))))) | AR15: =IF(OR(H15="",I15=""),"",H15*I15) | AS15: =IF(OR(H15="",J15=""),"",H15*J15) | AT15: =IF(OR(H15="",K15=""),"",H15*K15) | AU15: =IF(OR(H15="",L15=""),"",H15*L15) | AV15: 0.02 | AW15: =IF(OR(H15="",AV15=""),"",H15*AV15) | AY15: =IF(X15="","",X15+IF(OR(AP15="",M15=""),0,AP15/M15)+SUM(AQ15:AU15)+IF(AW15="",0,AW15)+IF(AX15="",0,AX15)) | AZ15: =IF(X15="","",0.13*X15/1.13) | BA15: =IF(OR(H15="",AY15=""),"",H15+AZ15-AY15) | BB15: =IF(OR(BA15="",H15=""),"",BA15/H15) | BC15: =IF(OR(H15="",AY15=""),"",H15-AY15) | BD15: =IF(OR(BC15="",H15=""),"",BC15/H15) | BE15: 义乌 | BF15: ABE8 | BG15: 海运 | BH15: （最低价） | BI15: =IF(OR(BE15="",BF15=""),"",IF(AND(BH15<>"",BH15<>"（最低价）"),IFERROR(IF(SUMIFS(海运报价!$F$2:$F$2000,海运报价!$C$2:$C$2000,BH15,海运报价!$D$2:$D$2000,BE15,海运报价!$E$2:$E$2000,BF15)=0,"",SUMIFS(海运报价!$F$2:$F$2000,海运报价!$C$2:$C$2000,BH15,海运报价!$D$2:$D$2000,BE15,海运报价!$E$2:$E$2000,BF15)),""),IFERROR(IF(SUMIFS(海运下拉!$H$2:$H$311,海运下拉!$F$2:$F$311,BE15,海运下拉!$G$2:$G$311,BF15)=0,"",SUMIFS(海运下拉!$H$2:$H$311,海运下拉!$F$2:$F$311,BE15,海运下拉!$G$2:$G$311,BF15)),""))) | BJ15: =IF(C15="","",VLOOKUP($C15,箱规!$A$2:$S$23,18,FALSE)) | BK15: =IF(OR(BI15="",BJ15=""),"",BJ15*(BI15+IF(AND(BH15<>"",BH15<>"（最低价）"),IFERROR(AVERAGEIFS(海运报价!$H$2:$H$2000,海运报价!$C$2:$C$2000,BH15,海运报价!$D$2:$D$2000,BE15,海运报价!$E$2:$E$2000,BF15),0),IFERROR(SUMIFS(海运下拉!$J$2:$J$311,海运下拉!$F$2:$F$311,BE15,海运下拉!$G$2:$G$311,BF15),0)))) | BM15: =IF(OR(BE15="",BF15=""),"请选起运地+FBA仓",IF(AND(AND(BH15<>"",BH15<>"（最低价）"),BI15=""),"⚠该渠道不服务此仓：请重选渠道，或选「（最低价）」",IF(BI15="","无报价：请换起运地/仓库",IF(AND(BH15<>"",BH15<>"（最低价）"),"按你选的渠道「"&BH15&"」计价","按最低价「"&IFERROR(SUMIFS(海运下拉!$I$2:$I$311,海运下拉!$F$2:$F$311,BE15,海运下拉!$G$2:$G$311,BF15),"")&"」（渠道默认最低价）")))) | BO15: =IF(OR($BE15="",$BF15=""),"",IFERROR(INDEX(海运报价!$C$2:$C$2000,AGGREGATE(15,6,(ROW(海运报价!$C$2:$C$2000)-ROW(海运报价!$C$2)+1)/((海运报价!$D$2:$D$2000=$BE15)*(海运报价!$E$2:$E$2000=$BF15)),1)),"")) | BP15: =IF(OR($BE15="",$BF15=""),"",IFERROR(INDEX(海运报价!$C$2:$C$2000,AGGREGATE(15,6,(ROW(海运报价!$C$2:$C$2000)-ROW(海运报价!$C$2)+1)/((海运报价!$D$2:$D$2000=$BE15)*(海运报价!$E$2:$E$2000=$BF15)),2)),"")) | BQ15: =IF(OR($BE15="",$BF15=""),"",IFERROR(INDEX(海运报价!$C$2:$C$2000,AGGREGATE(15,6,(ROW(海运报价!$C$2:$C$2000)-ROW(海运报价!$C$2)+1)/((海运报价!$D$2:$D$2000=$BE15)*(海运报价!$E$2:$E$2000=$BF15)),3)),"")) | BR15: =IF(OR($BE15="",$BF15=""),"",IFERROR(INDEX(海运报价!$C$2:$C$2000,AGGREGATE(15,6,(ROW(海运报价!$C$2:$C$2000)-ROW(海运报价!$C$2)+1)/((海运报价!$D$2:$D$2000=$BE15)*(海运报价!$E$2:$E$2000=$BF15)),4)),"")) | BS15: =IF(OR($BE15="",$BF15=""),"",IFERROR(INDEX(海运报价!$C$2:$C$2000,AGGREGATE(15,6,(ROW(海运报价!$C$2:$C$2000)-ROW(海运报价!$C$2)+1)/((海运报价!$D$2:$D$2000=$BE15)*(海运报价!$E$2:$E$2000=$BF15)),5)),"")) | BT15: =IF(OR($BE15="",$BF15=""),"",IFERROR(INDEX(海运报价!$C$2:$C$2000,AGGREGATE(15,6,(ROW(海运报价!$C$2:$C$2000)-ROW(海运报价!$C$2)+1)/((海运报价!$D$2:$D$2000=$BE15)*(海运报价!$E$2:$E$2000=$BF15)),6)),"")) | BU15: =IF(OR($BE15="",$BF15=""),"",IFERROR(INDEX(海运报价!$C$2:$C$2000,AGGREGATE(15,6,(ROW(海运报价!$C$2:$C$2000)-ROW(海运报价!$C$2)+1)/((海运报价!$D$2:$D$2000=$BE15)*(海运报价!$E$2:$E$2000=$BF15)),7)),"")) | BV15: =IF(OR($BE15="",$BF15=""),"",IFERROR(INDEX(海运报价!$C$2:$C$2000,AGGREGATE(15,6,(ROW(海运报价!$C$2:$C$2000)-ROW(海运报价!$C$2)+1)/((海运报价!$D$2:$D$2000=$BE15)*(海运报价!$E$2:$E$2000=$BF15)),8)),"")) | BW15: =IF(OR($BE15="",$BF15=""),"",IFERROR(INDEX(海运报价!$C$2:$C$2000,AGGREGATE(15,6,(ROW(海运报价!$C$2:$C$2000)-ROW(海运报价!$C$2)+1)/((海运报价!$D$2:$D$2000=$BE15)*(海运报价!$E$2:$E$2000=$BF15)),9)),"")) | BX15: =IF(OR($BE15="",$BF15=""),"",IFERROR(INDEX(海运报价!$C$2:$C$2000,AGGREGATE(15,6,(ROW(海运报价!$C$2:$C$2000)-ROW(海运报价!$C$2)+1)/((海运报价!$D$2:$D$2000=$BE15)*(海运报价!$E$2:$E$2000=$BF15)),10)),"")) | BY15: =IF(OR($BE15="",$BF15=""),"",IFERROR(INDEX(海运报价!$C$2:$C$2000,AGGREGATE(15,6,(ROW(海运报价!$C$2:$C$2000)-ROW(海运报价!$C$2)+1)/((海运报价!$D$2:$D$2000=$BE15)*(海运报价!$E$2:$E$2000=$BF15)),11)),"")) | BZ15: =IF(OR($BE15="",$BF15=""),"",IFERROR(INDEX(海运报价!$C$2:$C$2000,AGGREGATE(15,6,(ROW(海运报价!$C$2:$C$2000)-ROW(海运报价!$C$2)+1)/((海运报价!$D$2:$D$2000=$BE15)*(海运报价!$E$2:$E$2000=$BF15)),12)),"")) | CA15: =IF(OR($BE15="",$BF15=""),"",IFERROR(INDEX(海运报价!$C$2:$C$2000,AGGREGATE(15,6,(ROW(海运报价!$C$2:$C$2000)-ROW(海运报价!$C$2)+1)/((海运报价!$D$2:$D$2000=$BE15)*(海运报价!$E$2:$E$2000=$BF15)),13)),"")) | CB15: =IF(OR($BE15="",$BF15=""),"",IFERROR(INDEX(海运报价!$C$2:$C$2000,AGGREGATE(15,6,(ROW(海运报价!$C$2:$C$2000)-ROW(海运报价!$C$2)+1)/((海运报价!$D$2:$D$2000=$BE15)*(海运报价!$E$2:$E$2000=$BF15)),14)),"")) | CC15: =IF(OR($BE15="",$BF15=""),"",IFERROR(INDEX(海运报价!$C$2:$C$2000,AGGREGATE(15,6,(ROW(海运报价!$C$2:$C$2000)-ROW(海运报价!$C$2)+1)/((海运报价!$D$2:$D$2000=$BE15)*(海运报价!$E$2:$E$2000=$BF15)),15)),"")) | CD15: =IF(OR(X15="",M15=""),"",X15+IF(OR(AA15="",M15=""),0,AA15/M15)+IF(AB15="",0,AB15)+IF(AI15="",0,AI15)+IF(Z15="",0,Z15)) | CE15: =I15+J15+K15+L15+AG15
C16: 9'12' | D16: =IF(C16="","",VLOOKUP($C16,箱规!$A$2:$S$23,9,FALSE)) | G16: =IF(OR(CD16="",CE16="",CE16>=1,X16=""),"",ROUNDUP((CD16-0.13*X16/1.13)/(1-CE16),2)) | H16: =IF(OR(CD16="",CE16="",X16=""),"",IF((1-CE16-参数!$B$16)<=0,"费率过高",ROUND((CD16-0.13*X16/1.13)/(1-CE16-参数!$B$16),2))) | I16: 0.15 | J16: 0.07 | K16: 0.15 | L16: 0.01 | M16: =参数!$B$2 | N16: =IF(C16="","",VLOOKUP($C16,箱规!$A$2:$S$23,14,FALSE)) | O16: =IF(C16="","",VLOOKUP($C16,箱规!$A$2:$S$23,5,FALSE)) | P16: =IF(C16="","",VLOOKUP($C16,箱规!$A$2:$S$23,6,FALSE)) | Q16: =IF(C16="","",VLOOKUP($C16,箱规!$A$2:$S$23,7,FALSE)) | R16: =IF(OR(N16="",O16="",P16="",Q16=""),"",MAX(N16*FBA规则!$B$6,(O16/FBA规则!$B$5)*(P16/FBA规则!$B$5)*(Q16/FBA规则!$B$5)/FBA规则!$B$7)) | S16: =IF(R16="","",IF(AND(N16*FBA规则!$B$6<=1,MAX(O16,P16,Q16)/FBA规则!$B$5<=15,MEDIAN(O16,P16,Q16)/FBA规则!$B$5<=12,MIN(O16,P16,Q16)/FBA规则!$B$5<=0.75),"小标准",IF(AND(R16<=20,MAX(O16,P16,Q16)/FBA规则!$B$5<=18,MEDIAN(O16,P16,Q16)/FBA规则!$B$5<=14,MIN(O16,P16,Q16)/FBA规则!$B$5<=8),"大标准",IF(AND(R16<=50,MAX(O16,P16,Q16)/FBA规则!$B$5<=59,MEDIAN(O16,P16,Q16)/FBA规则!$B$5<=33,MIN(O16,P16,Q16)/FBA规则!$B$5<=33,T16<=130),"大件",IF(R16<=50,"超大0-50lb",IF(R16<=70,"超大50-70lb",IF(R16<=150,"超大70-150lb","超大150lb+"))))))) | T16: =IF(OR(O16="",P16="",Q16=""),"",MAX(O16,P16,Q16)/FBA规则!$B$5+2*((MEDIAN(O16,P16,Q16)+MIN(O16,P16,Q16))/FBA规则!$B$5)) | U16: =参数!$B$15 | V16: =IF(OR(C16="",U16=""),"",(IF(OR(VLOOKUP($C16,箱规!$A$2:$S$23,4,FALSE)="",VLOOKUP($C16,箱规!$A$2:$S$23,4,FALSE)=0),VLOOKUP($C16,箱规!$A$2:$S$23,2,FALSE)*VLOOKUP($C16,箱规!$A$2:$S$23,3,FALSE)/10000,VLOOKUP($C16,箱规!$A$2:$S$23,4,FALSE)))*U16) | X16: =IF(AND(V16<>"",M16<>""),V16/M16,IF(AND(W16<>"",M16<>""),W16*1.13/M16,"")) | Y16: =IF(OR(X16="",G16=""),"",X16/G16) | AA16: =IF(OR(D16="",D16=0),"",IF(BG16="陆运",IF(BL16="",0,BL16)/D16,IF(BG16="海运",IF(BK16="",0,BK16)/D16,IF(BG16="海运+陆运",(IF(BK16="",0,BK16)+IF(BL16="",0,BL16))/D16,IF(BK16="",0,BK16)/D16)))) | AB16: =IF(OR(S16="",R16="",参数!$B$23=""),"",IF(S16="小标准",IFERROR(INDEX(FBA规则!$B$58:$C$65,MATCH(N16*FBA规则!$B$6*16,FBA规则!$A$58:$A$65,1),IF(参数!$B$23="旺季",2,1)),INDEX(FBA规则!$B$65:$C$65,1,IF(参数!$B$23="旺季",2,1))),IF(S16="大标准",IF(R16<=3,IFERROR(INDEX(FBA规则!$B$35:$C$46,MATCH(R16,FBA规则!$A$35:$A$46,1),IF(参数!$B$23="旺季",2,1)),INDEX(FBA规则!$B$46:$C$46,1,IF(参数!$B$23="旺季",2,1))),INDEX(FBA规则!$B$47:$C$47,1,IF(参数!$B$23="旺季",2,1))+FBA规则!$D$47*CEILING((R16-3)*4,1)),IF(S16="大件",INDEX(FBA规则!$B$50:$C$50,1,IF(参数!$B$23="旺季",2,1))+FBA规则!$D$50*MAX(0,CEILING(R16,1)-1),IF(S16="超大0-50lb",INDEX(FBA规则!$B$51:$C$51,1,IF(参数!$B$23="旺季",2,1))+FBA规则!$D$51*MAX(0,CEILING(R16,1)-1),IF(S16="超大50-70lb",INDEX(FBA规则!$B$52:$C$52,1,IF(参数!$B$23="旺季",2,1))+FBA规则!$D$52*MAX(0,R16-FBA规则!$F$52),IF(S16="超大70-150lb",INDEX(FBA规则!$B$53:$C$53,1,IF(参数!$B$23="旺季",2,1))+FBA规则!$D$53*MAX(0,R16-FBA规则!$F$53),INDEX(FBA规则!$B$54:$C$54,1,IF(参数!$B$23="旺季",2,1))+FBA规则!$D$54*MAX(0,R16-FBA规则!$F$54)))))))) | AC16: =IF(OR(G16="",I16=""),"",G16*I16) | AD16: =IF(OR(G16="",J16=""),"",G16*J16) | AE16: =IF(OR(G16="",K16=""),"",G16*K16) | AF16: =IF(OR(G16="",L16=""),"",G16*L16) | AG16: 0.02 | AH16: =IF(OR(G16="",AG16=""),"",G16*AG16) | AJ16: =IF(X16="","",X16+IF(OR(AA16="",M16=""),0,AA16/M16)+SUM(AB16:AF16)+IF(AH16="",0,AH16)+IF(AI16="",0,AI16)) | AK16: =IF(X16="","",0.13*X16/1.13) | AL16: =IF(OR(G16="",AJ16=""),"",G16+AK16-AJ16) | AM16: =IF(OR(AL16="",G16=""),"",AL16/G16) | AN16: =IF(OR(X16="",H16=""),"",X16/H16) | AP16: =AA16 | AQ16: =IF(OR(S16="",R16="",参数!$B$23=""),"",IF(S16="小标准",IFERROR(INDEX(FBA规则!$B$58:$C$65,MATCH(N16*FBA规则!$B$6*16,FBA规则!$A$58:$A$65,1),IF(参数!$B$23="旺季",2,1)),INDEX(FBA规则!$B$65:$C$65,1,IF(参数!$B$23="旺季",2,1))),IF(S16="大标准",IF(R16<=3,IFERROR(INDEX(FBA规则!$B$35:$C$46,MATCH(R16,FBA规则!$A$35:$A$46,1),IF(参数!$B$23="旺季",2,1)),INDEX(FBA规则!$B$46:$C$46,1,IF(参数!$B$23="旺季",2,1))),INDEX(FBA规则!$B$47:$C$47,1,IF(参数!$B$23="旺季",2,1))+FBA规则!$D$47*CEILING((R16-3)*4,1)),IF(S16="大件",INDEX(FBA规则!$B$50:$C$50,1,IF(参数!$B$23="旺季",2,1))+FBA规则!$D$50*MAX(0,CEILING(R16,1)-1),IF(S16="超大0-50lb",INDEX(FBA规则!$B$51:$C$51,1,IF(参数!$B$23="旺季",2,1))+FBA规则!$D$51*MAX(0,CEILING(R16,1)-1),IF(S16="超大50-70lb",INDEX(FBA规则!$B$52:$C$52,1,IF(参数!$B$23="旺季",2,1))+FBA规则!$D$52*MAX(0,R16-FBA规则!$F$52),IF(S16="超大70-150lb",INDEX(FBA规则!$B$53:$C$53,1,IF(参数!$B$23="旺季",2,1))+FBA规则!$D$53*MAX(0,R16-FBA规则!$F$53),INDEX(FBA规则!$B$54:$C$54,1,IF(参数!$B$23="旺季",2,1))+FBA规则!$D$54*MAX(0,R16-FBA规则!$F$54)))))))) | AR16: =IF(OR(H16="",I16=""),"",H16*I16) | AS16: =IF(OR(H16="",J16=""),"",H16*J16) | AT16: =IF(OR(H16="",K16=""),"",H16*K16) | AU16: =IF(OR(H16="",L16=""),"",H16*L16) | AV16: 0.02 | AW16: =IF(OR(H16="",AV16=""),"",H16*AV16) | AY16: =IF(X16="","",X16+IF(OR(AP16="",M16=""),0,AP16/M16)+SUM(AQ16:AU16)+IF(AW16="",0,AW16)+IF(AX16="",0,AX16)) | AZ16: =IF(X16="","",0.13*X16/1.13) | BA16: =IF(OR(H16="",AY16=""),"",H16+AZ16-AY16) | BB16: =IF(OR(BA16="",H16=""),"",BA16/H16) | BC16: =IF(OR(H16="",AY16=""),"",H16-AY16) | BD16: =IF(OR(BC16="",H16=""),"",BC16/H16) | BE16: 义乌 | BF16: ABE8 | BG16: 海运 | BH16: （最低价） | BI16: =IF(OR(BE16="",BF16=""),"",IF(AND(BH16<>"",BH16<>"（最低价）"),IFERROR(IF(SUMIFS(海运报价!$F$2:$F$2000,海运报价!$C$2:$C$2000,BH16,海运报价!$D$2:$D$2000,BE16,海运报价!$E$2:$E$2000,BF16)=0,"",SUMIFS(海运报价!$F$2:$F$2000,海运报价!$C$2:$C$2000,BH16,海运报价!$D$2:$D$2000,BE16,海运报价!$E$2:$E$2000,BF16)),""),IFERROR(IF(SUMIFS(海运下拉!$H$2:$H$311,海运下拉!$F$2:$F$311,BE16,海运下拉!$G$2:$G$311,BF16)=0,"",SUMIFS(海运下拉!$H$2:$H$311,海运下拉!$F$2:$F$311,BE16,海运下拉!$G$2:$G$311,BF16)),""))) | BJ16: =IF(C16="","",VLOOKUP($C16,箱规!$A$2:$S$23,18,FALSE)) | BK16: =IF(OR(BI16="",BJ16=""),"",BJ16*(BI16+IF(AND(BH16<>"",BH16<>"（最低价）"),IFERROR(AVERAGEIFS(海运报价!$H$2:$H$2000,海运报价!$C$2:$C$2000,BH16,海运报价!$D$2:$D$2000,BE16,海运报价!$E$2:$E$2000,BF16),0),IFERROR(SUMIFS(海运下拉!$J$2:$J$311,海运下拉!$F$2:$F$311,BE16,海运下拉!$G$2:$G$311,BF16),0)))) | BM16: =IF(OR(BE16="",BF16=""),"请选起运地+FBA仓",IF(AND(AND(BH16<>"",BH16<>"（最低价）"),BI16=""),"⚠该渠道不服务此仓：请重选渠道，或选「（最低价）」",IF(BI16="","无报价：请换起运地/仓库",IF(AND(BH16<>"",BH16<>"（最低价）"),"按你选的渠道「"&BH16&"」计价","按最低价「"&IFERROR(SUMIFS(海运下拉!$I$2:$I$311,海运下拉!$F$2:$F$311,BE16,海运下拉!$G$2:$G$311,BF16),"")&"」（渠道默认最低价）")))) | BO16: =IF(OR($BE16="",$BF16=""),"",IFERROR(INDEX(海运报价!$C$2:$C$2000,AGGREGATE(15,6,(ROW(海运报价!$C$2:$C$2000)-ROW(海运报价!$C$2)+1)/((海运报价!$D$2:$D$2000=$BE16)*(海运报价!$E$2:$E$2000=$BF16)),1)),"")) | BP16: =IF(OR($BE16="",$BF16=""),"",IFERROR(INDEX(海运报价!$C$2:$C$2000,AGGREGATE(15,6,(ROW(海运报价!$C$2:$C$2000)-ROW(海运报价!$C$2)+1)/((海运报价!$D$2:$D$2000=$BE16)*(海运报价!$E$2:$E$2000=$BF16)),2)),"")) | BQ16: =IF(OR($BE16="",$BF16=""),"",IFERROR(INDEX(海运报价!$C$2:$C$2000,AGGREGATE(15,6,(ROW(海运报价!$C$2:$C$2000)-ROW(海运报价!$C$2)+1)/((海运报价!$D$2:$D$2000=$BE16)*(海运报价!$E$2:$E$2000=$BF16)),3)),"")) | BR16: =IF(OR($BE16="",$BF16=""),"",IFERROR(INDEX(海运报价!$C$2:$C$2000,AGGREGATE(15,6,(ROW(海运报价!$C$2:$C$2000)-ROW(海运报价!$C$2)+1)/((海运报价!$D$2:$D$2000=$BE16)*(海运报价!$E$2:$E$2000=$BF16)),4)),"")) | BS16: =IF(OR($BE16="",$BF16=""),"",IFERROR(INDEX(海运报价!$C$2:$C$2000,AGGREGATE(15,6,(ROW(海运报价!$C$2:$C$2000)-ROW(海运报价!$C$2)+1)/((海运报价!$D$2:$D$2000=$BE16)*(海运报价!$E$2:$E$2000=$BF16)),5)),"")) | BT16: =IF(OR($BE16="",$BF16=""),"",IFERROR(INDEX(海运报价!$C$2:$C$2000,AGGREGATE(15,6,(ROW(海运报价!$C$2:$C$2000)-ROW(海运报价!$C$2)+1)/((海运报价!$D$2:$D$2000=$BE16)*(海运报价!$E$2:$E$2000=$BF16)),6)),"")) | BU16: =IF(OR($BE16="",$BF16=""),"",IFERROR(INDEX(海运报价!$C$2:$C$2000,AGGREGATE(15,6,(ROW(海运报价!$C$2:$C$2000)-ROW(海运报价!$C$2)+1)/((海运报价!$D$2:$D$2000=$BE16)*(海运报价!$E$2:$E$2000=$BF16)),7)),"")) | BV16: =IF(OR($BE16="",$BF16=""),"",IFERROR(INDEX(海运报价!$C$2:$C$2000,AGGREGATE(15,6,(ROW(海运报价!$C$2:$C$2000)-ROW(海运报价!$C$2)+1)/((海运报价!$D$2:$D$2000=$BE16)*(海运报价!$E$2:$E$2000=$BF16)),8)),"")) | BW16: =IF(OR($BE16="",$BF16=""),"",IFERROR(INDEX(海运报价!$C$2:$C$2000,AGGREGATE(15,6,(ROW(海运报价!$C$2:$C$2000)-ROW(海运报价!$C$2)+1)/((海运报价!$D$2:$D$2000=$BE16)*(海运报价!$E$2:$E$2000=$BF16)),9)),"")) | BX16: =IF(OR($BE16="",$BF16=""),"",IFERROR(INDEX(海运报价!$C$2:$C$2000,AGGREGATE(15,6,(ROW(海运报价!$C$2:$C$2000)-ROW(海运报价!$C$2)+1)/((海运报价!$D$2:$D$2000=$BE16)*(海运报价!$E$2:$E$2000=$BF16)),10)),"")) | BY16: =IF(OR($BE16="",$BF16=""),"",IFERROR(INDEX(海运报价!$C$2:$C$2000,AGGREGATE(15,6,(ROW(海运报价!$C$2:$C$2000)-ROW(海运报价!$C$2)+1)/((海运报价!$D$2:$D$2000=$BE16)*(海运报价!$E$2:$E$2000=$BF16)),11)),"")) | BZ16: =IF(OR($BE16="",$BF16=""),"",IFERROR(INDEX(海运报价!$C$2:$C$2000,AGGREGATE(15,6,(ROW(海运报价!$C$2:$C$2000)-ROW(海运报价!$C$2)+1)/((海运报价!$D$2:$D$2000=$BE16)*(海运报价!$E$2:$E$2000=$BF16)),12)),"")) | CA16: =IF(OR($BE16="",$BF16=""),"",IFERROR(INDEX(海运报价!$C$2:$C$2000,AGGREGATE(15,6,(ROW(海运报价!$C$2:$C$2000)-ROW(海运报价!$C$2)+1)/((海运报价!$D$2:$D$2000=$BE16)*(海运报价!$E$2:$E$2000=$BF16)),13)),"")) | CB16: =IF(OR($BE16="",$BF16=""),"",IFERROR(INDEX(海运报价!$C$2:$C$2000,AGGREGATE(15,6,(ROW(海运报价!$C$2:$C$2000)-ROW(海运报价!$C$2)+1)/((海运报价!$D$2:$D$2000=$BE16)*(海运报价!$E$2:$E$2000=$BF16)),14)),"")) | CC16: =IF(OR($BE16="",$BF16=""),"",IFERROR(INDEX(海运报价!$C$2:$C$2000,AGGREGATE(15,6,(ROW(海运报价!$C$2:$C$2000)-ROW(海运报价!$C$2)+1)/((海运报价!$D$2:$D$2000=$BE16)*(海运报价!$E$2:$E$2000=$BF16)),15)),"")) | CD16: =IF(OR(X16="",M16=""),"",X16+IF(OR(AA16="",M16=""),0,AA16/M16)+IF(AB16="",0,AB16)+IF(AI16="",0,AI16)+IF(Z16="",0,Z16)) | CE16: =I16+J16+K16+L16+AG16
... C25: 2.6*8 | D25: =IF(C25="","",VLOOKUP($C25,箱规!$A$2:$S$23,9,FALSE)) | G25: =IF(OR(CD25="",CE25="",CE25>=1,X25=""),"",ROUNDUP((CD25-0.13*X25/1.13)/(1-CE25),2)) | H25: =IF(OR(CD25="",CE25="",X25=""),"",IF((1-CE25-参数!$B$16)<=0,"费率过高",ROUND((CD25-0.13*X25/1.13)/(1-CE25-参数!$B$16),2))) | I25: 0.15 | J25: 0.07 | K25: 0.15 | L25: 0.01 | M25: =参数!$B$2 | N25: =IF(C25="","",VLOOKUP($C25,箱规!$A$2:$S$23,14,FALSE)) | O25: =IF(C25="","",VLOOKUP($C25,箱规!$A$2:$S$23,5,FALSE)) | P25: =IF(C25="","",VLOOKUP($C25,箱规!$A$2:$S$23,6,FALSE)) | Q25: =IF(C25="","",VLOOKUP($C25,箱规!$A$2:$S$23,7,FALSE)) | R25: =IF(OR(N25="",O25="",P25="",Q25=""),"",MAX(N25*FBA规则!$B$6,(O25/FBA规则!$B$5)*(P25/FBA规则!$B$5)*(Q25/FBA规则!$B$5)/FBA规则!$B$7)) | S25: =IF(R25="","",IF(AND(N25*FBA规则!$B$6<=1,MAX(O25,P25,Q25)/FBA规则!$B$5<=15,MEDIAN(O25,P25,Q25)/FBA规则!$B$5<=12,MIN(O25,P25,Q25)/FBA规则!$B$5<=0.75),"小标准",IF(AND(R25<=20,MAX(O25,P25,Q25)/FBA规则!$B$5<=18,MEDIAN(O25,P25,Q25)/FBA规则!$B$5<=14,MIN(O25,P25,Q25)/FBA规则!$B$5<=8),"大标准",IF(AND(R25<=50,MAX(O25,P25,Q25)/FBA规则!$B$5<=59,MEDIAN(O25,P25,Q25)/FBA规则!$B$5<=33,MIN(O25,P25,Q25)/FBA规则!$B$5<=33,T25<=130),"大件",IF(R25<=50,"超大0-50lb",IF(R25<=70,"超大50-70lb",IF(R25<=150,"超大70-150lb","超大150lb+"))))))) | T25: =IF(OR(O25="",P25="",Q25=""),"",MAX(O25,P25,Q25)/FBA规则!$B$5+2*((MEDIAN(O25,P25,Q25)+MIN(O25,P25,Q25))/FBA规则!$B$5)) | U25: =参数!$B$15 | V25: =IF(OR(C25="",U25=""),"",(IF(OR(VLOOKUP($C25,箱规!$A$2:$S$23,4,FALSE)="",VLOOKUP($C25,箱规!$A$2:$S$23,4,FALSE)=0),VLOOKUP($C25,箱规!$A$2:$S$23,2,FALSE)*VLOOKUP($C25,箱规!$A$2:$S$23,3,FALSE)/10000,VLOOKUP($C25,箱规!$A$2:$S$23,4,FALSE)))*U25) | X25: =IF(AND(V25<>"",M25<>""),V25/M25,IF(AND(W25<>"",M25<>""),W25*1.13/M25,"")) | Y25: =IF(OR(X25="",G25=""),"",X25/G25) | AA25: =IF(OR(D25="",D25=0),"",IF(BG25="陆运",IF(BL25="",0,BL25)/D25,IF(BG25="海运",IF(BK25="",0,BK25)/D25,IF(BG25="海运+陆运",(IF(BK25="",0,BK25)+IF(BL25="",0,BL25))/D25,IF(BK25="",0,BK25)/D25)))) | AB25: =IF(OR(S25="",R25="",参数!$B$23=""),"",IF(S25="小标准",IFERROR(INDEX(FBA规则!$B$58:$C$65,MATCH(N25*FBA规则!$B$6*16,FBA规则!$A$58:$A$65,1),IF(参数!$B$23="旺季",2,1)),INDEX(FBA规则!$B$65:$C$65,1,IF(参数!$B$23="旺季",2,1))),IF(S25="大标准",IF(R25<=3,IFERROR(INDEX(FBA规则!$B$35:$C$46,MATCH(R25,FBA规则!$A$35:$A$46,1),IF(参数!$B$23="旺季",2,1)),INDEX(FBA规则!$B$46:$C$46,1,IF(参数!$B$23="旺季",2,1))),INDEX(FBA规则!$B$47:$C$47,1,IF(参数!$B$23="旺季",2,1))+FBA规则!$D$47*CEILING((R25-3)*4,1)),IF(S25="大件",INDEX(FBA规则!$B$50:$C$50,1,IF(参数!$B$23="旺季",2,1))+FBA规则!$D$50*MAX(0,CEILING(R25,1)-1),IF(S25="超大0-50lb",INDEX(FBA规则!$B$51:$C$51,1,IF(参数!$B$23="旺季",2,1))+FBA规则!$D$51*MAX(0,CEILING(R25,1)-1),IF(S25="超大50-70lb",INDEX(FBA规则!$B$52:$C$52,1,IF(参数!$B$23="旺季",2,1))+FBA规则!$D$52*MAX(0,R25-FBA规则!$F$52),IF(S25="超大70-150lb",INDEX(FBA规则!$B$53:$C$53,1,IF(参数!$B$23="旺季",2,1))+FBA规则!$D$53*MAX(0,R25-FBA规则!$F$53),INDEX(FBA规则!$B$54:$C$54,1,IF(参数!$B$23="旺季",2,1))+FBA规则!$D$54*MAX(0,R25-FBA规则!$F$54)))))))) | AC25: =IF(OR(G25="",I25=""),"",G25*I25) | AD25: =IF(OR(G25="",J25=""),"",G25*J25) | AE25: =IF(OR(G25="",K25=""),"",G25*K25) | AF25: =IF(OR(G25="",L25=""),"",G25*L25) | AG25: 0.02 | AH25: =IF(OR(G25="",AG25=""),"",G25*AG25) | AJ25: =IF(X25="","",X25+IF(OR(AA25="",M25=""),0,AA25/M25)+SUM(AB25:AF25)+IF(AH25="",0,AH25)+IF(AI25="",0,AI25)) | AK25: =IF(X25="","",0.13*X25/1.13) | AL25: =IF(OR(G25="",AJ25=""),"",G25+AK25-AJ25) | AM25: =IF(OR(AL25="",G25=""),"",AL25/G25) | AN25: =IF(OR(X25="",H25=""),"",X25/H25) | AP25: =AA25 | AQ25: =IF(OR(S25="",R25="",参数!$B$23=""),"",IF(S25="小标准",IFERROR(INDEX(FBA规则!$B$58:$C$65,MATCH(N25*FBA规则!$B$6*16,FBA规则!$A$58:$A$65,1),IF(参数!$B$23="旺季",2,1)),INDEX(FBA规则!$B$65:$C$65,1,IF(参数!$B$23="旺季",2,1))),IF(S25="大标准",IF(R25<=3,IFERROR(INDEX(FBA规则!$B$35:$C$46,MATCH(R25,FBA规则!$A$35:$A$46,1),IF(参数!$B$23="旺季",2,1)),INDEX(FBA规则!$B$46:$C$46,1,IF(参数!$B$23="旺季",2,1))),INDEX(FBA规则!$B$47:$C$47,1,IF(参数!$B$23="旺季",2,1))+FBA规则!$D$47*CEILING((R25-3)*4,1)),IF(S25="大件",INDEX(FBA规则!$B$50:$C$50,1,IF(参数!$B$23="旺季",2,1))+FBA规则!$D$50*MAX(0,CEILING(R25,1)-1),IF(S25="超大0-50lb",INDEX(FBA规则!$B$51:$C$51,1,IF(参数!$B$23="旺季",2,1))+FBA规则!$D$51*MAX(0,CEILING(R25,1)-1),IF(S25="超大50-70lb",INDEX(FBA规则!$B$52:$C$52,1,IF(参数!$B$23="旺季",2,1))+FBA规则!$D$52*MAX(0,R25-FBA规则!$F$52),IF(S25="超大70-150lb",INDEX(FBA规则!$B$53:$C$53,1,IF(参数!$B$23="旺季",2,1))+FBA规则!$D$53*MAX(0,R25-FBA规则!$F$53),INDEX(FBA规则!$B$54:$C$54,1,IF(参数!$B$23="旺季",2,1))+FBA规则!$D$54*MAX(0,R25-FBA规则!$F$54)))))))) | AR25: =IF(OR(H25="",I25=""),"",H25*I25) | AS25: =IF(OR(H25="",J25=""),"",H25*J25) | AT25: =IF(OR(H25="",K25=""),"",H25*K25) | AU25: =IF(OR(H25="",L25=""),"",H25*L25) | AV25: 0.02 | AW25: =IF(OR(H25="",AV25=""),"",H25*AV25) | AY25: =IF(X25="","",X25+IF(OR(AP25="",M25=""),0,AP25/M25)+SUM(AQ25:AU25)+IF(AW25="",0,AW25)+IF(AX25="",0,AX25)) | AZ25: =IF(X25="","",0.13*X25/1.13) | BA25: =IF(OR(H25="",AY25=""),"",H25+AZ25-AY25) | BB25: =IF(OR(BA25="",H25=""),"",BA25/H25) | BC25: =IF(OR(H25="",AY25=""),"",H25-AY25) | BD25: =IF(OR(BC25="",H25=""),"",BC25/H25) | BE25: 义乌 | BF25: ABE8 | BG25: 海运 | BH25: （最低价） | BI25: =IF(OR(BE25="",BF25=""),"",IF(AND(BH25<>"",BH25<>"（最低价）"),IFERROR(IF(SUMIFS(海运报价!$F$2:$F$2000,海运报价!$C$2:$C$2000,BH25,海运报价!$D$2:$D$2000,BE25,海运报价!$E$2:$E$2000,BF25)=0,"",SUMIFS(海运报价!$F$2:$F$2000,海运报价!$C$2:$C$2000,BH25,海运报价!$D$2:$D$2000,BE25,海运报价!$E$2:$E$2000,BF25)),""),IFERROR(IF(SUMIFS(海运下拉!$H$2:$H$311,海运下拉!$F$2:$F$311,BE25,海运下拉!$G$2:$G$311,BF25)=0,"",SUMIFS(海运下拉!$H$2:$H$311,海运下拉!$F$2:$F$311,BE25,海运下拉!$G$2:$G$311,BF25)),""))) | BJ25: =IF(C25="","",VLOOKUP($C25,箱规!$A$2:$S$23,18,FALSE)) | BK25: =IF(OR(BI25="",BJ25=""),"",BJ25*(BI25+IF(AND(BH25<>"",BH25<>"（最低价）"),IFERROR(AVERAGEIFS(海运报价!$H$2:$H$2000,海运报价!$C$2:$C$2000,BH25,海运报价!$D$2:$D$2000,BE25,海运报价!$E$2:$E$2000,BF25),0),IFERROR(SUMIFS(海运下拉!$J$2:$J$311,海运下拉!$F$2:$F$311,BE25,海运下拉!$G$2:$G$311,BF25),0)))) | BM25: =IF(OR(BE25="",BF25=""),"请选起运地+FBA仓",IF(AND(AND(BH25<>"",BH25<>"（最低价）"),BI25=""),"⚠该渠道不服务此仓：请重选渠道，或选「（最低价）」",IF(BI25="","无报价：请换起运地/仓库",IF(AND(BH25<>"",BH25<>"（最低价）"),"按你选的渠道「"&BH25&"」计价","按最低价「"&IFERROR(SUMIFS(海运下拉!$I$2:$I$311,海运下拉!$F$2:$F$311,BE25,海运下拉!$G$2:$G$311,BF25),"")&"」（渠道默认最低价）")))) | BO25: =IF(OR($BE25="",$BF25=""),"",IFERROR(INDEX(海运报价!$C$2:$C$2000,AGGREGATE(15,6,(ROW(海运报价!$C$2:$C$2000)-ROW(海运报价!$C$2)+1)/((海运报价!$D$2:$D$2000=$BE25)*(海运报价!$E$2:$E$2000=$BF25)),1)),"")) | BP25: =IF(OR($BE25="",$BF25=""),"",IFERROR(INDEX(海运报价!$C$2:$C$2000,AGGREGATE(15,6,(ROW(海运报价!$C$2:$C$2000)-ROW(海运报价!$C$2)+1)/((海运报价!$D$2:$D$2000=$BE25)*(海运报价!$E$2:$E$2000=$BF25)),2)),"")) | BQ25: =IF(OR($BE25="",$BF25=""),"",IFERROR(INDEX(海运报价!$C$2:$C$2000,AGGREGATE(15,6,(ROW(海运报价!$C$2:$C$2000)-ROW(海运报价!$C$2)+1)/((海运报价!$D$2:$D$2000=$BE25)*(海运报价!$E$2:$E$2000=$BF25)),3)),"")) | BR25: =IF(OR($BE25="",$BF25=""),"",IFERROR(INDEX(海运报价!$C$2:$C$2000,AGGREGATE(15,6,(ROW(海运报价!$C$2:$C$2000)-ROW(海运报价!$C$2)+1)/((海运报价!$D$2:$D$2000=$BE25)*(海运报价!$E$2:$E$2000=$BF25)),4)),"")) | BS25: =IF(OR($BE25="",$BF25=""),"",IFERROR(INDEX(海运报价!$C$2:$C$2000,AGGREGATE(15,6,(ROW(海运报价!$C$2:$C$2000)-ROW(海运报价!$C$2)+1)/((海运报价!$D$2:$D$2000=$BE25)*(海运报价!$E$2:$E$2000=$BF25)),5)),"")) | BT25: =IF(OR($BE25="",$BF25=""),"",IFERROR(INDEX(海运报价!$C$2:$C$2000,AGGREGATE(15,6,(ROW(海运报价!$C$2:$C$2000)-ROW(海运报价!$C$2)+1)/((海运报价!$D$2:$D$2000=$BE25)*(海运报价!$E$2:$E$2000=$BF25)),6)),"")) | BU25: =IF(OR($BE25="",$BF25=""),"",IFERROR(INDEX(海运报价!$C$2:$C$2000,AGGREGATE(15,6,(ROW(海运报价!$C$2:$C$2000)-ROW(海运报价!$C$2)+1)/((海运报价!$D$2:$D$2000=$BE25)*(海运报价!$E$2:$E$2000=$BF25)),7)),"")) | BV25: =IF(OR($BE25="",$BF25=""),"",IFERROR(INDEX(海运报价!$C$2:$C$2000,AGGREGATE(15,6,(ROW(海运报价!$C$2:$C$2000)-ROW(海运报价!$C$2)+1)/((海运报价!$D$2:$D$2000=$BE25)*(海运报价!$E$2:$E$2000=$BF25)),8)),"")) | BW25: =IF(OR($BE25="",$BF25=""),"",IFERROR(INDEX(海运报价!$C$2:$C$2000,AGGREGATE(15,6,(ROW(海运报价!$C$2:$C$2000)-ROW(海运报价!$C$2)+1)/((海运报价!$D$2:$D$2000=$BE25)*(海运报价!$E$2:$E$2000=$BF25)),9)),"")) | BX25: =IF(OR($BE25="",$BF25=""),"",IFERROR(INDEX(海运报价!$C$2:$C$2000,AGGREGATE(15,6,(ROW(海运报价!$C$2:$C$2000)-ROW(海运报价!$C$2)+1)/((海运报价!$D$2:$D$2000=$BE25)*(海运报价!$E$2:$E$2000=$BF25)),10)),"")) | BY25: =IF(OR($BE25="",$BF25=""),"",IFERROR(INDEX(海运报价!$C$2:$C$2000,AGGREGATE(15,6,(ROW(海运报价!$C$2:$C$2000)-ROW(海运报价!$C$2)+1)/((海运报价!$D$2:$D$2000=$BE25)*(海运报价!$E$2:$E$2000=$BF25)),11)),"")) | BZ25: =IF(OR($BE25="",$BF25=""),"",IFERROR(INDEX(海运报价!$C$2:$C$2000,AGGREGATE(15,6,(ROW(海运报价!$C$2:$C$2000)-ROW(海运报价!$C$2)+1)/((海运报价!$D$2:$D$2000=$BE25)*(海运报价!$E$2:$E$2000=$BF25)),12)),"")) | CA25: =IF(OR($BE25="",$BF25=""),"",IFERROR(INDEX(海运报价!$C$2:$C$2000,AGGREGATE(15,6,(ROW(海运报价!$C$2:$C$2000)-ROW(海运报价!$C$2)+1)/((海运报价!$D$2:$D$2000=$BE25)*(海运报价!$E$2:$E$2000=$BF25)),13)),"")) | CB25: =IF(OR($BE25="",$BF25=""),"",IFERROR(INDEX(海运报价!$C$2:$C$2000,AGGREGATE(15,6,(ROW(海运报价!$C$2:$C$2000)-ROW(海运报价!$C$2)+1)/((海运报价!$D$2:$D$2000=$BE25)*(海运报价!$E$2:$E$2000=$BF25)),14)),"")) | CC25: =IF(OR($BE25="",$BF25=""),"",IFERROR(INDEX(海运报价!$C$2:$C$2000,AGGREGATE(15,6,(ROW(海运报价!$C$2:$C$2000)-ROW(海运报价!$C$2)+1)/((海运报价!$D$2:$D$2000=$BE25)*(海运报价!$E$2:$E$2000=$BF25)),15)),"")) | CD25: =IF(OR(X25="",M25=""),"",X25+IF(OR(AA25="",M25=""),0,AA25/M25)+IF(AB25="",0,AB25)+IF(AI25="",0,AI25)+IF(Z25="",0,Z25)) | CE25: =I25+J25+K25+L25+AG25

Sheet 全尺寸利润
A1: 全尺寸利润测算（按一件·尺寸来自箱规）
A2: 条件：起运地义乌 / FBA仓ABE8 / 渠道（最低价） / 海运；采购19.0元/㎡；汇率6.6838；目标利润率30%；发货日2026-10-27 → 旺季 FBA费率；费率 佣金15%/退款7%/广告15%/提现1%/仓储2%
A3: 尺寸 | B3: 面积㎡ | C3: 装数 | D3: 单件净重kg | E3: FBA计费重lb | F3: FBA分段 | G3: 海运渠道(最低) | H3: 海运单价 | I3: 采购RMB/件 | J3: 采购USD/件 | K3: 头程RMB/件 | L3: FBA USD/件 | M3: 保本售价USD | N3: 保本利润USD | O3: 保本利润率 | P3: 利润售价USD | Q3: 利润USD | R3: 利润率
A4: 2'3' | B4: 0.56 | C4: 16 | D4: 0.64 | E4: 1.41 | F4: 大标准 | G4: Y-A6全美直送专线 | H4: 9.18 | I4: 10.64 | J4: 1.59 | K4: 6.56 | L4: 5.68 | M4: 13.46 | N4: 0.0052 | O4: 0.00038502586 | P4: 26.9 | Q4: 8.07 | R4: 0.29996961
A5: 2'5' | B5: 0.93 | C5: 16 | D5: 1.28 | E5: 2.82 | F5: 大标准 | G5: Y-A6全美直送专线 | H5: 9.18 | I5: 17.67 | J5: 2.64 | K5: 12.44 | L5: 7.03 | M5: 18.72 | N5: 0.0014 | O5: 7.2359123e-05 | P5: 37.44 | Q5: 11.23 | R5: 0.30003618
A6: 2'6' | B6: 1.12 | C6: 14 | D6: 1.28 | E6: 3.39 | F6: 大标准 | G6: Y-A6全美直送专线 | H6: 9.18 | I6: 21.28 | J6: 3.18 | K6: 12.54 | L6: 7.62 | M6: 20.53 | N6: 0.0047 | O6: 0.00022698758 | P6: 41.04 | Q6: 12.31 | R6: 0.29996735
A7: 2'8' | B7: 1.49 | C7: 10 | D7: 1.71 | E7: 4 | F7: 大标准 | G7: Y-A6全美直送专线 | H7: 9.18 | I7: 28.31 | J7: 4.24 | K7: 16.8 | L7: 7.78 | M7: 23.41 | N7: 0.0042 | O7: 0.00017822602 | P7: 46.81 | Q7: 14.04 | R7: 0.30002504
A8: 2'10' | B8: 1.86 | C8: 9 | D8: 2.1 | E8: 4.63 | F8: 大标准 | G8: Y-A6全美直送专线 | H8: 9.18 | I8: 35.34 | J8: 5.29 | K8: 20.5 | L8: 8.02 | M8: 26.28 | N8: 0.0014 | O8: 5.3324904e-05 | P8: 52.56 | Q8: 15.77 | R8: 0.30002666
A9: 3'5' | B9: 1.38 | C9: 11 | D9: 1.59 | E9: 4.01 | F9: 大标准 | G9: Y-A6全美直送专线 | H9: 9.18 | I9: 26.22 | J9: 3.92 | K9: 15.6 | L9: 7.86 | M9: 22.78 | N9: 0.0027 | O9: 0.00011842855 | P9: 45.55 | Q9: 13.66 | R9: 0.29999337
A10: 4'6' | B10: 2.23 | C10: 7 | D10: 2.75 | E10: 6.06 | F10: 大标准 | G10: Y-A6全美直送专线 | H10: 9.18 | I10: 42.37 | J10: 6.34 | K10: 24.9 | L10: 8.5 | M10: 29.73 | N10: 0.002 | O10: 6.6746436e-05 | P10: 59.45 | Q10: 17.83 | R10: 0.29998292
A11: 5'7' | B11: 3.24 | C11: 4 | D11: 3.72 | E11: 8.22 | F11: 大标准 | G11: Y-A6全美直送专线 | H11: 9.18 | I11: 61.56 | J11: 9.21 | K11: 36.44 | L11: 9.14 | M11: 37.91 | N11: 0.0025 | O11: 6.5671853e-05 | P11: 75.81 | Q11: 22.74 | R11: 0.29999327
A12: 5'8' | B12: 3.71 | C12: 4 | D12: 3.8 | E12: 10.37 | F12: 大标准 | G12: Y-A6全美直送专线 | H12: 9.18 | I12: 70.49 | J12: 10.55 | K12: 37.64 | L12: 9.86 | M12: 41.38 | N12: 0.0036 | O12: 8.6248265e-05 | P12: 82.75 | Q12: 24.83 | R12: 0.30000688
A13: 6'9' | B13: 5.01 | C13: 3 | D13: 5.77 | E13: 12.72 | F13: 大件 | G13: Y-A6全美直送专线 | H13: 9.18 | I13: 95.19 | J13: 14.24 | K13: 56.95 | L13: 15.21 | M13: 60.56 | N13: 0.0023 | O13: 3.8010847e-05 | P13: 121.11 | Q13: 36.33 | R13: 0.29999424
A14: 7'9' | B14: 5.84 | C14: 2 | D14: 6.91 | E14: 16.2 | F14: 大件 | G14: Y-A6全美直送专线 | H14: 9.18 | I14: 110.96 | J14: 16.6 | K14: 68.53 | L14: 16.73 | M14: 69.46 | N14: 0.0014 | O14: 2.0381502e-05 | P14: 138.92 | Q14: 41.68 | R14: 0.30001019
A15: 8'10' | B15: 7.44 | C15: 2 | D15: 8.56 | E15: 18.87 | F15: 大件 | G15: Y-A6全美直送专线 | H15: 9.18 | I15: 141.36 | J15: 21.15 | K15: 84.09 | L15: 17.49 | M15: 81.32 | N15: 0.0043 | O15: 5.2672451e-05 | P15: 162.63 | Q15: 48.79 | R15: 0.30000789
... A25: 2.6*8 | B25: 1.9764 | C25: 8 | D25: 2.36 | E25: 5.35 | F25: 大标准 | G25: Y-A6全美直送专线 | H25: 9.18 | I25: 37.55 | J25: 5.62 | K25: 22.93 | L25: 8.26 | M25: 27.78 | N25: 0.0057 | O25: 0.00020694259 | P25: 55.54 | Q25: 16.66 | R25: 0.29999548
A26: 说明：保本售价=利润(含退税)≥0的最低价(向上到分)；利润售价=利润率约30%。改仓库/发货日/汇率后，请重新运行计算或看主表公式自动重算。

Sheet 海运报价
A1: 线路Sheet | B1: 区域 | C1: 渠道 | D1: 起运地 | E1: FBA仓 | F1: 单价(RMB/KG) | G1: 计费单位 | H1: 地毯附加(RMB/KG) | I1: 生效日期 | J1: 来源文件 | L1: 主表顺序：起运地→FBA仓→运输方式→海运渠道。下拉仅有价。刷新用 更新海运报价.py | N1: 渠道列表(旧/全量) | O1: 起运地列表 | P1: FBA仓列表(旧/全量勿直接用)
A2: 美西快线 | B2: 美西快线 | C2: Y-911专线 | D2: 义乌 | E2: 凯琦美西仓 | F2: 13.18 | G2: RMB/KG | H2: 0 | I2: 2026-10-26 | J2: 凯琦FBA报价_当期.xlsx | L2: 固定文件名：与成本表同目录的 凯琦FBA报价_当期.xlsx | N2: 718海派 | O2: 义乌 | P2: ABE3
A3: 美西快线 | B3: 美西快线 | C3: Y-911专线 | D3: 义乌 | E3: ONT8 | F3: 13.38 | G3: RMB/KG | H3: 0 | I3: 2026-10-26 | J3: 凯琦FBA报价_当期.xlsx | L3: Alt+F8 → RefreshOceanFreight；详见 宏更新说明.txt / 更新海运报价.bas | N3: Q-718专线 | O3: 青岛 | P3: ABE4
A4: 美西快线 | B4: 美西快线 | C4: Y-911专线 | D4: 义乌 | E4: LGB8 | F4: 13.38 | G4: RMB/KG | H4: 0 | I4: 2026-10-26 | J4: 凯琦FBA报价_当期.xlsx | L4: 当前已载入 943 条（义乌 819 / 青岛 124） | N4: Q15纽约海卡 | P4: ABE8
A5: 美西快线 | B5: 美西快线 | C5: Y-911专线 | D5: 义乌 | E5: LAX9 | F5: 13.38 | G5: RMB/KG | H5: 0 | I5: 2026-10-26 | J5: 凯琦FBA报价_当期.xlsx | N5: Y-718专线 | P5: ABQ2
A6: 美西快线 | B6: 美西快线 | C6: Y-911专线 | D6: 义乌 | E6: SBD1 | F6: 13.38 | G6: RMB/KG | H6: 0 | I6: 2026-10-26 | J6: 凯琦FBA报价_当期.xlsx | N6: Y-718海派 | P6: ACY2
A7: 美西快线 | B7: 美西快线 | C7: Y-911专线 | D7: 义乌 | E7: POC1 | F7: 13.68 | G7: RMB/KG | H7: 0 | I7: 2026-10-26 | J7: 凯琦FBA报价_当期.xlsx | N7: Y-911专线 | P7: AKR1
A8: 美西快线 | B8: 美西快线 | C8: Y-911专线 | D8: 义乌 | E8: POC2 | F8: 13.48 | G8: RMB/KG | H8: 0 | I8: 2026-10-26 | J8: 凯琦FBA报价_当期.xlsx | N8: Y-911海派 | P8: ALB1
A9: 美西快线 | B9: 美西快线 | C9: Y-911专线 | D9: 义乌 | E9: POC3 | F9: 13.48 | G9: RMB/KG | H9: 0 | I9: 2026-10-26 | J9: 凯琦FBA报价_当期.xlsx | N9: Y-A4-专线 | P9: AVP1
A10: 美西快线 | B10: 美西快线 | C10: Y-911专线 | D10: 义乌 | E10: IUSP | F10: 13.78 | G10: RMB/KG | H10: 0 | I10: 2026-10-26 | J10: 凯琦FBA报价_当期.xlsx | N10: Y-A4NY | P10: AVP9
A11: 美西快线 | B11: 美西快线 | C11: Y-911专线 | D11: 义乌 | E11: PSP3 | F11: 13.78 | G11: RMB/KG | H11: 0 | I11: 2026-10-26 | J11: 凯琦FBA报价_当期.xlsx | N11: Y-A4SAV | P11: BDL6
A12: 美西快线 | B12: 美西快线 | C12: Y-911专线 | D12: 义乌 | E12: LAS1 | F12: 14.28 | G12: RMB/KG | H12: 0 | I12: 2026-10-26 | J12: 凯琦FBA报价_当期.xlsx | N12: Y-A6全美直送专线 | P12: BFI3
A13: 美西快线 | B13: 美西快线 | C13: Y-911专线 | D13: 义乌 | E13: GYR2 | F13: 14.28 | G13: RMB/KG | H13: 0 | I13: 2026-10-26 | J13: 凯琦FBA报价_当期.xlsx | N13: Y-K13美中专线 | P13: BJC1
A14: 美西快线 | B14: 美西快线 | C14: Y-911专线 | D14: 义乌 | E14: GYR3 | F14: 14.28 | G14: RMB/KG | H14: 0 | I14: 2026-10-26 | J14: 凯琦FBA报价_当期.xlsx | N14: Y-K14芝加哥专线 | P14: BNA2
A15: 美西快线 | B15: 美西快线 | C15: Y-911专线 | D15: 义乌 | E15: VGT2 | F15: 14.28 | G15: RMB/KG | H15: 0 | I15: 2026-10-26 | J15: 凯琦FBA报价_当期.xlsx | N15: Y-K16萨瓦纳海卡 | P15: BNA6
A16: 美西快线 | B16: 美西快线 | C16: Y-911专线 | D16: 义乌 | E16: GEU3 | F16: 14.28 | G16: RMB/KG | H16: 0 | I16: 2026-10-26 | J16: 凯琦FBA报价_当期.xlsx | N16: Y-SEND普船专线 | P16: BOS7
... A35: 美西快线 | B35: 美西快线 | C35: Y-911专线 | D35: 义乌 | E35: AVP1 | F35: 19.08 | G35: RMB/KG | H35: 0 | I35: 2026-10-26 | J35: 凯琦FBA报价_当期.xlsx | N35: Y琦速达纽约 | P35: FTW2
A36: 美西快线 | B36: 美西快线 | C36: Y-911专线 | D36: 义乌 | E36: CLT2 | F36: 18.28 | G36: RMB/KG | H36: 0 | I36: 2026-10-26 | J36: 凯琦FBA报价_当期.xlsx | P36: FTW5
A37: 美西快线 | B37: 美西快线 | C37: Y-911专线 | D37: 义乌 | E37: RMN3 | F37: 19.08 | G37: RMB/KG | H37: 0 | I37: 2026-10-26 | J37: 凯琦FBA报价_当期.xlsx | P37: FTW9
A38: 美西快线 | B38: 美西快线 | C38: Y-911专线 | D38: 义乌 | E38: ORF2 | F38: 19.08 | G38: RMB/KG | H38: 0 | I38: 2026-10-26 | J38: 凯琦FBA报价_当期.xlsx | P38: FWA4
A39: 美西快线 | B39: 美西快线 | C39: Y-911专线 | D39: 义乌 | E39: RDU2 | F39: 18.58 | G39: RMB/KG | H39: 0 | I39: 2026-10-26 | J39: 凯琦FBA报价_当期.xlsx | P39: GEG2
A40: 美西快线 | B40: 美西快线 | C40: Y-911专线 | D40: 义乌 | E40: TEB9 | F40: 19.08 | G40: RMB/KG | H40: 0 | I40: 2026-10-26 | J40: 凯琦FBA报价_当期.xlsx | P40: GEU2
A41: 美西快线 | B41: 美西快线 | C41: Y-911专线 | D41: 义乌 | E41: SWF2 | F41: 19.08 | G41: RMB/KG | H41: 0 | I41: 2026-10-26 | J41: 凯琦FBA报价_当期.xlsx | P41: GEU3
A42: 美西快线 | B42: 美西快线 | C42: Y-琦速达 | D42: 义乌 | E42: 凯琦美西仓 | F42: 11.38 | G42: RMB/KG | H42: 0 | I42: 2026-10-26 | J42: 凯琦FBA报价_当期.xlsx | P42: GSO1
A43: 美西快线 | B43: 美西快线 | C43: Y-琦速达 | D43: 义乌 | E43: ONT8 | F43: 11.58 | G43: RMB/KG | H43: 0 | I43: 2026-10-26 | J43: 凯琦FBA报价_当期.xlsx | P43: GYR2
A44: 美西快线 | B44: 美西快线 | C44: Y-琦速达 | D44: 义乌 | E44: LGB8 | F44: 11.58 | G44: RMB/KG | H44: 0 | I44: 2026-10-26 | J44: 凯琦FBA报价_当期.xlsx | P44: GYR3
A45: 美西快线 | B45: 美西快线 | C45: Y-琦速达 | D45: 义乌 | E45: LAX9 | F45: 11.58 | G45: RMB/KG | H45: 0 | I45: 2026-10-26 | J45: 凯琦FBA报价_当期.xlsx | P45: HEA2
A46: 美西快线 | B46: 美西快线 | C46: Y-琦速达 | D46: 义乌 | E46: SBD1 | F46: 11.58 | G46: RMB/KG | H46: 0 | I46: 2026-10-26 | J46: 凯琦FBA报价_当期.xlsx | P46: HGR2
A47: 美西快线 | B47: 美西快线 | C47: Y-琦速达 | D47: 义乌 | E47: POC1 | F47: 11.88 | G47: RMB/KG | H47: 0 | I47: 2026-10-26 | J47: 凯琦FBA报价_当期.xlsx | P47: HGR6
... A195: 美西普船 | B195: 美西普船 | C195: Y-718专线 | D195: 义乌 | E195: TCY1 | F195: 9.78 | G195: RMB/KG | H195: 0 | I195: 2026-10-26 | J195: 凯琦FBA报价_当期.xlsx | P195: 美国西岸北（邮编97.98.99开头）
A196: 美西普船 | B196: 美西普船 | C196: Y-718专线 | D196: 义乌 | E196: TCY2 | F196: 9.78 | G196: RMB/KG | H196: 0 | I196: 2026-10-26 | J196: 凯琦FBA报价_当期.xlsx
A197: 美西普船 | B197: 美西普船 | C197: Y-718专线 | D197: 义乌 | E197: QXY8 | F197: 9.88 | G197: RMB/KG | H197: 0 | I197: 2026-10-26 | J197: 凯琦FBA报价_当期.xlsx
A198: 美西普船 | B198: 美西普船 | C198: Y-718专线 | D198: 义乌 | E198: IUTE | F198: 10.48 | G198: RMB/KG | H198: 0 | I198: 2026-10-26 | J198: 凯琦FBA报价_当期.xlsx
A199: 美西普船 | B199: 美西普船 | C199: Y-718专线 | D199: 义乌 | E199: ABQ2 | F199: 10.58 | G199: RMB/KG | H199: 0 | I199: 2026-10-26 | J199: 凯琦FBA报价_当期.xlsx
A200: 美西普船 | B200: 美西普船 | C200: Y-718专线 | D200: 义乌 | E200: MCC1 | F200: 10.08 | G200: RMB/KG | H200: 0 | I200: 2026-10-26 | J200: 凯琦FBA报价_当期.xlsx
A201: 美西普船 | B201: 美西普船 | C201: Y-718专线 | D201: 义乌 | E201: IAZ1 | F201: 10.08 | G201: RMB/KG | H201: 0 | I201: 2026-10-26 | J201: 凯琦FBA报价_当期.xlsx
A202: 美西普船 | B202: 美西普船 | C202: Y-718专线 | D202: 义乌 | E202: FTW1 | F202: 12.18 | G202: RMB/KG | H202: 0 | I202: 2026-10-26 | J202: 凯琦FBA报价_当期.xlsx
A203: 美西普船 | B203: 美西普船 | C203: Y-718专线 | D203: 义乌 | E203: IAH3 | F203: 12.28 | G203: RMB/KG | H203: 0 | I203: 2026-10-26 | J203: 凯琦FBA报价_当期.xlsx
A204: 美西普船 | B204: 美西普船 | C204: Y-718专线 | D204: 义乌 | E204: MDW2 | F204: 13.08 | G204: RMB/KG | H204: 0 | I204: 2026-10-26 | J204: 凯琦FBA报价_当期.xlsx
A205: 美西普船 | B205: 美西普船 | C205: Y-718专线 | D205: 义乌 | E205: IND9 | F205: 13.18 | G205: RMB/KG | H205: 0 | I205: 2026-10-26 | J205: 凯琦FBA报价_当期.xlsx
A206: 美西普船 | B206: 美西普船 | C206: Y-718专线 | D206: 义乌 | E206: FWA4 | F206: 13.08 | G206: RMB/KG | H206: 0 | I206: 2026-10-26 | J206: 凯琦FBA报价_当期.xlsx
A207: 美西普船 | B207: 美西普船 | C207: Y-718专线 | D207: 义乌 | E207: MQJ1 | F207: 13.18 | G207: RMB/KG | H207: 0 | I207: 2026-10-26 | J207: 凯琦FBA报价_当期.xlsx
... A944: 整柜直送 | B944: 整柜直送 | C944: Y-A6全美直送专线 | D944: 义乌 | E944: CLT2 | F944: 9.88 | G944: RMB/KG | H944: 0 | I944: 2026-10-26 | J944: 凯琦FBA报价_当期.xlsx

Sheet 海运下拉
A1: 起运地 | B1: 义乌FBA仓 | C1: 青岛FBA仓 | D1: 填写顺序：起运地 → FBA仓 → 运输方式 → 海运渠道。仓/渠道下拉仅含有报价项。 | E1: 义乌||ABE3 | F1: 起运地 | G1: FBA仓 | H1: 该仓最低单价 | I1: 最低价渠道 | J1: 地毯附加 | L1: 义乌可选渠道 | M1: 青岛可选渠道 | N1: 渠道下拉：默认「（最低价）」=按该仓最低价；选具体渠道=按你的选择计价 | T1: 义乌||BWI4 | U1: 义乌||CHA2 | V1: 义乌||CHO1 | W1: 义乌||CLT2 | X1: 义乌||CLT3 | Y1: 义乌||CLT6 | Z1: 义乌||CMH2 | AA1: 义乌||CMH3 | AB1: 义乌||DAL3 | AC1: 义乌||DCA6 | AD1: 义乌||DEN8 | AE1: 义乌||DET1 | AF1: 义乌||DET2 | AG1: 义乌||DFW6 | AH1: 义乌||DFW7 | AI1: 义乌||FAT2 | AJ1: 义乌||FOE1 | AK1: 义乌||FTW1 | AL1: 义乌||FTW2 | AM1: 义乌||FTW5 | AN1: 义乌||FTW9 | AO1: 义乌||FWA4 | AP1: 义乌||GEG2 | AQ1: 义乌||GEU2 | AR1: 义乌||GEU3 | AS1: 义乌||GSO1 | AT1: 义乌||GYR2 | AU1: 义乌||GYR3 | AV1: 义乌||HEA2 | AW1: 义乌||HGR2 | AX1: 义乌||HGR6 | AY1: 义乌||HIA1 | AZ1: 义乌||HLI2 | BA1: 义乌||HOU1 | BB1: 义乌||HOU2 | BC1: 义乌||HOU3 | BD1: 义乌||HOU7 | BE1: 义乌||HOU8 | BF1: 义乌||HSV1 | BG1: 义乌||IAH3 | BH1: 义乌||IAZ1 | BI1: 义乌||ICA3 | BJ1: 义乌||ICT2 | BK1: 义乌||IGA3 | BL1: 义乌||IGQ2 | BM1: 义乌||ILG1 | BN1: 义乌||IMI1 | BO1: 义乌||IMO1 | BP1: 义乌||IMS1 | BQ1: 义乌||INC1 | BR1: 义乌||IND5 | BS1: 义乌||IND9 | BT1: 义乌||IPA1 | BU1: 义乌||ITX3 | BV1: 义乌||IUSJ | BW1: 义乌||IUSP | BX1: 义乌||IUSR | BY1: 义乌||IUST | BZ1: 义乌||IUTE | CA1: 义乌||IUTH | CB1: 义乌||IUTJ | CC1: 义乌||IUTL | CD1: 义乌||IWA6 | CE1: 义乌||JAX3 | CF1: 义乌||JVL1 | CG1: 义乌||LAS1 | CH1: 义乌||LAS6 | CI1: 义乌||LAX9 | CJ1: 义乌||LBE1 | CK1: 义乌||LFT1 | CL1: 义乌||LGB4 | CM1: 义乌||LGB6 | CN1: 义乌||LGB8 | CO1: 义乌||LIT2 | CP1: 义乌||MCC1 | CQ1: 义乌||MCE1 | CR1: 义乌||MCI4 | CS1: 义乌||MCO2 | CT1: 义乌||MDT1 | CU1: 义乌||MDT4 | CV1: 义乌||MDW2 | CW1: 义乌||MDW6 | CX1: 义乌||MEM1 | CY1: 义乌||MEM8 | CZ1: 义乌||MGE1 | DA1: 义乌||MGE3 | DB1: 义乌||MIT2 | DC1: 义乌||MKC4 | DD1: 义乌||MQJ1 | DE1: 义乌||MQY2 | DF1: 义乌||OAK3 | DG1: 义乌||OKC2 | DH1: 义乌||ONT8 | DI1: 义乌||ORD2 | DJ1: 义乌||ORF2 | DK1: 义乌||PBI2 | DL1: 义乌||PDX7 | DM1: 义乌||PHX5 | DN1: 义乌||PHX7 | DO1: 义乌||PIT2 | DP1: 义乌||POC1 | DQ1: 义乌||POC2 | DR1: 义乌||POC3 | DS1: 义乌||PSP3 | DT1: 义乌||QXY8 | DU1: 义乌||RDU2 | DV1: 义乌||RFD2 | DW1: 义乌||RFD4 | DX1: 义乌||RMN3 | DY1: 义乌||RYY2 | DZ1: 义乌||SAT1 | EA1: 义乌||SAT4 | EB1: 义乌||SAT6 | EC1: 义乌||SBD1 | ED1: 义乌||SBD2 | EE1: 义乌||SCK1 | EF1: 义乌||SCK3 | EG1: 义乌||SCK4 | EH1: 义乌||SCK8 | EI1: 义乌||SLC2 | EJ1: 义乌||SMF1 | EK1: 义乌||SMF3 | EL1: 义乌||SMF6 | EM1: 义乌||SMF7 | EN1: 义乌||SNA4 | EO1: 义乌||STL3 | EP1: 义乌||STL4 | EQ1: 义乌||SWF1 | ER1: 义乌||SWF2 | ES1: 义乌||TCY1 | ET1: 义乌||TCY2 | EU1: 义乌||TEB3 | EV1: 义乌||TEB4 | EW1: 义乌||TEB6 | EX1: 义乌||TEB9 | EY1: 义乌||TOL3 | EZ1: 义乌||TPA2 | FA1: 义乌||TPA3 | FB1: 义乌||TTN2 | FC1: 义乌||VGT2 | FD1: 义乌||XCAB | FE1: 义乌||XEW5 | FF1: 义乌||XLX1 | FG1: 义乌||XLX6 | FH1: 义乌||XLX7 | FI1: 义乌||XMI3 | FJ1: 义乌||XPB2 | FK1: 义乌||XPH1 | FL1: 义乌||XRI3 | FM1: 义乌||XYY1 | FN1: 义乌||XYY3 | FO1: 义乌||XYY4 | FP1: 义乌||YEG1 | FQ1: 义乌||YEG2 | FR1: 义乌||YGK1 | FS1: 义乌||YHM1 | FT1: 义乌||YOO1 | FU1: 义乌||YOW1 | FV1: 义乌||YOW3 | FW1: 义乌||YVR1 | FX1: 义乌||YVR2 | FY1: 义乌||YVR3 | FZ1: 义乌||YVR4 | GA1: 义乌||YXU1 | GB1: 义乌||YXX2 | GC1: 义乌||YYC1 | GD1: 义乌||YYC4 | GE1: 义乌||YYC6 | GF1: 义乌||YYZ1 | GG1: 义乌||YYZ3 | GH1: 义乌||YYZ4 | GI1: 义乌||YYZ6 | GJ1: 义乌||YYZ7 | GK1: 义乌||YYZ9 | GL1: 义乌||凯琦美西仓 | GM1: 义乌||商业地址 | GN1: 义乌||美国东岸(邮编0.1.2.3.4开头) | GO1: 义乌||美国中部(邮编5.6.7开头) | GP1: 义乌||美国西岸北（邮编97.98.99开头） | GQ1: 青岛||ABE3 | GR1: 青岛||ABE4 | GS1: 青岛||ABE8 | GT1: 青岛||ABQ2 | GU1: 青岛||ACY2 | GV1: 青岛||AKR1 | GW1: 青岛||ALB1 | GX1: 青岛||AVP1 | GY1: 青岛||AVP9 | GZ1: 青岛||BDL6 | HA1: 青岛||BJC1 | HB1: 青岛||BNA2 | HC1: 青岛||BNA6 | HD1: 青岛||BOS7 | HE1: 青岛||BWI4 | HF1: 青岛||CHA2 | HG1: 青岛||CHO1 | HH1: 青岛||CLT2 | HI1: 青岛||CLT6 | HJ1: 青岛||CMH2 | HK1: 青岛||CMH3 | HL1: 青岛||DCA6 | HM1: 青岛||DEN8 | HN1: 青岛||FAT2 | HO1: 青岛||FTW1 | HP1: 青岛||FWA4 | HQ1: 青岛||GEG2 | HR1: 青岛||GEU2 | HS1: 青岛||GEU3 | HT1: 青岛||GSO1 | HU1: 青岛||GYR2 | HV1: 青岛||GYR3 | HW1: 青岛||HEA2 | HX1: 青岛||HGR2 | HY1: 青岛||HGR6 | HZ1: 青岛||HIA1 | IA1: 青岛||HLI2 | IB1: 青岛||HSV1 | IC1: 青岛||IAH3 | ID1: 青岛||IAZ1 | IE1: 青岛||ILG1 | IF1: 青岛||IND9 | IG1: 青岛||IPA1 | IH1: 青岛||ITX3 | II1: 青岛||IUSJ | IJ1: 青岛||IUSP | IK1: 青岛||IUSR | IL1: 青岛||IUST | IM1: 青岛||IUTE | IN1: 青岛||IUTJ | IO1: 青岛||IUTL | IP1: 青岛||LAS1 | IQ1: 青岛||LAS6 | IR1: 青岛||LAX9 | IS1: 青岛||LBE1 | IT1: 青岛||LGB4 | IU1: 青岛||LGB6 | IV1: 青岛||LGB8 | IW1: 青岛||MCC1 | IX1: 青岛||MCE1 | IY1: 青岛||MCO2 | IZ1: 青岛||MDT1 | JA1: 青岛||MDT4 | JB1: 青岛||MDW2 | JC1: 青岛||MEM1 | JD1: 青岛||MGE1 | JE1: 青岛||MGE3 | JF1: 青岛||MIT2 | JG1: 青岛||MQJ1 | JH1: 青岛||OAK3 | JI1: 青岛||ONT8 | JJ1: 青岛||ORF2 | JK1: 青岛||PDX7 | JL1: 青岛||PHX5 | JM1: 青岛||PHX7 | JN1: 青岛||PIT2 | JO1: 青岛||POC1 | JP1: 青岛||POC2 | JQ1: 青岛||POC3 | JR1: 青岛||PSP3 | JS1: 青岛||QXY8 | JT1: 青岛||RDU2 | JU1: 青岛||RFD2 | JV1: 青岛||RMN3 | JW1: 青岛||RYY2 | JX1: 青岛||SBD1 | JY1: 青岛||SBD2 | JZ1: 青岛||SCK1 | KA1: 青岛||SCK4 | KB1: 青岛||SCK8 | KC1: 青岛||SLC2 | KD1: 青岛||SMF3 | KE1: 青岛||SMF6 | KF1: 青岛||SNA4 | KG1: 青岛||SWF1 | KH1: 青岛||SWF2 | KI1: 青岛||TCY1 | KJ1: 青岛||TCY2 | KK1: 青岛||TEB3 | KL1: 青岛||TEB4 | KM1: 青岛||TEB6 | KN1: 青岛||TEB9 | KO1: 青岛||TPA2 | KP1: 青岛||TPA3 | KQ1: 青岛||TTN2 | KR1: 青岛||VGT2 | KS1: 青岛||XEW5 | KT1: 青岛||XLX1 | KU1: 青岛||XLX6 | KV1: 青岛||XLX7 | KW1: 青岛||XPH1 | KX1: 青岛||XRI3 | KY1: 青岛||凯琦美西仓 | KZ1: 青岛||美国东岸(邮编0.1.2.3.4开头) | LA1: 青岛||美国中部(邮编5.6.7开头) | LB1: 青岛||美国西岸北（邮编97.98.99开头）
A2: 义乌 | B2: ABE3 | C2: ABE3 | E2: 4 | F2: 义乌 | G2: ABE3 | H2: 9.48 | I2: Y-A4NY | J2: 0 | L2: （最低价） | M2: （最低价） | T2: 4 | U2: 6 | V2: 4 | W2: 12 | X2: 2 | Y2: 6 | Z2: 6 | AA2: 6 | AB2: 1 | AC2: 4 | AD2: 3 | AE2: 2 | AF2: 2 | AG2: 1 | AH2: 1 | AI2: 3 | AJ2: 3 | AK2: 6 | AL2: 1 | AM2: 1 | AN2: 1 | AO2: 7 | AP2: 4 | AQ2: 6 | AR2: 6 | AS2: 6 | AT2: 6 | AU2: 6 | AV2: 4 | AW2: 4 | AX2: 4 | AY2: 4 | AZ2: 6 | BA2: 1 | BB2: 1 | BC2: 1 | BD2: 1 | BE2: 1 | BF2: 6 | BG2: 6 | BH2: 1 | BI2: 1 | BJ2: 1 | BK2: 2 | BL2: 2 | BM2: 4 | BN2: 1 | BO2: 1 | BP2: 2 | BQ2: 2 | BR2: 2 | BS2: 8 | BT2: 4 | BU2: 1 | BV2: 2 | BW2: 6 | BX2: 6 | BY2: 4 | BZ2: 1 | CA2: 1 | CB2: 1 | CC2: 1 | CD2: 1 | CE2: 2 | CF2: 2 | CG2: 6 | CH2: 3 | CI2: 7 | CJ2: 4 | CK2: 1 | CL2: 3 | CM2: 3 | CN2: 6 | CO2: 1 | CP2: 4 | CQ2: 4 | CR2: 1 | CS2: 6 | CT2: 4 | CU2: 4 | CV2: 8 | CW2: 2 | CX2: 7 | CY2: 1 | CZ2: 4 | DA2: 6 | DB2: 6 | DC2: 2 | DD2: 7 | DE2: 2 | DF2: 2 | DG2: 1 | DH2: 6 | DI2: 2 | DJ2: 8 | DK2: 2 | DL2: 3 | DM2: 3 | DN2: 3 | DO2: 4 | DP2: 5 | DQ2: 5 | DR2: 6 | DS2: 4 | DT2: 6 | DU2: 10 | DV2: 5 | DW2: 2 | DX2: 8 | DY2: 6 | DZ2: 1 | EA2: 1 | EB2: 1 | EC2: 7 | ED2: 3 | EE2: 4 | EF2: 1 | EG2: 7 | EH2: 7 | EI2: 3 | EJ2: 1 | EK2: 8 | EL2: 4 | EM2: 1 | EN2: 3 | EO2: 2 | EP2: 2 | EQ2: 4 | ER2: 8 | ES2: 6 | ET2: 6 | EU2: 4 | EV2: 4 | EW2: 4 | EX2: 10 | EY2: 2 | EZ2: 6 | FA2: 6 | FB2: 4 | FC2: 5 | FD2: 1 | FE2: 4 | FF2: 4 | FG2: 6 | FH2: 2 | FI2: 2 | FJ2: 2 | FK2: 2 | FL2: 4 | FM2: 7 | FN2: 4 | FO2: 4 | FP2: 6 | FQ2: 6 | FR2: 7 | FS2: 7 | FT2: 7 | FU2: 7 | FV2: 7 | FW2: 6 | FX2: 6 | FY2: 6 | FZ2: 6 | GA2: 7 | GB2: 6 | GC2: 6 | GD2: 6 | GE2: 6 | GF2: 7 | GG2: 7 | GH2: 7 | GI2: 7 | GJ2: 7 | GK2: 7 | GL2: 5 | GM2: 4 | GN2: 4 | GO2: 4 | GP2: 4 | GQ2: 1 | GR2: 1 | GS2: 2 | GT2: 1 | GU2: 1 | GV2: 1 | GW2: 1 | GX2: 2 | GY2: 1 | GZ2: 1 | HA2: 1 | HB2: 1 | HC2: 1 | HD2: 1 | HE2: 1 | HF2: 1 | HG2: 1 | HH2: 2 | HI2: 1 | HJ2: 1 | HK2: 1 | HL2: 1 | HM2: 1 | HN2: 1 | HO2: 1 | HP2: 1 | HQ2: 1 | HR2: 1 | HS2: 1 | HT2: 1 | HU2: 1 | HV2: 1 | HW2: 1 | HX2: 1 | HY2: 1 | HZ2: 1 | IA2: 1 | IB2: 1 | IC2: 1 | ID2: 1 | IE2: 1 | IF2: 1 | IG2: 1 | IH2: 1 | II2: 1 | IJ2: 1 | IK2: 1 | IL2: 1 | IM2: 1 | IN2: 1 | IO2: 1 | IP2: 1 | IQ2: 1 | IR2: 1 | IS2: 1 | IT2: 1 | IU2: 1 | IV2: 1 | IW2: 1 | IX2: 1 | IY2: 1 | IZ2: 1 | JA2: 1 | JB2: 1 | JC2: 1 | JD2: 1 | JE2: 1 | JF2: 1 | JG2: 1 | JH2: 1 | JI2: 1 | JJ2: 2 | JK2: 1 | JL2: 1 | JM2: 1 | JN2: 1 | JO2: 1 | JP2: 1 | JQ2: 1 | JR2: 1 | JS2: 1 | JT2: 2 | JU2: 1 | JV2: 2 | JW2: 1 | JX2: 1 | JY2: 1 | JZ2: 1 | KA2: 1 | KB2: 1 | KC2: 1 | KD2: 1 | KE2: 1 | KF2: 1 | KG2: 1 | KH2: 2 | KI2: 1 | KJ2: 1 | KK2: 1 | KL2: 1 | KM2: 1 | KN2: 2 | KO2: 1 | KP2: 1 | KQ2: 1 | KR2: 1 | KS2: 1 | KT2: 1 | KU2: 1 | KV2: 1 | KW2: 1 | KX2: 1 | KY2: 1 | KZ2: 1 | LA2: 1 | LB2: 1
A3: 青岛 | B3: ABE4 | C3: ABE4 | E3: Y-A4NY | F3: 义乌 | G3: ABE4 | H3: 9.48 | I3: Y-A4NY | J3: 0 | L3: Y-718专线 | M3: 718海派 | T3: Y-A4NY | U3: Y-A4NY | V3: Y-A4NY | W3: Y-718专线 | X3: Y-A4SAV | Y3: Y-A4NY | Z3: Y-A4NY | AA3: Y-A4NY | AB3: Y-K13美中专线 | AC3: Y-A4NY | AD3: Y-718专线 | AE3: Y-K14芝加哥专线 | AF3: Y-K14芝加哥专线 | AG3: Y-K13美中专线 | AH3: Y-K13美中专线 | AI3: Y-718专线 | AJ3: Y-K13美中专线 | AK3: Y-718专线 | AL3: Y-K13美中专线 | AM3: Y-K13美中专线 | AN3: Y-K13美中专线 | AO3: Y-718专线 | AP3: Y-718专线 | AQ3: Y-718专线 | AR3: Y-718专线 | AS3: Y-A4NY | AT3: Y-718专线 | AU3: Y-718专线 | AV3: Y-A4NY | AW3: Y-A4NY | AX3: Y-A4NY | AY3: Y-A4NY | AZ3: Y-718专线 | BA3: Y-K13美中专线 | BB3: Y-K13美中专线 | BC3: Y-K13美中专线 | BD3: Y-K13美中专线 | BE3: Y-K13美中专线 | BF3: Y-A4NY | BG3: Y-718专线 | BH3: Y-718专线 | BI3: Y-奥克兰快船 | BJ3: Y-K13美中专线 | BK3: Y-A4SAV | BL3: Y-K14芝加哥专线 | BM3: Y-A4NY | BN3: Y-K14芝加哥专线 | BO3: Y-K14芝加哥专线 | BP3: Y-A4SAV | BQ3: Y-A4SAV | BR3: Y-K14芝加哥专线 | BS3: Y-718专线 | BT3: Y-A4NY | BU3: Y-718专线 | BV3: Y-718专线 | BW3: Y-718专线 | BX3: Y-A4NY | BY3: Y-A4NY | BZ3: Y-718专线 | CA3: Y-K13美中专线 | CB3: Y-718专线 | CC3: Y-718专线 | CD3: Y-奥克兰快船 | CE3: Y-A4SAV | CF3: Y-K14芝加哥专线 | CG3: Y-718专线 | CH3: Y-718专线 | CI3: Y-718专线 | CJ3: Y-A4NY | CK3: Y-K13美中专线 | CL3: Y-718专线 | CM3: Y-718专线 | CN3: Y-718专线 | CO3: Y-K13美中专线 | CP3: Y-718专线 | CQ3: Y-718专线 | CR3: Y-K14芝加哥专线 | CS3: Y-A4NY | CT3: Y-A4NY | CU3: Y-A4NY | CV3: Y-718专线 | CW3: Y-K14芝加哥专线 | CX3: Y-718专线 | CY3: Y-K13美中专线 | CZ3: Y-A4NY | DA3: Y-A4NY | DB3: Y-718专线 | DC3: Y-K14芝加哥专线 | DD3: Y-718专线 | DE3: Y-A4SAV | DF3: Y-718专线 | DG3: Y-K13美中专线 | DH3: Y-718专线 | DI3: Y-K14芝加哥专线 | DJ3: Y-718专线 | DK3: Y-A4SAV | DL3: Y-718专线 | DM3: Y-718专线 | DN3: Y-718专线 | DO3: Y-A4NY | DP3: Y-718专线 | DQ3: Y-718专线 | DR3: Y-718专线 | DS3: Y-718专线 | DT3: Y-718专线 | DU3: Y-718专线 | DV3: Y-718专线 | DW3: Y-K14芝加哥专线 | DX3: Y-718专线 | DY3: Y-A4NY | DZ3: Y-K13美中专线 | EA3: Y-K13美中专线 | EB3: Y-K13美中专线 | EC3: Y-718专线 | ED3: Y-718专线 | EE3: Y-718专线 | EF3: Y-奥克兰快船 | EG3: Y-718专线 | EH3: Y-718专线 | EI3: Y-718专线 | EJ3: Y-奥克兰快船 | EK3: Y-718专线 | EL3: Y-718专线 | EM3: Y-奥克兰快船 | EN3: Y-718专线 | EO3: Y-K14芝加哥专线 | EP3: Y-K14芝加哥专线 | EQ3: Y-A4NY | ER3: Y-718专线 | ES3: Y-718专线 | ET3: Y-718专线 | EU3: Y-A4NY | EV3: Y-A4NY | EW3: Y-A4NY | EX3: Y-718专线 | EY3: Y-K14芝加哥专线 | EZ3: Y-A4NY | FA3: Y-A4NY | FB3: Y-A4NY | FC3: Y-718专线 | FD3: Y-X1-专线(卡尔加里) | FE3: Y-A4NY | FF3: Y-A4NY | FG3: Y-A4NY | FH3: Y-718专线 | FI3: Y-A4SAV | FJ3: Y-A4SAV | FK3: Y-A4NY | FL3: Y-A4NY | FM3: Y-X1-专线(多伦多) | FN3: Y-X1-专线(温尼伯) | FO3: Y-X1-专线(多伦多) | FP3: Y-X1-专线(卡尔加里) | FQ3: Y-X1-专线(卡尔加里) | FR3: Y-X1-专线(多伦多) | FS3: Y-X1-专线(多伦多) | FT3: Y-X1-专线(多伦多) | FU3: Y-X1-专线(多伦多) | FV3: Y-X1-专线(多伦多) | FW3: Y-X1-专线(温哥华) | FX3: Y-X1-专线(温哥华) | FY3: Y-X1-专线(温哥华) | FZ3: Y-X1-专线(温哥华) | GA3: Y-X1-专线(多伦多) | GB3: Y-X1-专线(温哥华) | GC3: Y-X1-专线(卡尔加里) | GD3: Y-X1-专线(卡尔加里) | GE3: Y-X1-专线(卡尔加里) | GF3: Y-X1-专线(多伦多) | GG3: Y-X1-专线(多伦多) | GH3: Y-X1-专线(多伦多) | GI3: Y-X1-专线(多伦多) | GJ3: Y-X1-专线(多伦多) | GK3: Y-X1-专线(多伦多) | GL3: Y-718专线 | GM3: Y-X1-专线(多伦多) | GN3: Y-718海派 | GO3: Y-718海派 | GP3: Y-718海派 | GQ3: Q15纽约海卡 | GR3: Q15纽约海卡 | GS3: Q-718专线 | GT3: Q-718专线 | GU3: Q15纽约海卡 | GV3: Q15纽约海卡 | GW3: Q15纽约海卡 | GX3: Q-718专线 | GY3: Q15纽约海卡 | GZ3: Q15纽约海卡 | HA3: Q-718专线 | HB3: Q15纽约海卡 | HC3: Q15纽约海卡 | HD3: Q15纽约海卡 | HE3: Q15纽约海卡 | HF3: Q15纽约海卡 | HG3: Q15纽约海卡 | HH3: Q-718专线 | HI3: Q15纽约海卡 | HJ3: Q15纽约海卡 | HK3: Q15纽约海卡 | HL3: Q15纽约海卡 | HM3: Q-718专线 | HN3: Q-718专线 | HO3: Q-718专线 | HP3: Q-718专线 | HQ3: Q-718专线 | HR3: Q-718专线 | HS3: Q-718专线 | HT3: Q15纽约海卡 | HU3: Q-718专线 | HV3: Q-718专线 | HW3: Q15纽约海卡 | HX3: Q15纽约海卡 | HY3: Q15纽约海卡 | HZ3: Q15纽约海卡 | IA3: Q-718专线 | IB3: Q15纽约海卡 | IC3: Q-718专线 | ID3: Q-718专线 | IE3: Q15纽约海卡 | IF3: Q-718专线 | IG3: Q15纽约海卡 | IH3: Q-718专线 | II3: Q-718专线 | IJ3: Q-718专线 | IK3: Q15纽约海卡 | IL3: Q15纽约海卡 | IM3: Q-718专线 | IN3: Q-718专线 | IO3: Q-718专线 | IP3: Q-718专线 | IQ3: Q-718专线 | IR3: Q-718专线 | IS3: Q15纽约海卡 | IT3: Q-718专线 | IU3: Q-718专线 | IV3: Q-718专线 | IW3: Q-718专线 | IX3: Q-718专线 | IY3: Q15纽约海卡 | IZ3: Q15纽约海卡 | JA3: Q15纽约海卡 | JB3: Q-718专线 | JC3: Q-718专线 | JD3: Q15纽约海卡 | JE3: Q15纽约海卡 | JF3: Q-718专线 | JG3: Q-718专线 | JH3: Q-718专线 | JI3: Q-718专线 | JJ3: Q-718专线 | JK3: Q-718专线 | JL3: Q-718专线 | JM3: Q-718专线 | JN3: Q15纽约海卡 | JO3: Q-718专线 | JP3: Q-718专线 | JQ3: Q-718专线 | JR3: Q-718专线 | JS3: Q-718专线 | JT3: Q-718专线 | JU3: Q-718专线 | JV3: Q-718专线 | JW3: Q15纽约海卡 | JX3: Q-718专线 | JY3: Q-718专线 | JZ3: Q-718专线 | KA3: Q-718专线 | KB3: Q-718专线 | KC3: Q-718专线 | KD3: Q-718专线 | KE3: Q-718专线 | KF3: Q-718专线 | KG3: Q15纽约海卡 | KH3: Q-718专线 | KI3: Q-718专线 | KJ3: Q-718专线 | KK3: Q15纽约海卡 | KL3: Q15纽约海卡 | KM3: Q15纽约海卡 | KN3: Q-718专线 | KO3: Q15纽约海卡 | KP3: Q15纽约海卡 | KQ3: Q15纽约海卡 | KR3: Q-718专线 | KS3: Q15纽约海卡 | KT3: Q15纽约海卡 | KU3: Q15纽约海卡 | KV3: Q-718专线 | KW3: Q15纽约海卡 | KX3: Q15纽约海卡 | KY3: Q-718专线 | KZ3: 718海派 | LA3: 718海派 | LB3: 718海派
B4: ABE8 | C4: ABE8 | E4: Y-纽约快速达 | F4: 义乌 | G4: ABE8 | H4: 9.18 | I4: Y-A6全美直送专线 | J4: 0 | L4: Y-718海派 | M4: Q-718专线 | T4: Y-纽约快速达 | U4: Y-A4SAV | V4: Y-纽约快速达 | W4: Y-911专线 | X4: Y-K16萨瓦纳海卡 | Y4: Y-A4SAV | Z4: Y-K14芝加哥专线 | AA4: Y-K14芝加哥专线 | AC4: Y-纽约快速达 | AD4: Y-快速达 | AE4: Y-琦速达芝加哥 | AF4: Y-琦速达芝加哥 | AI4: Y-快速达 | AJ4: Y-K14芝加哥专线 | AK4: Y-911专线 | AO4: Y-911专线 | AP4: Y-奥克兰快船 | AQ4: Y-911专线 | AR4: Y-911专线 | AS4: Y-A4SAV | AT4: Y-911专线 | AU4: Y-911专线 | AV4: Y-纽约快速达 | AW4: Y-纽约快速达 | AX4: Y-纽约快速达 | AY4: Y-纽约快速达 | AZ4: Y-911专线 | BF4: Y-A4SAV | BG4: Y-911专线 | BK4: Y-K16萨瓦纳海卡 | BL4: Y-琦速达芝加哥 | BM4: Y-纽约快速达 | BP4: Y-K16萨瓦纳海卡 | BQ4: Y-K16萨瓦纳海卡 | BR4: Y-琦速达芝加哥 | BS4: Y-911专线 | BT4: Y-纽约快速达 | BV4: Y-A4-专线 | BW4: Y-911专线 | BX4: Y-A4SAV | BY4: Y-纽约快速达 | CE4: Y-K16萨瓦纳海卡 | CF4: Y-琦速达芝加哥 | CG4: Y-911专线 | CH4: Y-快速达 | CI4: Y-911专线 | CJ4: Y-纽约快速达 | CL4: Y-快速达 | CM4: Y-快速达 | CN4: Y-911专线 | CP4: Y-奥克兰快船 | CQ4: Y-奥克兰快船 | CS4: Y-A4SAV | CT4: Y-纽约快速达 | CU4: Y-纽约快速达 | CV4: Y-911专线 | CW4: Y-琦速达芝加哥 | CX4: Y-911专线 | CZ4: Y-纽约快速达 | DA4: Y-A4SAV | DB4: Y-911专线 | DC4: Y-琦速达芝加哥 | DD4: Y-911专线 | DE4: Y-K16萨瓦纳海卡 | DF4: Y-奥克兰快船 | DH4: Y-911专线 | DI4: Y-琦速达芝加哥 | DJ4: Y-911专线 | DK4: Y-K16萨瓦纳海卡 | DL4: Y-快速达 | DM4: Y-快速达 | DN4: Y-快速达 | DO4: Y-纽约快速达 | DP4: Y-911专线 | DQ4: Y-911专线 | DR4: Y-911专线 | DS4: Y-911专线 | DT4: Y-911专线 | DU4: Y-911专线 | DV4: Y-K14芝加哥专线 | DW4: Y-琦速达芝加哥 | DX4: Y-911专线 | DY4: Y-A4SAV | EC4: Y-911专线 | ED4: Y-快速达 | EE4: Y-奥克兰快船 | EG4: Y-911专线 | EH4: Y-911专线 | EI4: Y-快速达 | EK4: Y-911专线 | EL4: Y-奥克兰快船 | EN4: Y-快速达 | EO4: Y-琦速达芝加哥 | EP4: Y-琦速达芝加哥 | EQ4: Y-纽约快速达 | ER4: Y-911专线 | ES4: Y-911专线 | ET4: Y-911专线 | EU4: Y-纽约快速达 | EV4: Y-纽约快速达 | EW4: Y-纽约快速达 | EX4: Y-911专线 | EY4: Y-琦速达芝加哥 | EZ4: Y-A4SAV | FA4: Y-A4SAV | FB4: Y-纽约快速达 | FC4: Y-911专线 | FE4: Y-纽约快速达 | FF4: Y-纽约快速达 | FG4: Y-A4SAV | FH4: Y-A4-专线 | FI4: Y-K16萨瓦纳海卡 | FJ4: Y-K16萨瓦纳海卡 | FK4: Y15纽约海卡 | FL4: Y-纽约快速达 | FM4: Y-X1-多伦多海派 | FN4: Y-X3-专线 | FO4: Y-X3-专线 | FP4: Y-X3-专线 | FQ4: Y-X3-专线 | FR4: Y-X1-多伦多海派 | FS4: Y-X1-多伦多海派 | FT4: Y-X1-多伦多海派 | FU4: Y-X1-多伦多海派 | FV4: Y-X1-多伦多海派 | FW4: Y-X3-专线 | FX4: Y-X3-专线 | FY4: Y-X3-专线 | FZ4: Y-X3-专线 | GA4: Y-X1-多伦多海派 | GB4: Y-X3-专线 | GC4: Y-X3-专线 | GD4: Y-X3-专线 | GE4: Y-X3-专线 | GF4: Y-X1-多伦多海派 | GG4: Y-X1-多伦多海派 | GH4: Y-X1-多伦多海派 | GI4: Y-X1-多伦多海派 | GJ4: Y-X1-多伦多海派 | GK4: Y-X1-多伦多海派 | GL4: Y-911专线 | GM4: Y-X1-多伦多海派 | GN4: Y-911海派 | GO4: Y-911海派 | GP4: Y-911海派 | GS4: Q15纽约海卡 | GX4: Q15纽约海卡 | HH4: Q15纽约海卡 | JJ4: Q15纽约海卡 | JT4: Q15纽约海卡 | JV4: Q15纽约海卡 | KH4: Q15纽约海卡 | KN4: Q15纽约海卡
B5: ABQ2 | C5: ABQ2 | E5: Y15纽约海卡 | F5: 义乌 | G5: ABQ2 | H5: 10.58 | I5: Y-718专线 | J5: 0 | L5: Y-911专线 | M5: Q15纽约海卡 | T5: Y15纽约海卡 | U5: Y-K16萨瓦纳海卡 | V5: Y15纽约海卡 | W5: Y-A4NY | Y5: Y-K16萨瓦纳海卡 | Z5: Y-琦速达芝加哥 | AA5: Y-琦速达芝加哥 | AC5: Y15纽约海卡 | AD5: Y-琦速达 | AI5: Y-琦速达 | AJ5: Y-琦速达芝加哥 | AK5: Y-A6全美直送专线 | AO5: Y-A4-专线 | AP5: Y-快速达 | AQ5: Y-A4-专线 | AR5: Y-A4-专线 | AS5: Y-K16萨瓦纳海卡 | AT5: Y-A4-专线 | AU5: Y-A4-专线 | AV5: Y15纽约海卡 | AW5: Y15纽约海卡 | AX5: Y15纽约海卡 | AY5: Y15纽约海卡 | AZ5: Y-A4-专线 | BF5: Y-K16萨瓦纳海卡 | BG5: Y-A6全美直送专线 | BM5: Y15纽约海卡 | BS5: Y-A4-专线 | BT5: Y15纽约海卡 | BW5: Y-A4-专线 | BX5: Y-K16萨瓦纳海卡 | BY5: Y15纽约海卡 | CG5: Y-A4-专线 | CH5: Y-琦速达 | CI5: Y-A4-专线 | CJ5: Y15纽约海卡 | CL5: Y-琦速达 | CM5: Y-琦速达 | CN5: Y-A4-专线 | CP5: Y-快速达 | CQ5: Y-快速达 | CS5: Y-K16萨瓦纳海卡 | CT5: Y15纽约海卡 | CU5: Y15纽约海卡 | CV5: Y-A4-专线 | CX5: Y-A4-专线 | CZ5: Y15纽约海卡 | DA5: Y-K16萨瓦纳海卡 | DB5: Y-A4-专线 | DD5: Y-A4-专线 | DH5: Y-A4-专线 | DJ5: Y-A4NY | DL5: Y-琦速达 | DM5: Y-琦速达 | DN5: Y-琦速达 | DO5: Y15纽约海卡 | DP5: Y-A4-专线 | DQ5: Y-A4-专线 | DR5: Y-A4-专线 | DS5: Y-快速达 | DT5: Y-A4-专线 | DU5: Y-A4NY | DV5: Y-快速达 | DX5: Y-A4NY | DY5: Y-K16萨瓦纳海卡 | EC5: Y-A4-专线 | ED5: Y-琦速达 | EE5: Y-快速达 | EG5: Y-A4-专线 | EH5: Y-A4-专线 | EI5: Y-琦速达 | EK5: Y-A4-专线 | EL5: Y-快速达 | EN5: Y-琦速达 | EQ5: Y15纽约海卡 | ER5: Y-A4NY | ES5: Y-A4-专线 | ET5: Y-A4-专线 | EU5: Y15纽约海卡 | EV5: Y15纽约海卡 | EW5: Y15纽约海卡 | EX5: Y-A4NY | EZ5: Y-K16萨瓦纳海卡 | FA5: Y-K16萨瓦纳海卡 | FB5: Y15纽约海卡 | FC5: Y-A4-专线 | FE5: Y15纽约海卡 | FF5: Y15纽约海卡 | FG5: Y-K16萨瓦纳海卡 | FL5: Y15纽约海卡 | FM5: Y-X3-专线 | FN5: Y-X5-专线 | FO5: Y-X5-专线 | FP5: Y-X3-海派 | FQ5: Y-X3-海派 | FR5: Y-X3-专线 | FS5: Y-X3-专线 | FT5: Y-X3-专线 | FU5: Y-X3-专线 | FV5: Y-X3-专线 | FW5: Y-X3-海派 | FX5: Y-X3-海派 | FY5: Y-X3-海派 | FZ5: Y-X3-海派 | GA5: Y-X3-专线 | GB5: Y-X3-海派 | GC5: Y-X3-海派 | GD5: Y-X3-海派 | GE5: Y-X3-海派 | GF5: Y-X3-专线 | GG5: Y-X3-专线 | GH5: Y-X3-专线 | GI5: Y-X3-专线 | GJ5: Y-X3-专线 | GK5: Y-X3-专线 | GL5: Y-A4-专线 | GM5: Y-X3-海派 | GN5: Y-快速达海派 | GO5: Y-快速达海派 | GP5: Y-快速达海派
B6: ACY2 | C6: ACY2 | E6: Y琦速达纽约 | F6: 义乌 | G6: ACY2 | H6: 9.38 | I6: Y-A4NY | J6: 0 | L6: Y-911海派 | T6: Y琦速达纽约 | U6: Y-纽约快速达 | V6: Y琦速达纽约 | W6: Y-A4SAV | Y6: Y-纽约快速达 | Z6: Y-纽约快速达 | AA6: Y-纽约快速达 | AC6: Y琦速达纽约 | AK6: Y-K13美中专线 | AO6: Y-K14芝加哥专线 | AP6: Y-琦速达 | AQ6: Y-A6全美直送专线 | AR6: Y-A6全美直送专线 | AS6: Y-纽约快速达 | AT6: Y-A6全美直送专线 | AU6: Y-A6全美直送专线 | AV6: Y琦速达纽约 | AW6: Y琦速达纽约 | AX6: Y琦速达纽约 | AY6: Y琦速达纽约 | AZ6: Y-奥克兰快船 | BF6: Y-纽约快速达 | BG6: Y-K13美中专线 | BM6: Y琦速达纽约 | BS6: Y-A6全美直送专线 | BT6: Y琦速达纽约 | BW6: Y-A6全美直送专线 | BX6: Y-纽约快速达 | BY6: Y琦速达纽约 | CG6: Y-A6全美直送专线 | CI6: Y-A6全美直送专线 | CJ6: Y琦速达纽约 | CN6: Y-A6全美直送专线 | CP6: Y-琦速达 | CQ6: Y-琦速达 | CS6: Y-纽约快速达 | CT6: Y琦速达纽约 | CU6: Y琦速达纽约 | CV6: Y-A6全美直送专线 | CX6: Y-A4SAV | CZ6: Y琦速达纽约 | DA6: Y-纽约快速达 | DB6: Y-A6全美直送专线 | DD6: Y-K14芝加哥专线 | DH6: Y-A6全美直送专线 | DJ6: Y-快速达 | DO6: Y琦速达纽约 | DP6: Y-快速达 | DQ6: Y-快速达 | DR6: Y-A6全美直送专线 | DS6: Y-琦速达 | DT6: Y-奥克兰快船 | DU6: Y-A4SAV | DV6: Y-琦速达 | DX6: Y-快速达 | DY6: Y-纽约快速达 | EC6: Y-A6全美直送专线 | EE6: Y-琦速达 | EG6: Y-A6全美直送专线 | EH6: Y-A6全美直送专线 | EK6: Y-A6全美直送专线 | EL6: Y-琦速达 | EQ6: Y琦速达纽约 | ER6: Y-快速达 | ES6: Y-奥克兰快船 | ET6: Y-奥克兰快船 | EU6: Y琦速达纽约 | EV6: Y琦速达纽约 | EW6: Y琦速达纽约 | EX6: Y-A6全美直送专线 | EZ6: Y-纽约快速达 | FA6: Y-纽约快速达 | FB6: Y琦速达纽约 | FC6: Y-快速达 | FE6: Y琦速达纽约 | FF6: Y琦速达纽约 | FG6: Y-纽约快速达 | FL6: Y琦速达纽约 | FM6: Y-X3-海派 | FN6: Y-X7-专线 | FO6: Y-X7-专线 | FP6: Y-X5-专线 | FQ6: Y-X5-专线 | FR6: Y-X3-海派 | FS6: Y-X3-海派 | FT6: Y-X3-海派 | FU6: Y-X3-海派 | FV6: Y-X3-海派 | FW6: Y-X5-专线 | FX6: Y-X5-专线 | FY6: Y-X5-专线 | FZ6: Y-X5-专线 | GA6: Y-X3-海派 | GB6: Y-X5-专线 | GC6: Y-X5-专线 | GD6: Y-X5-专线 | GE6: Y-X5-专线 | GF6: Y-X3-海派 | GG6: Y-X3-海派 | GH6: Y-X3-海派 | GI6: Y-X3-海派 | GJ6: Y-X3-海派 | GK6: Y-X3-海派 | GL6: Y-快速达 | GM6: Y-X7-海派 | GN6: Y-琦速达海派 | GO6: Y-琦速达海派 | GP6: Y-琦速达海派
B7: AKR1 | C7: AKR1 | F7: 义乌 | G7: AKR1 | H7: 10.38 | I7: Y-A4NY | J7: 0 | L7: Y-A4-专线 | U7: Y15纽约海卡 | W7: Y-A6全美直送专线 | Y7: Y15纽约海卡 | Z7: Y15纽约海卡 | AA7: Y15纽约海卡 | AK7: Y-快速达 | AO7: Y-快速达 | AQ7: Y-快速达 | AR7: Y-快速达 | AS7: Y15纽约海卡 | AT7: Y-快速达 | AU7: Y-快速达 | AZ7: Y-快速达 | BF7: Y15纽约海卡 | BG7: Y-快速达 | BS7: Y-K14芝加哥专线 | BW7: Y-快速达 | BX7: Y15纽约海卡 | CG7: Y-快速达 | CI7: Y-SEND普船专线 | CN7: Y-快速达 | CS7: Y15纽约海卡 | CV7: Y-K14芝加哥专线 | CX7: Y-K16萨瓦纳海卡 | DA7: Y15纽约海卡 | DB7: Y-快速达 | DD7: Y-快速达 | DH7: Y-快速达 | DJ7: Y-琦速达 | DP7: Y-琦速达 | DQ7: Y-琦速达 | DR7: Y-快速达 | DT7: Y-快速达 | DU7: Y-K16萨瓦纳海卡 | DV7: Y-琦速达芝加哥 | DX7: Y-琦速达 | DY7: Y15纽约海卡 | EC7: Y-SEND普船专线 | EG7: Y-奥克兰快船 | EH7: Y-奥克兰快船 | EK7: Y-SEND普船专线 | ER7: Y-琦速达 | ES7: Y-快速达 | ET7: Y-快速达 | EX7: Y-SEND普船专线 | EZ7: Y15纽约海卡 | FA7: Y15纽约海卡 | FC7: Y-琦速达 | FG7: Y15纽约海卡 | FM7: Y-X5-专线 | FP7: Y-X7-专线 | FQ7: Y-X7-专线 | FR7: Y-X5-专线 | FS7: Y-X5-专线 | FT7: Y-X5-专线 | FU7: Y-X5-专线 | FV7: Y-X5-专线 | FW7: Y-X7-专线 | FX7: Y-X7-专线 | FY7: Y-X7-专线 | FZ7: Y-X7-专线 | GA7: Y-X5-专线 | GB7: Y-X7-专线 | GC7: Y-X7-专线 | GD7: Y-X7-专线 | GE7: Y-X7-专线 | GF7: Y-X5-专线 | GG7: Y-X5-专线 | GH7: Y-X5-专线 | GI7: Y-X5-专线 | GJ7: Y-X5-专线 | GK7: Y-X5-专线 | GL7: Y-琦速达
B8: ALB1 | C8: ALB1 | F8: 义乌 | G8: ALB1 | H8: 9.98 | I8: Y-A4NY | J8: 0 | L8: Y-A4NY | U8: Y琦速达纽约 | W8: Y-K16萨瓦纳海卡 | Y8: Y琦速达纽约 | Z8: Y琦速达纽约 | AA8: Y琦速达纽约 | AK8: Y-琦速达 | AO8: Y-琦速达 | AQ8: Y-琦速达 | AR8: Y-琦速达 | AS8: Y琦速达纽约 | AT8: Y-琦速达 | AU8: Y-琦速达 | AZ8: Y-琦速达 | BF8: Y琦速达纽约 | BG8: Y-琦速达 | BS8: Y-快速达 | BW8: Y-琦速达 | BX8: Y琦速达纽约 | CG8: Y-琦速达 | CI8: Y-快速达 | CN8: Y-琦速达 | CS8: Y琦速达纽约 | CV8: Y-快速达 | CX8: Y-快速达 | DA8: Y琦速达纽约 | DB8: Y-琦速达 | DD8: Y-琦速达 | DH8: Y-琦速达 | DJ8: Y-纽约快速达 | DR8: Y-琦速达 | DT8: Y-琦速达 | DU8: Y-快速达 | DX8: Y-纽约快速达 | DY8: Y琦速达纽约 | EC8: Y-快速达 | EG8: Y-快速达 | EH8: Y-快速达 | EK8: Y-奥克兰快船 | ER8: Y-纽约快速达 | ES8: Y-琦速达 | ET8: Y-琦速达 | EX8: Y-快速达 | EZ8: Y琦速达纽约 | FA8: Y琦速达纽约 | FG8: Y琦速达纽约 | FM8: Y-X7-专线 | FP8: Y-X7-海派 | FQ8: Y-X7-海派 | FR8: Y-X7-专线 | FS8: Y-X7-专线 | FT8: Y-X7-专线 | FU8: Y-X7-专线 | FV8: Y-X7-专线 | FW8: Y-X7-海派 | FX8: Y-X7-海派 | FY8: Y-X7-海派 | FZ8: Y-X7-海派 | GA8: Y-X7-专线 | GB8: Y-X7-海派 | GC8: Y-X7-海派 | GD8: Y-X7-海派 | GE8: Y-X7-海派 | GF8: Y-X7-专线 | GG8: Y-X7-专线 | GH8: Y-X7-专线 | GI8: Y-X7-专线 | GJ8: Y-X7-专线 | GK8: Y-X7-专线
B9: AVP1 | C9: AVP1 | F9: 义乌 | G9: AVP1 | H9: 9.68 | I9: Y-A4NY | J9: 0 | L9: Y-A4SAV | W9: Y-SEND普船专线 | AO9: Y-琦速达芝加哥 | BS9: Y-琦速达 | CI9: Y-琦速达 | CV9: Y-琦速达 | CX9: Y-琦速达 | DD9: Y-琦速达芝加哥 | DJ9: Y15纽约海卡 | DU9: Y-琦速达 | DX9: Y15纽约海卡 | EC9: Y-琦速达 | EG9: Y-琦速达 | EH9: Y-琦速达 | EK9: Y-快速达 | ER9: Y15纽约海卡 | EX9: Y-琦速达 | FM9: Y-X7-海派 | FR9: Y-X7-海派 | FS9: Y-X7-海派 | FT9: Y-X7-海派 | FU9: Y-X7-海派 | FV9: Y-X7-海派 | GA9: Y-X7-海派 | GF9: Y-X7-海派 | GG9: Y-X7-海派 | GH9: Y-X7-海派 | GI9: Y-X7-海派 | GJ9: Y-X7-海派 | GK9: Y-X7-海派
B10: AVP9 | C10: AVP9 | F10: 义乌 | G10: AVP9 | H10: 9.68 | I10: Y-A4NY | J10: 0 | L10: Y-A6全美直送专线 | W10: Y-快速达 | BS10: Y-琦速达芝加哥 | CV10: Y-琦速达芝加哥 | DJ10: Y琦速达纽约 | DU10: Y-纽约快速达 | DX10: Y琦速达纽约 | EK10: Y-琦速达 | ER10: Y琦速达纽约 | EX10: Y-纽约快速达
B11: BDL6 | C11: BDL6 | F11: 义乌 | G11: BDL6 | H11: 10.18 | I11: Y-A4NY | J11: 0 | L11: Y-K13美中专线 | W11: Y-琦速达 | DU11: Y15纽约海卡 | EX11: Y15纽约海卡
B12: BFI3 | C12: BJC1 | F12: 义乌 | G12: BFI3 | H12: 10.98 | I12: Y-奥克兰快船 | J12: 0 | L12: Y-K14芝加哥专线 | W12: Y-纽约快速达 | DU12: Y琦速达纽约 | EX12: Y琦速达纽约
B13: BJC1 | C13: BNA2 | F13: 义乌 | G13: BJC1 | H13: 11.78 | I13: Y-A4-专线 | J13: 0 | L13: Y-K16萨瓦纳海卡 | W13: Y15纽约海卡
B14: BNA2 | C14: BNA6 | F14: 义乌 | G14: BNA2 | H14: 10.28 | I14: Y-A4SAV | J14: 0 | L14: Y-SEND普船专线 | W14: Y琦速达纽约
B15: BNA6 | C15: BOS7 | F15: 义乌 | G15: BNA6 | H15: 10.28 | I15: Y-A4SAV | J15: 0 | L15: Y-X1-专线(卡尔加里)
B16: BOS7 | C16: BWI4 | F16: 义乌 | G16: BOS7 | H16: 10.18 | I16: Y-A4NY | J16: 0 | L16: Y-X1-专线(多伦多)
B17: BWI4 | C17: CHA2 | F17: 义乌 | G17: BWI4 | H17: 10.18 | I17: Y-A4NY | J17: 0 | L17: Y-X1-专线(温哥华)
B18: CHA2 | C18: CHO1 | F18: 义乌 | G18: CHA2 | H18: 10.48 | I18: Y-A4SAV | J18: 0 | L18: Y-X1-专线(温尼伯)
B19: CHO1 | C19: CLT2 | F19: 义乌 | G19: CHO1 | H19: 10.18 | I19: Y-A4NY | J19: 0 | L19: Y-X1-多伦多海派
B20: CLT2 | C20: CLT6 | F20: 义乌 | G20: CLT2 | H20: 9.48 | I20: Y-SEND普船专线 | J20: 0 | L20: Y-X3-专线
B21: CLT3 | C21: CMH2 | F21: 义乌 | G21: CLT3 | H21: 9.88 | I21: Y-A4SAV | J21: 0 | L21: Y-X3-海派
B22: CLT6 | C22: CMH3 | F22: 义乌 | G22: CLT6 | H22: 9.88 | I22: Y-A4SAV | J22: 0 | L22: Y-X5-专线
B23: CMH2 | C23: DCA6 | F23: 义乌 | G23: CMH2 | H23: 10.58 | I23: Y-A4NY | J23: 0 | L23: Y-X7-专线
B24: CMH3 | C24: DEN8 | F24: 义乌 | G24: CMH3 | H24: 10.58 | I24: Y-A4NY | J24: 0 | L24: Y-X7-海派
B25: DAL3 | C25: FAT2 | F25: 义乌 | G25: DAL3 | H25: 10.18 | I25: Y-K13美中专线 | J25: 0 | L25: Y-奥克兰快船
B26: DCA6 | C26: FTW1 | F26: 义乌 | G26: DCA6 | H26: 9.88 | I26: Y-A4NY | J26: 0 | L26: Y-快速达
... B33: FOE1 | C33: GYR3 | F33: 义乌 | G33: FOE1 | H33: 11.18 | I33: Y-K13美中专线 | J33: 0 | L33: Y琦速达纽约
B34: FTW1 | C34: HEA2 | F34: 义乌 | G34: FTW1 | H34: 9.68 | I34: Y-A6全美直送专线 | J34: 0
B35: FTW2 | C35: HGR2 | F35: 义乌 | G35: FTW2 | H35: 10.18 | I35: Y-K13美中专线 | J35: 0
B36: FTW5 | C36: HGR6 | F36: 义乌 | G36: FTW5 | H36: 10.08 | I36: Y-K13美中专线 | J36: 0
B37: FTW9 | C37: HIA1 | F37: 义乌 | G37: FTW9 | H37: 10.18 | I37: Y-K13美中专线 | J37: 0
B38: FWA4 | C38: HLI2 | F38: 义乌 | G38: FWA4 | H38: 10.78 | I38: Y-K14芝加哥专线 | J38: 0
B39: GEG2 | C39: HSV1 | F39: 义乌 | G39: GEG2 | H39: 10.88 | I39: Y-奥克兰快船 | J39: 0
B40: GEU2 | C40: IAH3 | F40: 义乌 | G40: GEU2 | H40: 9.08 | I40: Y-A4-专线 | J40: 0
B41: GEU3 | C41: IAZ1 | F41: 义乌 | G41: GEU3 | H41: 9.08 | I41: Y-A4-专线 | J41: 0
B42: GSO1 | C42: ILG1 | F42: 义乌 | G42: GSO1 | H42: 9.88 | I42: Y-A4SAV | J42: 0
B43: GYR2 | C43: IND9 | F43: 义乌 | G43: GYR2 | H43: 9.08 | I43: Y-A4-专线 | J43: 0
B44: GYR3 | C44: IPA1 | F44: 义乌 | G44: GYR3 | H44: 9.08 | I44: Y-A4-专线 | J44: 0
B45: HEA2 | C45: ITX3 | F45: 义乌 | G45: HEA2 | H45: 9.58 | I45: Y-A4NY | J45: 0
... B117: POC1 | C117: 美国西岸北（邮编97.98.99开头） | F117: 义乌 | G117: POC1 | H117: 8.48 | I117: Y-A4-专线 | J117: 0
B118: POC2 | F118: 义乌 | G118: POC2 | H118: 8.28 | I118: Y-A4-专线 | J118: 0
B119: POC3 | F119: 义乌 | G119: POC3 | H119: 8.28 | I119: Y-A4-专线 | J119: 0
B120: PSP3 | F120: 义乌 | G120: PSP3 | H120: 9.08 | I120: Y-718专线 | J120: 0
B121: QXY8 | F121: 义乌 | G121: QXY8 | H121: 9.18 | I121: Y-奥克兰快船 | J121: 0
B122: RDU2 | F122: 义乌 | G122: RDU2 | H122: 9.88 | I122: Y-A4SAV | J122: 0
B123: RFD2 | F123: 义乌 | G123: RFD2 | H123: 10.18 | I123: Y-K14芝加哥专线 | J123: 0
B124: RFD4 | F124: 义乌 | G124: RFD4 | H124: 10.28 | I124: Y-K14芝加哥专线 | J124: 0
B125: RMN3 | F125: 义乌 | G125: RMN3 | H125: 10.18 | I125: Y-A4NY | J125: 0
B126: RYY2 | F126: 义乌 | G126: RYY2 | H126: 9.88 | I126: Y-A4SAV | J126: 0
B127: SAT1 | F127: 义乌 | G127: SAT1 | H127: 10.08 | I127: Y-K13美中专线 | J127: 0
B128: SAT4 | F128: 义乌 | G128: SAT4 | H128: 10.18 | I128: Y-K13美中专线 | J128: 0
B129: SAT6 | F129: 义乌 | G129: SAT6 | H129: 10.08 | I129: Y-K13美中专线 | J129: 0
... B195: 美国西岸北（邮编97.98.99开头） | F195: 义乌 | G195: 美国西岸北（邮编97.98.99开头） | H195: 13.18 | I195: Y-718海派 | J195: 0
F196: 青岛 | G196: ABE3 | H196: 9.68 | I196: Q15纽约海卡 | J196: 0
F197: 青岛 | G197: ABE4 | H197: 9.68 | I197: Q15纽约海卡 | J197: 0
F198: 青岛 | G198: ABE8 | H198: 9.58 | I198: Q15纽约海卡 | J198: 0
F199: 青岛 | G199: ABQ2 | H199: 10.58 | I199: Q-718专线 | J199: 0
F200: 青岛 | G200: ACY2 | H200: 9.58 | I200: Q15纽约海卡 | J200: 0
F201: 青岛 | G201: AKR1 | H201: 10.58 | I201: Q15纽约海卡 | J201: 0
F202: 青岛 | G202: ALB1 | H202: 10.18 | I202: Q15纽约海卡 | J202: 0
F203: 青岛 | G203: AVP1 | H203: 9.88 | I203: Q15纽约海卡 | J203: 0
F204: 青岛 | G204: AVP9 | H204: 9.88 | I204: Q15纽约海卡 | J204: 0
F205: 青岛 | G205: BDL6 | H205: 10.38 | I205: Q15纽约海卡 | J205: 0
F206: 青岛 | G206: BJC1 | H206: 12.38 | I206: Q-718专线 | J206: 0
F207: 青岛 | G207: BNA2 | H207: 11.08 | I207: Q15纽约海卡 | J207: 0
... F311: 青岛 | G311: 美国西岸北（邮编97.98.99开头） | H311: 13.18 | I311: 718海派 | J311: 0

Sheet 箱规
A1: 产品尺寸（英寸） | B1: 长(CM) | C1: 宽(CM) | D1: 产品面积 | E1: 单件长(CM) | F1: 单件宽(CM) | G1: 单件高(CM) | H1: 单件体积 | I1: 装箱数（件） | J1: 外箱长(CM) | K1: 外箱宽(CM) | L1: 外箱高(CM) | M1: 一箱体积 | N1: 单件产品净重（KG） | O1: 总产品净重（KG） | P1: 外箱重（KG） | Q1: 一箱净重（KG） | R1: 一箱毛重（KG） | S1: 备注 | U1: 说明：完整箱规数据。采购成本对比表的「尺寸」下拉与自动填充引用本表。
A2: 2'3' | B2: 61 | C2: 91 | D2: 0.56 | E2: 23 | F2: 22 | G2: 5 | H2: 0.0025 | I2: 16 | J2: 48 | K2: 48 | L2: 29 | M2: 0.067 | N2: 0.64 | O2: 10.24 | P2: 1.2 | Q2: 10.24 | R2: 11.44
A3: 2'5' | B3: 61 | C3: 152 | D3: 0.93 | E3: 26 | F3: 22 | G3: 10 | H3: 0.0057 | I3: 16 | J3: 48 | K3: 44 | L3: 48 | M3: 0.101 | N3: 1.28 | O3: 20.48 | P3: 1.2 | Q3: 20.48 | R3: 21.68 | S3: 新
A4: 2'6' | B4: 61 | C4: 183 | D4: 1.12 | E4: 24 | F4: 23 | G4: 14 | H4: 0.0077 | I4: 14 | J4: 48 | K4: 44 | L4: 48 | M4: 0.101 | N4: 1.28 | O4: 17.92 | P4: 1.2 | Q4: 17.92 | R4: 19.12
A5: 2'8' | B5: 61 | C5: 244 | D5: 1.49 | E5: 26 | F5: 25 | G5: 14 | H5: 0.0091 | I5: 10 | J5: 48 | K5: 44 | L5: 48 | M5: 0.101 | N5: 1.71 | O5: 17.1 | P5: 1.2 | Q5: 17.1 | R5: 18.3
A6: 2'10' | B6: 61 | C6: 305 | D6: 1.86 | E6: 27 | F6: 24 | G6: 16 | H6: 0.0104 | I6: 9 | J6: 48 | K6: 44 | L6: 48 | M6: 0.101 | N6: 2.1 | O6: 18.9 | P6: 1.2 | Q6: 18.9 | R6: 20.1
A7: 3'5' | B7: 91 | C7: 152 | D7: 1.38 | E7: 27 | F7: 26 | G7: 13 | H7: 0.0091 | I7: 11 | J7: 48 | K7: 44 | L7: 48 | M7: 0.101 | N7: 1.59 | O7: 17.49 | P7: 1.2 | Q7: 17.49 | R7: 18.69
A8: 4'6' | B8: 122 | C8: 183 | D8: 2.23 | E8: 36 | F8: 27 | G8: 12 | H8: 0.0143 | I8: 7 | J8: 55 | K8: 35 | L8: 50 | M8: 0.096 | N8: 2.75 | O8: 17.99 | P8: 1 | Q8: 17.99 | R8: 18.99
A9: 5'7' | B9: 152 | C9: 213 | D9: 3.24 | E9: 39 | F9: 30 | G9: 16 | H9: 0.0187 | I9: 4 | J9: 40 | K9: 34 | L9: 52.5 | M9: 0.074 | N9: 3.72 | O9: 14.88 | P9: 1 | Q9: 14.88 | R9: 15.88
A10: 5'8' | B10: 152 | C10: 244 | D10: 3.71 | E10: 41 | F10: 32 | G10: 18 | H10: 0.0236 | I10: 4 | J10: 43 | K10: 36 | L10: 60 | M10: 0.093 | N10: 3.8 | O10: 15.2 | P10: 1.2 | Q10: 15.2 | R10: 16.4
A11: 6'9' | B11: 183 | C11: 274 | D11: 5.01 | E11: 40 | F11: 36 | G11: 19 | H11: 0.0274 | I11: 3 | J11: 60 | K11: 41 | L11: 41 | M11: 0.101 | N11: 5.77 | O11: 17.31 | P11: 1.3 | Q11: 17.31 | R11: 18.61
A12: 7'9' | B12: 213 | C12: 274 | D12: 5.84 | E12: 45 | F12: 41 | G12: 20 | H12: 0.0369 | I12: 2 | J12: 46 | K12: 42 | L12: 46 | M12: 0.089 | N12: 6.91 | O12: 13.82 | P12: 1.1 | Q12: 13.82 | R12: 14.93
A13: 8'10' | B13: 244 | C13: 305 | D13: 7.44 | E13: 44 | F13: 40 | G13: 23 | H13: 0.0405 | I13: 2 | J13: 48 | K13: 44 | L13: 48 | M13: 0.101 | N13: 8.56 | O13: 17.12 | P13: 1.2 | Q13: 17.12 | R13: 18.32
A14: 9'12' | B14: 274 | C14: 366 | D14: 10.03 | E14: 49 | F14: 39 | G14: 32 | H14: 0.0612 | I14: 1 | J14: 49 | K14: 39 | L14: 32 | M14: 0.061 | N14: 11.53 | O14: 11.53 | P14: 1 | Q14: 11.53 | R14: 12.53
A15: Φ4' | B15: 122 | C15: 122 | D15: 1.13 | E15: 24 | F15: 22 | G15: 13 | H15: 0.0069 | I15: 12 | J15: 48 | K15: 44 | L15: 48 | M15: 0.101 | N15: 1.3 | O15: 15.6 | P15: 1.2 | Q15: 15.6 | R15: 16.8
... A19: 8'8' | B19: 244 | C19: 244 | D19: 5.95 | E19: 43 | F19: 43 | G19: 22 | H19: 0.0407 | I19: 2 | J19: 48 | K19: 44 | L19: 48 | M19: 0.101 | N19: 6.8 | O19: 13.6 | P19: 1.2 | Q19: 13.6 | R19: 14.8
A20: Φ3.15' | B20: 96 | C20: 96 | E20: 24 | F20: 22 | G20: 13 | I20: 20 | J20: 48 | K20: 44 | L20: 48 | N20: 0.86 | O20: 17.2 | P20: 1.4 | Q20: 17.2 | R20: 18.6 | S20: 新
A21: Φ3.4' | B21: 103.6 | C21: 103.6 | E21: 24 | F21: 22 | G21: 13 | I21: 18 | J21: 48 | K21: 44 | L21: 48 | N21: 1 | O21: 18 | P21: 1.4 | Q21: 18 | R21: 19.4 | S21: 新
A22: Φ5' | B22: 152 | C22: 152 | E22: 34 | F22: 40 | G22: 9 | I22: 7 | J22: 40 | K22: 34 | L22: 52.5 | N22: 2.14 | O22: 14.98 | P22: 1.2 | Q22: 14.98 | R22: 16.8 | S22: 新
A23: 2.6*8 | B23: 81 | C23: 244 | E23: 41 | F23: 33 | G23: 9 | I23: 8 | J23: 44 | K23: 33 | L23: 48 | N23: 2.36 | O23: 18.88 | P23: 1.1 | Q23: 18.88 | R23: 19.98
B24: 91 | C24: 244 | E24: 43 | F24: 25 | G24: 12 | I24: 7 | J24: 48 | K24: 44 | L24: 48 | N24: 2.7 | O24: 18.9 | P24: 1.2 | Q24: 18.9 | R24: 20.1

Sheet 定价规则说明
A1: 地毯加拿大定价规则 → 已并入方式（防重复计算）
A3: 原规则字段 | B3: 本表对应 | C3: 处理方式
A4: 平米（长宽） | B4: 仅箱规维护（主表R/S/T已清空隐藏） | C4: 勿再使用主表产品长/宽/平米列
A5: 采购=平米×单价 | B5: 单价固定19元/㎡（参数!B15） | C5: V=箱规面积×19；X=V/汇率
A6: 物流RMB | B6: 头程运费(RMB) | C6: 沿用原列，不另加「物流」避免重复
A7: FBA配送费 | B7: 见「FBA规则」+ 主表R/S/T/AB | C7: 计费重→分段→费用；尺寸来自箱规单件长宽高
A8: 佣金/广告/退货 | B8: 佣金率/广告率/退款率 | C8: 沿用，不平行复制
A9: 仓储费2% | B9: 仓储费率+仓储费 | C9: 新增并入总成本
A10: 优惠券 | B10: 优惠券(USD) | C10: 新增并入总成本
A11: 引流行/盈利行 | B11: 保本状态 / 销售状态 | C11: 用两套售价列表达，不复制整行
A14: 海运报价关联
A15: 凯琦月更报价 | B15: 海运报价（中间表） | C15: 不直接引用凯琦多Sheet原文件；每月覆盖更新中间表数字，主表公式不变
A16: 陆运 | B16: 陆运运费(BL)手填 | C16: 与海运分开，避免混算
A17: 头程合计 | B17: AA = 海运运费 + 陆运运费 | C17: 已接入保本/销售总成本
A19: 宏更新（推荐）
A20: RefreshOceanFreight | B20: 读取凯琦FBA报价_当期.xlsx | C20: 自动重建「海运报价」；主表公式不变。见 宏更新说明.txt / 更新海运报价.bas
A22: 可变值与汇率
A23: 竞品售价 / 保本售价 / 利润售价 | B23: F / G / H（手填 USD） | C23: 保本块用G，销售块用H；竞品F仅对照
A24: 佣金/退款/广告/提现 | B24: 默认 15% / 7% / 15% / 1% | C24: 写在 I–L，可按行改
A25: 汇率 | B25: 参数!B2（USD→CNY） | C25: 主表 M 列公式引用；更新汇率.py 每日刷新
A27: 自动售价（两套）
A28: 保本售价 | B28: ROUNDUP((采购USD+头程USD+FBA+优惠券+中转-退税)/(1-费率合计),2) | C28: 保证利润(含退税)≥0
A29: 利润售价 | B29: ROUND(同上分子/(1-费率合计-目标利润率),2) | C29: 默认目标利润率30%
A30: 必填 | B30: 尺寸 + 起运地 + FBA仓 | C30: 渠道可选；空则MIN海运单价
A31: 海运计价规则
A32: 渠道为空 | B32: 海运下拉!最低单价（随起运地+FBA仓变） | C32: 改仓库后保本/利润售价自动变
A33: 渠道已填 | B33: 海运报价精确匹配 渠道+起运地+仓 | C33: 不匹配则单价空白并提示
A34: 按件分摊
A35: 采购 | B35: 单件面积×19（本来就是一件）
A36: 头程运费 | B36: 单箱计费重×单价 → 单箱运费 ÷ 装数 = 一件头程
A37: FBA | B37: 按单件净重(kg)计算，不再用整箱毛重
A38: FBA计算步骤
A39: 1.抓取 | B39: 箱规：单件长/宽/高(cm)、单件净重(kg)
A40: 2.计费重 | B40: 实重lb=kg×2.2046；抛重=(L×W×H inch)/139；计费重=MAX(实重,抛重)
A41: 3.尺寸段 | B41: 小标准/大标准/大件/超大（看边长与长+围长是否超限）
A42: 4.费用 | B42: 按分段与计费重查FBA规则表（2025美站非旺季估算）
A43: FBA旺季判断
A44: 发货/出库日 | B44: 参数!B22（可改） | C44: 按货件离开运营中心日期估算
A45: 旺季窗口 | B45: 每年 10/15–次年 1/14 | C45: 参数!B23 自动显示旺季/非旺季
A46: 费率 | B46: FBA规则表：绿=非旺季，橙=旺季 | C46: AB/AQ 按季节自动引用

Sheet 利润表
A1: 利润表（桥接页·按表头从「全尺寸利润/参数/采购成本对比」取值）
A2: 选用尺寸（改这里，下面指标跟着变） | B2: 2'3'
A3: 说明：旧模板单元格位置保留（F15/H14/P14/S14/T14/U15/X15/I15），内容用INDEX+MATCH按表头跳转。
A5: 桥接映射（表头）
A6: 旧单元格 | B6: 含义 | C6: 新来源表头/位置
A7: F15 | B7: 货=采购成本RMB/件 | C7: 全尺寸利润!采购RMB/件
A8: H14 | B8: 头程物流RMB/件 | C8: 全尺寸利润!头程RMB/件
A9: P14 | B9: 广告费USD/件 | C9: 20%售价 × 采购成本对比!广告率
A10: S14 | B10: 退款费USD/件 | C10: 20%售价 × 退款率
A11: T14 | B11: 佣金USD/件 | C11: 采购成本对比!AG4（保本侧仓储费率；勿用AV重复列）
A12: U15 | B12: 20%利润售价USD | C12: 按成本反推目标利润率20%
A13: X15 | B13: 汇率 | C13: 参数!B2 | H13: 头程RMB/件 | P13: 广告USD/件 | S13: 退款USD/件 | T13: 佣金USD/件
A14: I15 | B14: 单件综合成本RMB | C14: 采购RMB+头程RMB+FBA×汇率 | E14: 采购USD/件 | F14: 采购RMB/件 | G14: FBA USD/件 | H14: =INDEX(全尺寸利润!$K$4:$K$50,MATCH($B$2,全尺寸利润!$A$4:$A$50,0)) | I14: 单件综合成本RMB | K14: 费率合计 | L14: 目标利润率(本页U15) | P14: =IF(U15="","",U15*采购成本对比!K4) | S14: =IF(U15="","",U15*采购成本对比!J4) | T14: =IF(U15="","",U15*采购成本对比!I4) | U14: 20%利润售价USD | V14: 30%利润售价(全尺寸利润) | X14: 汇率
E15: =INDEX(全尺寸利润!$J$4:$J$50,MATCH($B$2,全尺寸利润!$A$4:$A$50,0)) | F15: =INDEX(全尺寸利润!$I$4:$I$50,MATCH($B$2,全尺寸利润!$A$4:$A$50,0)) | G15: =INDEX(全尺寸利润!$L$4:$L$50,MATCH($B$2,全尺寸利润!$A$4:$A$50,0)) | I15: =F15+H14+G15*X15 | K15: =采购成本对比!I4+采购成本对比!J4+采购成本对比!K4+采购成本对比!L4+采购成本对比!AG4 | L15: 0.2 | U15: =IF(OR(E15="",X15="",K15=""),"",ROUND((E15+H14/X15+G15-0.13*E15/1.13)/(1-K15-L15),2)) | V15: =INDEX(全尺寸利润!$P$4:$P$50,MATCH($B$2,全尺寸利润!$A$4:$A$50,0)) | X15: =参数!$B$2
A16: 选用尺寸的全尺寸利润行号 | B16: =MATCH($B$2,全尺寸利润!$A$4:$A$50,0)

Sheet 经营规划
A1: 目标达成预期收益
A2: 日销量 | B2: 20%利润售价 | C2: 月销量 | D2: 月销售额 | E2: 年销售额 | F2: 人民币
A3: 2000 | B3: ='利润表'!U15 | C3: =A3*30 | D3: =C3*B3 | E3: =D3*12 | F3: ='利润表'!X15*E3
A4: （参考） | B4: 来自利润表·按尺寸 | C4: =C3/8 | D4: 月销量口径2→ | E4: C4=月销量/8
A6: 阶段划分
A7: 时间 | B7: 今年跑通 | C7: 年份 | D7: 新款式 | E7: 首批 | F7: 定位 | G7: 策略
A8: 阶段 | B8: 28年1K | C8: 传统 | D8: 新款式 | E8: 2 | F8: 新款式 | G8: 做利润
B9: 29年2K | D9: 低价 | E9: 3 | F9: 低价 | G9: 流速
A11: 需要准备
A12: 账号/店铺公司 | B12: 商标 | C12: 人员 | D12: 备注
A13: 3 | B13: 1 | C13: 2个运营 | D13: 还没找到第二个
A15: 投入金额
A16: 项目 | B16: 判断标准 | C16: 获取时间 | D16: 成本 | E16: 风险准备金 | F16: 合计 | G16: 备注
A17: 第一笔 | B17: 启动 | C17: 启动 | D17: =SUM(D33:D41) | E17: 0 | F17: =D17+E17 | G17: 可以正常启动，进入循环
A18: 第二笔 | B18: 月销1000+件 | C18: 到货后1个月 / 启动后3个月 | D18: =F33 | E18: =C28*('利润表'!P14+'利润表'!T14+'利润表'!S14)*'利润表'!X15 | F18: =D18+E18 | G18: 货
A19: 启动后6个月自负盈亏
A21: 盈利预估
A22: 阶段 | B22: 利润率 | C22: 月销量 | D22: 月收益 | E22: 回本周期(月)
A23: 启动6-10个月 | B23: 0.15 | C23: 3000 | D23: ='利润表'!U15*B23*C23 | E23: =IF(D23=0,"",F17/D23)
A24: 启动10个月后 | B24: 0.15 | C24: 5000 | D24: ='利润表'!U15*B24*C24
A26: 订单计划
A27: 项目 | B27: 说明 | C27: 数量(件) | D27: 公式/备注
A28: 首单 | B28: 1个月量 | C28: =200+400+400 | D28: 启动备货
A29: 第一个月结束 | B29: 备3个月库存 | C29: =C28*3 | D29: 避免断货
A30: 返单 | B30: 二个月销量 | C30: 24000 | D30: 可按实际月销调整
A31: 费用计算
A32: 费用项 | B32: 单次/月标准 | C32: 数量口径 | D32: 3个月合计 | F32: 因不能断货提前备货
A33: 货 | B33: ='利润表'!F15*C28 | C33: =C28 | D33: =B33 | F33: ='利润表'!I15*C29
A34: 头程物流 | B34: ='利润表'!H14*C28 | C34: =C28 | D34: =B34
A35: 广告(含佣金/退款口径) | B35: =('利润表'!P14+'利润表'!T14+'利润表'!S14)*C28*'利润表'!X15 | C35: =C28 | D35: =B35
A36: 人工 | B36: 20000 | C36: 每月 | D36: =B36*3
A37: 账号 | B37: =300+68+30 | C37: 每月 | D37: =B37*3
A38: 场地 | B38: 5000 | C38: 每月 | D38: =B38*3
A39: 设计 | B39: 1000 | C39: 每个产品 | D39: =B39*(E8+E9)
A40: A+ | B40: 3000 | C40: 每链接 | D40: =B40*(E8+E9)
A41: 视频 | B41: 1000 | C41: 每链接 | D41: =B41*(E8+E9)
A43: 跨页说明：本页引用「利润表」固定单元格；利润表再用表头 INDEX/MATCH 跳到「全尺寸利润」「参数」「采购成本对比」。改「利润表!B2」尺寸后，售价/采购/头程/FBA/经营规划费用会一起变。
